Workbook

Sheet S00_Index
A1: S00 — WORKBOOK INDEX — Greenfield Expansion Phase II · CapEx & Supply Chain Portfolio Model
A2: Prepared by: Sourabh Tarodekar | Contact: sourabh232@gmail.com | Purpose: Portfolio demonstration of Engineering Program Management – CapEx & Supply Chain Operations
A4: This workbook contains synthetic sample data created for portfolio demonstration purposes only. The data does not represent proprietary or confidential information from any employer or client.
A6: ZONE LEGEND — TAB COLOR GUIDE
A7: Zone | B7: Color | C7: Category | D7: Purpose
A8: Zone 0 | B8: Gray | C8: Navigation & Governance | D8: Index, Disclaimer & Assumptions, version control
A9: Zone 1 | B9: Blue | C9: Program Foundation | D9: Equipment portfolio, supplier data, should-cost, TCO
A10: Zone 2 | B10: Green | C10: Planning & Scheduling | D10: WBS, CPM, Milestone Roadmap, deployment, capacity, demand forecast
A11: Zone 3 | B11: Orange | C11: Financial & Risk | D11: AR, cash flow, FX, scenario analysis, supply chain risk
A12: Zone 4 | B12: Purple | C12: Strategic Supply Chain | D12: Market analysis, network, sourcing, dual-source, negotiation, inventory, assets
A13: Zone 5 | B13: Red | C13: Execution & Control | D13: Gates, ECO, VDC, yield metrics, ROI tracker, scorecard, change tracker
A14: Zone 6 | B14: Teal | C14: Portfolio & Capital Allocation | D14: Multi-program register, portfolio dashboard, prioritization scorecard
A16: SHEET DIRECTORY
A17: Sheet # | B17: Sheet Name (click to navigate) | C17: Zone | D17: Status | E17: What This Sheet Demonstrates | F17: Key Metrics / Outputs
A18: S00 | B18: S00_Index | C18: Zone 0 | D18: New | E18: Workbook navigation, zone guide, sheet directory | F18: This page
A19: S01 | B19: S01_Disclaimer_Assumptions | C19: Zone 0 | D19: Revised | E19: Portfolio disclaimer, global model assumptions, version control | F19: WACC=8%, Uptime=92%, FX rates, version log
A20: S02 | B20: S02_Equipment_Portfolio | C20: Zone 1 | D20: Revised | E20: Master equipment dataset for 2 programs (PRG-001, PRG-002) — costs, energy, throughput | F20: $13.87M + $2.38M CapEx across 21 platforms
A21: S03 | B21: S03_Supplier_Dataset | C21: Zone 1 | D21: Revised | E21: Supplier lead times, reliability scores, risk tiers across both programs | F21: 21 OEMs; Program ID column for portfolio rollups
A22: S04 | B22: S04_Should_Cost_Model | C22: Zone 1 | D22: Preserved | E22: First-principles should-cost by material, labour, OH, margin | F22: Should-cost vs quote variance analysis
A23: S05 | B23: S05_TCO_Downtime_Model | C23: Zone 1 | D23: Preserved | E23: 10-year TCO, energy, maintenance, downtime cost comparison | F23: NPV-based lifecycle cost comparison
A24: S06 | B24: S06_WBS | C24: Zone 2 | D24: New | E24: Work Breakdown Structure — all program workstreams and tasks | F24: 8 workstreams, 60+ work packages
A25: S07 | B25: S07_CPM_Master_Schedule | C25: Zone 2 | D25: New | E25: Critical Path Method schedule — activities, float, predecessors | F25: Critical path = 46 weeks; 39 activities
A26: S08 | B26: S08_Program_Milestone_Roadmap | C26: Zone 2 | D26: New | E26: Visual Gantt-style program roadmap — recruiter-friendly view | F26: G0 to G5 gates, Apr-2025 to Dec-2025
A27: S09 | B27: S09_Deployment_Timeline | C27: Zone 2 | D27: Revised | E27: Equipment-level deployment schedule by workstream | F27: 46-week program; 6 critical-path items
A28: S10 | B28: S10_Capacity_Planning | C28: Zone 2 | D28: Revised | E28: Equipment capacity model — throughput, utilization, bottleneck ID | F28: 1,040K units/yr capacity; 72.1% utilization
... A53: S35 | B53: S35_Portfolio_Prioritization | C53: Zone 6 | D53: New | E53: Weighted capital allocation scorecard — ranks programs for sequencing | F53: Greenfield #1 (4.25/5.0), Riverside #2 (3.15/5.0)

Sheet S34_Portfolio_Dashboard
A1: S34 — PORTFOLIO EXECUTIVE DASHBOARD — ALL PROGRAMS
A2: Portfolio Director: Sourabh Tarodekar · Aggregates every active/proposed program in S33_Portfolio_Register · All values linked live
A4: PORTFOLIO KEY PERFORMANCE INDICATORS
A5: ACTIVE + PROPOSED PROGRAMS | C5: TOTAL PORTFOLIO CAPEX | E5: TOTAL APPROVED/EST. BUDGET | G5: BLENDED SUPPLY CHAIN RISK | I5: TOTAL EQUIPMENT PLATFORMS
A6: ='S33_Portfolio_Register'!B10 | C6: ='S33_Portfolio_Register'!B11 | E6: ='S33_Portfolio_Register'!B12 | G6: ='S33_Portfolio_Register'!B13 | I6: ='S33_Portfolio_Register'!B14
A7: S33 — Portfolio Register | C7: Sum across all programs | E7: Incl. contingency + reserves | G7: Avg across all programs | I7: All programs combined
A9: PROGRAM-BY-PROGRAM COMPARISON
A10: Program | B10: Phase / Status | C10: CapEx (USD) | D10: % of Portfolio CapEx | E10: Approved/Est. Budget (USD) | F10: IRR | G10: Risk Score | H10: Equipment Platforms | I10: Payback (yrs)
A11: ='S33_Portfolio_Register'!B5 | B11: ='S33_Portfolio_Register'!G5 | C11: ='S33_Portfolio_Register'!H5 | D11: =C11/'S33_Portfolio_Register'!B11 | E11: ='S33_Portfolio_Register'!J5 | F11: ='S33_Portfolio_Register'!K5 | G11: ='S33_Portfolio_Register'!N5 | H11: ='S33_Portfolio_Register'!O5 | I11: ='S33_Portfolio_Register'!M5
A12: ='S33_Portfolio_Register'!B6 | B12: ='S33_Portfolio_Register'!G6 | C12: ='S33_Portfolio_Register'!H6 | D12: =C12/'S33_Portfolio_Register'!B11 | E12: ='S33_Portfolio_Register'!J6 | F12: ='S33_Portfolio_Register'!K6 | G12: ='S33_Portfolio_Register'!N6 | H12: ='S33_Portfolio_Register'!O6 | I12: ='S33_Portfolio_Register'!M6
A13: PORTFOLIO TOTAL | C13: =SUM(C11:C12) | D13: 1 | E13: =SUM(E11:E12) | G13: =AVERAGE(G11:G12) | H13: =SUM(H11:H12)
A15: PORTFOLIO NOTES
A16: PRG-001 (Greenfield Expansion Phase II) is fully approved and in execution — every figure above is live-linked to its 33-sheet model (S00-S32). PRG-002 (Riverside Automation Upgrade Phase I) is at FEL-2 (feasibility); its equipment, supplier, and risk data are live-linked to S02/S03/S16, but its IRR/NPV/payback are Finance's FEL-2 planning estimates pending a full TCO build-out ahead of AR submission. See S35_Portfolio_Prioritization for the capital allocation decision framework across both programs.

Sheet S33_Portfolio_Register
A1: S33 — Portfolio Register — All Active & Proposed CapEx Programs
A2: Portfolio Director: Sourabh Tarodekar | One row per program; financial and risk fields link live to each program's own data sheets (S02, S03, S16) where a supporting model exists | Program ID is the join key used across S33-S35
A4: Program ID | B4: Program Name | C4: Sponsor | D4: Program Manager | E4: Business Unit | F4: Phase / Gate | G4: Status | H4: Total CapEx — Equip+Install (USD) | I4: Contingency Reserve (USD) | J4: Total Approved Budget (USD) | K4: Estimated IRR | L4: 10-Yr NPV (USD) | M4: Payback (yrs) | N4: Avg Supply Chain Risk Score | O4: Equipment Platforms | P4: Strategic Capacity Impact | Q4: Notes
A5: PRG-001 | B5: Greenfield Expansion Phase II | C5: Sourabh Tarodekar (Portfolio Director) | D5: Sourabh Tarodekar | E5: Semiconductor & Advanced Process Division | F5: G2 — Equipment Build & FAT (Execution) | G5: APPROVED — IN EXECUTION | H5: ='S02_Equipment_Portfolio'!B25 | I5: ='S12_AR_Summary'!F24 | J5: ='S12_AR_Summary'!F27 | K5: ='S12_AR_Summary'!B34 | L5: ='S12_AR_Summary'!B33 | M5: 4.2 | N5: ='S16_Supply_Chain_Risk'!B36 | O5: ='S02_Equipment_Portfolio'!B27 | P5: +312,000 units/yr (35% customer volume increase) | Q5: Full 33-sheet model (S00-S32); financials, schedule, and risk fully linked
A6: PRG-002 | B6: Riverside Automation Upgrade Phase I | C6: Sourabh Tarodekar (Portfolio Director) | D6: Elena Vargas | E6: Packaging & Distribution Operations | F6: FEL-2 — Feasibility (Pre-Execution) | G6: PROPOSED — AWAITING AR APPROVAL | H6: ='S02_Equipment_Portfolio'!I40+'S02_Equipment_Portfolio'!K40 | I6: =H6*0.10 | J6: =H6+I6+42000.0+95000.0 | K6: 0.168 | L6: 1850000 | M6: 3.1 | N6: ='S16_Supply_Chain_Risk'!B53 | O6: =COUNTA('S02_Equipment_Portfolio'!A34:'S02_Equipment_Portfolio'!A39) | P6: +18% packaging line throughput (~45,000 cases/day incremental) | Q6: Equipment/supplier/risk data live-linked (S02, S03, S16); IRR/NPV/payback are Finance FEL-2 estimates, not yet a full 10-yr TCO model
A9: PORTFOLIO TOTALS
A10: Active + Proposed Programs | B10: =COUNTA(A5:A6)
A11: Total Portfolio CapEx (USD) | B11: =SUM(H5:H6)
A12: Total Portfolio Approved/Estimated Budget (USD) | B12: =SUM(J5:J6)
A13: Blended Avg Supply Chain Risk Score | B13: =AVERAGE(N5:N6)
A14: Total Equipment Platforms (All Programs) | B14: =SUM(O5:O6)

Sheet S35_Portfolio_Prioritization
A1: S35 — Portfolio Prioritization — Capital Allocation Decision Framework
A2: Portfolio Director: Sourabh Tarodekar | Weighted scorecard used to rank active + proposed programs each planning cycle | Same weighting methodology as S13_Scenario_Analysis, applied program-vs-program instead of scenario-vs-scenario
A4: SCORING DIMENSION WEIGHTS & RATIONALE
A5: Dimension | B5: Weight | C5: PRG-001 Score (1-5) | D5: PRG-002 Score (1-5) | E5: Wtd PRG-001 | F5: Wtd PRG-002 | G5: Rationale
A6: Financial Return (NPV / IRR) | B6: 0.25 | C6: 5 | D6: 3 | E6: =B6*C6 | F6: =B6*D6 | G6: Greenfield's $9.5M NPV and 14.2% IRR dwarf Riverside's $1.85M/16.8% in absolute terms
A7: Strategic Fit / Business Priority | B7: 0.2 | C7: 5 | D7: 3 | E7: =B7*C7 | F7: =B7*D7 | G7: Greenfield is core capacity for the primary revenue driver; Riverside is an efficiency play
A8: Supply Chain / Execution Risk (higher score = lower risk) | B8: 0.15 | C8: 3 | D8: 4 | E8: =B8*C8 | F8: =B8*D8 | G8: Greenfield carries a HIGH-tier single-source pump risk; Riverside's risk profile is materially lighter
A9: Schedule Readiness / Time to Value | B9: 0.15 | C9: 4 | D9: 2 | E9: =B9*C9 | F9: =B9*D9 | G9: Greenfield is already at G2 execution; Riverside is still FEL-2, pre-AR
A10: Capital Efficiency (impact per $ requested) | B10: 0.15 | C10: 3 | D10: 4 | E10: =B10*C10 | F10: =B10*D10 | G10: Riverside's smaller ask and 3.1-yr payback are more capital-efficient than Greenfield's $16M ask
A11: Organizational Readiness | B11: 0.1 | C11: 5 | D11: 3 | E11: =B11*C11 | F11: =B11*D11 | G11: Greenfield has a dedicated, established program team; Riverside's PM and team are still standing up
A12: TOTAL WEIGHTED SCORE | B12: =SUM(B6:B11) | E12: =SUM(E6:E11) | F12: =SUM(F6:F11)
A14: RECOMMENDED SEQUENCING
A15: #1 Ranked Program | B15: =IF(E12>=F12,"PRG-001 — Greenfield Expansion Phase II","PRG-002 — Riverside Automation Upgrade Phase I")
A16: #1 Weighted Score | B16: =MAX(E12,F12)
A18: DECISION SUMMARY
A19: Greenfield Expansion Phase II ranks #1 (4.25/5.0) and remains the portfolio's priority commitment — it is already AR-approved and in execution, and no action changes that. Riverside Automation Upgrade Phase I ranks #2 (3.15/5.0): recommend continuing FEL-2 feasibility work and targeting AR submission once Greenfield's peak capital draw (Q3-2025, per S14_CashFlow_Model) has passed, so the two programs' spend curves don't compete for the same capital window. Riverside's lower risk profile and faster payback make it an attractive next-in-queue candidate once schedule and organizational readiness catch up to Greenfield's.

Sheet S01_Disclaimer_Assumptions
A1: S01 — Disclaimer & Global Model Assumptions
A2: Program: Greenfield Expansion Phase II | All hardcoded inputs are in BLUE — update here ONLY. All other sheets link to this sheet.
A4: This workbook contains synthetic sample data created for portfolio demonstration purposes only. The data does not represent proprietary or confidential information from any employer or client. Prepared by Sourabh Tarodekar for demonstration of Engineering Program Management – CapEx & Supply Chain Operations capabilities. Contact: sourabh232@gmail.com
A6: ENERGY & UTILITIES
A7: Parameter | B7: Value | C7: Unit | D7: Source / Basis | E7: Date Validated | F7: Notes
A8: Energy Price – Electricity | B8: 0.11 | C8: USD/kWh | D8: EIA Industrial Rate Survey – US Avg 2024 | E8: 2025-01 | F8: Used in Annual Energy Cost calculations across S02, S05 TCO model
A9: Natural Gas Price | B9: 4.8 | C9: USD/MMBtu | D9: EIA Natural Gas Industrial Price – 2024 | E9: 2025-01 | F9: Used for high-temp furnace operating cost estimation
A10: Cooling Water Cost | B10: 0.018 | C10: USD/gallon | D10: Site Utility Rate Schedule Rev C | E10: 2025-01 | F10: Applicable to chiller and process cooling loads
A11: N2 Bulk Gas Cost | B11: 0.045 | C11: USD/scf | D11: Site Utility Rate Schedule Rev C | E11: 2025-01 | F11: Applicable to gas handling system operating cost
A13: FINANCIAL & DISCOUNT ASSUMPTIONS
A14: Parameter | B14: Value | C14: Unit | D14: Source / Basis | E14: Date Validated | F14: Notes
A15: Discount Rate (WACC) | B15: 0.08 | C15: — | D15: Finance Department; WACC model approved Q4-2024 | E15: 2025-01 | F15: Used in NPV calculations; 8% reflects blended cost of capital
A16: Project Horizon | B16: 10 | C16: Years | D16: Standard CapEx lifecycle policy | E16: 2025-01 | F16: All TCO and NPV models use 10-year horizon
A17: Tax Rate (Effective) | B17: 0.21 | C17: — | D17: US Federal + State blended estimate | E17: 2025-01 | F17: Applied in AR payback model for after-tax IRR
A18: CapEx Depreciation Method | B18: MACRS 7-yr | C18: — | D18: Finance / Tax Counsel guidance | E18: 2025-01 | F18: Per AR Summary financial justification
A19: Inflation Rate | B19: 0.025 | C19: — | D19: Corporate finance planning assumption | E19: 2025-01 | F19: Used to escalate Year 2-10 OpEx in TCO model
A21: LABOR RATES
A22: Parameter | B22: Value | C22: Unit | D22: Source / Basis | E22: Date Validated | F22: Notes
A23: Fabrication Shop Rate | B23: 95 | C23: USD/hr | D23: Supplier benchmarking; 2024 MW industrial rate | E23: 2025-01 | F23: Used in Should-Cost labor model (S04)
A24: Engineering Labor Rate | B24: 120 | C24: USD/hr | D24: Internal engineering rate card Rev 2024 | E24: 2025-01 | F24: Used in NRE and program labor estimates
A25: Installation Labor Rate | B25: 85 | C25: USD/hr | D25: Facilities contractor rate card | E25: 2025-01 | F25: Used in on-site installation cost estimates
A26: Field Service Rate (Supplier) | B26: 175 | C26: USD/hr | D26: Supplier FSE rate benchmark | E26: 2025-01 | F26: Used in downtime / MTTR cost modelling
A28: EQUIPMENT PERFORMANCE
A29: Parameter | B29: Value | C29: Unit | D29: Source / Basis | E29: Date Validated | F29: Notes
A30: Equipment Uptime Target | B30: 0.92 | C30: — | D30: Program engineering specification | E30: 2025-01 | F30: 92% uptime = 608 downtime hrs/yr basis for MTBF model
A31: Planned Maintenance Downtime | B31: 0.04 | C31: — | D31: Maintenance planning schedule | E31: 2025-01 | F31: 4% of annual hours allocated to preventive maintenance
A32: Process Yield Assumption | B32: 0.96 | C32: — | D32: Engineering process spec | E32: 2025-01 | F32: Used in capacity model to calculate effective throughput
A33: Production Value per Hour | B33: 4500 | C33: USD/hr | D33: Finance — fully-loaded production cost model | E33: 2025-01 | F33: Downtime Cost = Value/hr × MTTR hrs
A35: SUPPLIER COST MODEL INPUTS
A36: Parameter | B36: Value | C36: Unit | D36: Source / Basis | E36: Date Validated | F36: Notes
A37: Supplier Margin – Low | B37: 0.15 | C37: — | D37: Benchmarking; competitive-bid suppliers | E37: 2025-01 | F37: Lower bound; applied to multi-source components
A38: Supplier Margin – High | B38: 0.25 | C38: — | D38: Benchmarking; sole-source suppliers | E38: 2025-01 | F38: Upper bound; applied to single-source components
A39: Material Scrap Factor – Low | B39: 0.05 | C39: — | D39: Engineering; precision machined parts | E39: 2025-01 | F39: 5% scrap on raw material purchases
A40: Material Scrap Factor – High | B40: 0.08 | C40: — | D40: Engineering; cast / welded assemblies | E40: 2025-01 | F40: 8% scrap on complex fabrications
A41: Material Price – Steel (304 SS) | B41: 3.8 | C41: USD/kg | D41: Metal bulletin Q1-2025 | E41: 2025-01 | F41: Used in vacuum chamber and furnace body cost estimates
A42: Material Price – Aluminum | B42: 4.2 | C42: USD/kg | D42: Metal bulletin Q1-2025 | E42: 2025-01 | F42: Used in robotics frame and structural components
A43: Material Price – Copper | B43: 9.5 | C43: USD/kg | D43: COMEX spot Q1-2025 | E43: 2025-01 | F43: Used in transformer winding and electrical bus cost estimates
A45: DEPLOYMENT TIMELINE ASSUMPTIONS
A46: Parameter | B46: Value | C46: Unit | D46: Source / Basis | E46: Date Validated | F46: Notes
A47: Supplier Manufacturing Duration | B47: 20 | C47: Weeks | D47: Program schedule baseline Rev 1.0 | E47: 2025-01 | F47: Range: 16–24 wks depending on equipment complexity
A48: Factory Acceptance Testing (FAT) | B48: 2 | C48: Weeks | D48: Standard FAT protocol – all equipment | E48: 2025-01 | F48: 2 weeks minimum; may extend for complex systems
A49: International Shipping Duration | B49: 3 | C49: Weeks | D49: Freight forwarder estimate; ocean freight | E49: 2025-01 | F49: Air freight contingency +50% cost; used for risk scenario
A50: On-Site Installation | B50: 4 | C50: Weeks | D50: Facilities project plan Rev A | E50: 2025-01 | F50: Per equipment platform; parallel installation possible
A51: Utility Hookup | B51: 2 | C51: Weeks | D51: Facilities electrical + mechanical schedule | E51: 2025-01 | F51: Includes inspection and commissioning sign-off
A52: Process Qualification (PQ) | B52: 5 | C52: Weeks | D52: Process engineering qualification plan | E52: 2025-01 | F52: Range: 4–6 wks; 5 wks used as baseline
A54: FX SENSITIVITY ASSUMPTIONS
A55: Parameter | B55: Value | C55: Unit | D55: Source / Basis | E55: Date Validated | F55: Notes
A56: USD/EUR Exchange Rate (Baseline) | B56: 1.09 | C56: USD per EUR | D56: Bloomberg rates Q1-2025 average | E56: 2025-01 | F56: Baseline conversion rate for EUR-denominated equipment
A57: USD/JPY Exchange Rate (Baseline) | B57: 149.5 | C57: JPY per USD | D57: Bloomberg rates Q1-2025 average | E57: 2025-01 | F57: Baseline conversion rate for JPY-denominated equipment
A58: EUR Sensitivity – Adverse | B58: 1.15 | C58: USD per EUR | D58: FX stress scenario +6% | E58: 2025-01 | F58: 1% move in EUR/USD = ~$85K portfolio cost impact
A59: EUR Sensitivity – Favorable | B59: 1.03 | C59: USD per EUR | D59: FX stress scenario -6% | E59: 2025-01 | F59: Favorable scenario used in S13 Scenario Analysis
A60: JPY Sensitivity – Adverse | B60: 142 | C60: JPY per USD | D60: FX stress scenario (JPY strengthens) | E60: 2025-01 | F60: Stronger JPY = higher USD cost for JPY equipment
A61: JPY Sensitivity – Favorable | B61: 157 | C61: JPY per USD | D61: FX stress scenario (JPY weakens) | E61: 2025-01 | F61: Weaker JPY = lower USD cost for JPY equipment
A63: VERSION CONTROL LOG — Model Revision History & Change Tracking
A64: Version | B64: Date | C64: Owner / Author | D64: Change Description | E64: Impact on Model | F64: Approval Status | G64: Notes / Reference
A65: V1.0 | B65: 2025-02-10 | C65: Sourabh Tarodekar (TPM) | D65: Initial workbook created. Equipment portfolio dataset populated with 15 platforms from supplier quotes. | E65: Baseline established. All formulas reference V1.0 assumptions. | F65: APPROVED | G65: Baseline model — AR-2025-0082 submission basis
A66: V1.1 | B66: 2025-02-14 | C66: S. Kim (Supply Chain) | D66: Updated Pfeiffer vacuum pump (EQ-002) lead time from 16 to 26 weeks based on supplier confirmation. | E66: Deployment timeline extended. EQ-002 now on critical path. Risk flag updated to CRITICAL. | F66: APPROVED | G66: Supplier email confirmation 2025-02-13 on file
A67: V1.2 | B67: 2025-02-18 | C67: R. Patel (Finance) | D67: Discount rate updated from 7.5% to 8.0% per Q1-2025 corporate WACC guidance. | E67: NPV reduced by ~$420K. TCO model and scenario analysis recalculated. | F67: APPROVED | G67: Finance guidance memo FIN-2025-007
A68: V1.3 | B68: 2025-02-24 | C68: T. Okonkwo (Facilities) | D68: Added EQ-004 crane hire and floor reinforcement to installation cost — +$62K. | E68: Total installation cost increased. CR-001 raised. Change tracker updated. | F68: APPROVED | G68: CR-001 approved by PM 2025-02-24
A69: V1.4 | B69: 2025-03-05 | C69: M. Chen (Process Eng.) | D69: Equipment uptime revised from 90% to 92% following process engineering specification review. | E69: Annual capacity increased. Utilization % reduced. Capacity model updated. | F69: APPROVED | G69: Process spec document PE-2025-014 Rev A
A70: V1.5 | B70: 2025-03-10 | C70: R. Patel (Finance) | D70: FX sensitivity assumptions added. EUR/JPY baseline and stress scenarios populated. | E70: FX exposure model now active. EUR/USD baseline 1.09, JPY/USD baseline 149.5. | F70: APPROVED | G70: Bloomberg rates Q1-2025 average
A71: V1.6 | B71: 2025-03-17 | C71: S. Kim (Supply Chain) | D71: Supplier risk scores recalculated after Daifuku confirmed 30-week manufacturing lead time for EQ-006. | E71: EQ-006 risk tier escalated to CRITICAL. Supply chain risk index increased. | F71: APPROVED | G71: Daifuku PO confirmation email
A72: V1.7 | B72: 2025-03-19 | C72: Sourabh Tarodekar (TPM) | D72: AR Summary populated and submitted to VP Engineering + CFO. Budget: $40.04M (Scenario B benchmark). | E72: Formal program approval process initiated. Model frozen for AR submission. | F72: APPROVED | G72: AR-2025-0082 submitted to Finance
A73: V1.8 | B73: 2025-04-05 | C73: R. Patel (Finance) | D73: AR approved. POs placed for long-lead items. Spend tracking model activated. | E73: Program execution phase begins. Cash flow schedule now active. | F73: APPROVED | G73: CFO approval email 2025-04-05
A74: V1.9 | B74: 2025-05-12 | C74: P. Singh (IT/OT) | D74: IT/OT DMZ infrastructure cost ($45K) added to scope. CR-009 raised. | E74: Contingency draw of $45K. Change tracker updated. Contingency at 5.8%. | F74: UNDER REVIEW | G74: CR-009 pending PM approval
A75: V2.0 | B75: 2025-05-19 | C75: Sourabh Tarodekar (TPM) | D75: Version 2.0 release: Cash flow schedule, FX exposure model, and ROI tracker sheets added. | E75: Workbook extended with 4 new analytical sheets. Full model refresh completed. | F75: APPROVED | G75: Issued to Finance and Engineering Leadership

Sheet S02_Equipment_Portfolio
A1: S02 — CapEx Equipment Portfolio Dataset — Advanced Manufacturing Program
A2: Fiscal Year: 2025 | Portfolio Director: Sourabh Tarodekar | Status: Active | Blue = Hardcoded Input · Black = Formula · Green = Cross-sheet Link | Program ID column (right-most) enables portfolio-wide SUMIFS rollups in S33-S35
A4: Equip. ID | B4: Category | C4: Tool Type / Model | D4: Supplier | E4: Region | F4: Ccy | G4: Unit Cost (USD) | H4: Qty | I4: Total Equip. Cost (USD) | J4: Install Cost/Unit (USD) | K4: Install Total (USD) | L4: Life (yrs) | M4: Energy (kWh/hr) | N4: Annual Maint. Rate (%) | O4: Throughput (u/hr) | P4: Op Hrs/Yr | Q4: Annual Energy Cost (USD) | R4: Engineering Notes | S4: Program ID
A5: EQ-001 | B5: Vacuum Pump System | C5: Dry Screw Vacuum Pump – 250 m³/hr | D5: Edwards Vacuum | E5: UK | F5: EUR | G5: 185000 | H5: 4 | I5: =G5*H5 | J5: 22000 | K5: =J5*H5 | L5: 12 | M5: 18.5 | N5: 0.06 | O5: 0 | P5: 8320 | Q5: =M5*P5*'S01_Disclaimer_Assumptions'!$B$8 | R5: Requires N2 purge line; facility electrical upgrade needed prior to installation | S5: PRG-001
A6: EQ-002 | B6: Vacuum Pump System | C6: Turbomolecular Pump Assembly – 2000 L/s | D6: Pfeiffer Vacuum | E6: DE | F6: EUR | G6: 310000 | H6: 3 | I6: =G6*H6 | J6: 28000 | K6: =J6*H6 | L6: 10 | M6: 12 | N6: 0.05 | O6: 0 | P6: 8320 | Q6: =M6*P6*'S01_Disclaimer_Assumptions'!$B$8 | R6: Single-source supplier; no qualified alt vendor as of Q1-2025; lead time under review | S6: PRG-001
A7: EQ-003 | B7: High-Temp Furnace | C7: Tube Furnace System – 1200°C / 8-zone | D7: Thermco Systems | E7: USA | F7: USD | G7: 520000 | H7: 2 | I7: =G7*H7 | J7: 45000 | K7: =J7*H7 | L7: 15 | M7: 95 | N7: 0.04 | O7: 24 | P7: 8320 | Q7: =M7*P7*'S01_Disclaimer_Assumptions'!$B$8 | R7: FAT to be conducted at supplier site in Austin, TX; includes process recipe transfer | S7: PRG-001
A8: EQ-004 | B8: High-Temp Furnace | C8: Batch Oxidation Furnace – 1100°C | D8: Tokyo Electron Ltd | E8: JP | F8: JPY | G8: 680000 | H8: 2 | I8: =G8*H8 | J8: 52000 | K8: =J8*H8 | L8: 15 | M8: 110 | N8: 0.045 | O8: 18 | P8: 8320 | Q8: =M8*P8*'S01_Disclaimer_Assumptions'!$B$8 | R8: JPY-denominated; FX hedge required; import duty ~3.2%; installation requires crane lift | S8: PRG-001
A9: EQ-005 | B9: Robotics / Automation | C9: 6-Axis Wafer Transfer Robot – SCARA | D9: Brooks Automation | E9: USA | F9: USD | G9: 275000 | H9: 6 | I9: =G9*H9 | J9: 18000 | K9: =J9*H9 | L9: 10 | M9: 4.2 | N9: 0.05 | O9: 120 | P9: 8320 | Q9: =M9*P9*'S01_Disclaimer_Assumptions'!$B$8 | R9: Software integration with fab MES required; vendor to supply integration team on-site | S9: PRG-001
A10: EQ-006 | B10: Robotics / Automation | C10: Overhead Track Conveyor – 50m loop | D10: Daifuku | E10: JP | F10: JPY | G10: 420000 | H10: 1 | I10: =G10*H10 | J10: 85000 | K10: =J10*H10 | L10: 12 | M10: 22 | N10: 0.04 | O10: 0 | P10: 8320 | Q10: =M10*P10*'S01_Disclaimer_Assumptions'!$B$8 | R10: Single installation; civil works for track mounts included in install cost estimate | S10: PRG-001
A11: EQ-007 | B11: Gas Handling System | C11: Process Gas Cabinet – 6-zone manifold | D11: Air Liquide Engineering | E11: FR | F11: EUR | G11: 195000 | H11: 4 | I11: =G11*H11 | J11: 32000 | K11: =J11*H11 | L11: 12 | M11: 0.8 | N11: 0.06 | O11: 0 | P11: 8320 | Q11: =M11*P11*'S01_Disclaimer_Assumptions'!$B$8 | R11: Hazmat classified; requires local regulatory permit; supplier quote under negotiation | S11: PRG-001
A12: EQ-008 | B12: Gas Handling System | C12: Bulk Gas Storage & Delivery – N2/O2/Ar | D12: Linde Engineering | E12: DE | F12: EUR | G12: 340000 | H12: 1 | I12: =G12*H12 | J12: 120000 | K12: =J12*H12 | L12: 20 | M12: 2.5 | N12: 0.03 | O12: 0 | P12: 8320 | Q12: =M12*P12*'S01_Disclaimer_Assumptions'!$B$8 | R12: Facility infrastructure tie-in; utility coordination required with site civil team | S12: PRG-001
A13: EQ-009 | B13: PLC Control System | C13: Distributed Control System – Siemens S7-1500 | D13: Siemens AG | E13: DE | F13: EUR | G13: 165000 | H13: 5 | I13: =G13*H13 | J13: 15000 | K13: =J13*H13 | L13: 10 | M13: 1.2 | N13: 0.07 | O13: 0 | P13: 8320 | Q13: =M13*P13*'S01_Disclaimer_Assumptions'!$B$8 | R13: Software license included; annual subscription renewal at $12K/system; cybersecurity review pending | S13: PRG-001
A14: EQ-010 | B14: PLC Control System | C14: SCADA Integration Platform – Ignition | D14: Inductive Automation | E14: USA | F14: USD | G14: 85000 | H14: 3 | I14: =G14*H14 | J14: 8000 | K14: =J14*H14 | L14: 8 | M14: 0.5 | N14: 0.08 | O14: 0 | P14: 8320 | Q14: =M14*P14*'S01_Disclaimer_Assumptions'!$B$8 | R14: Server hardware separate line item; IT/OT network segmentation required by InfoSec | S14: PRG-001
A15: EQ-011 | B15: Facility Infra – Power | C15: Dry-Type Transformer – 2 MVA / 480V | D15: ABB Ltd | E15: CH | F15: USD | G15: 210000 | H15: 2 | I15: =G15*H15 | J15: 35000 | K15: =J15*H15 | L15: 25 | M15: 0 | N15: 0.02 | O15: 0 | P15: 8760 | Q15: =M15*P15*'S01_Disclaimer_Assumptions'!$B$8 | R15: Component reused from prior program (legacy); refurbishment cost included in install | S15: PRG-001
A16: EQ-012 | B16: Facility Infra – Cooling | C16: Process Chiller System – 200 kW | D16: Daikin Applied | E16: JP | F16: JPY | G16: 295000 | H16: 3 | I16: =G16*H16 | J16: 40000 | K16: =J16*H16 | L16: 15 | M16: 68 | N16: 0.05 | O16: 0 | P16: 8760 | Q16: =M16*P16*'S01_Disclaimer_Assumptions'!$B$8 | R16: Glycol loop design pending; coordinate with mechanical engineering; JPY FX risk noted | S16: PRG-001
... A19: EQ-015 | B19: Robotics / Automation | C19: AMR Fleet – Autonomous Mobile Robots (×10) | D19: Mobile Industrial Robots (MiR) | E19: DK | F19: EUR | G19: 380000 | H19: 1 | I19: =G19*H19 | J19: 45000 | K19: =J19*H19 | L19: 8 | M19: 6 | N19: 0.06 | O19: 0 | P19: 8320 | Q19: =M19*P19*'S01_Disclaimer_Assumptions'!$B$8 | R19: Fleet management software license included; Wi-Fi infrastructure upgrade required | S19: PRG-001
A20: PRG-001 TOTAL — Greenfield Expansion Phase II | H20: =SUM(H5:H19) | I20: =SUM(I5:I19) | K20: =SUM(K5:K19) | Q20: =SUM(Q5:Q19)
A22: PRG-001 SUMMARY STATISTICS — Greenfield Expansion Phase II
A23: Total Equipment Purchase Cost (USD) | B23: =I20
A24: Total Installation Cost (USD) | B24: =K20
A25: Total Portfolio CapEx (USD) | B25: =B23+B24
A26: Total Annual Energy Cost (USD) | B26: =Q20
A27: Number of Equipment Platforms | B27: =COUNTA(A5:A19)
A28: Total Equipment Units | B28: =H20
A29: Average Unit Cost (USD) | B29: =AVERAGE(G5:G19)
A30: Highest Unit Cost Item (USD) | B30: =MAX(G5:G19)
A32: PRG-002 EQUIPMENT — Riverside Automation Upgrade Phase I
A33: Equip. ID | B33: Category | C33: Tool Type / Model | D33: Supplier | E33: Region | F33: Ccy | G33: Unit Cost (USD) | H33: Qty | I33: Total Equip. Cost (USD) | J33: Install Cost/Unit (USD) | K33: Install Total (USD) | L33: Life (yrs) | M33: Energy (kWh/hr) | N33: Annual Maint. Rate (%) | O33: Throughput (u/hr) | P33: Op Hrs/Yr | Q33: Annual Energy Cost (USD) | R33: Engineering Notes | S33: Program ID
A34: RV-001 | B34: Robotics / Automation | C34: Palletizing Robot – 6-Axis, 40kg payload | D34: Fanuc America | E34: USA | F34: USD | G34: 165000 | H34: 2 | I34: =G34*H34 | J34: 20000 | K34: =J34*H34 | L34: 10 | M34: 3.8 | N34: 0.05 | O34: 0 | P34: 6240 | Q34: =M34*P34*'S01_Disclaimer_Assumptions'!$B$8 | R34: Replaces manual end-of-line palletizing; guarding and safety scanner included in install | S34: PRG-002
A35: RV-002 | B35: Packaging Automation | C35: Case Packer / Cartoning System | D35: Krones AG | E35: DE | F35: EUR | G35: 410000 | H35: 1 | I35: =G35*H35 | J35: 55000 | K35: =J35*H35 | L35: 12 | M35: 14 | N35: 0.05 | O35: 0 | P35: 6240 | Q35: =M35*P35*'S01_Disclaimer_Assumptions'!$B$8 | R35: Single-source specialized cartoning technology; no qualified alt vendor identified | S35: PRG-002
A36: RV-003 | B36: Robotics / Automation | C36: AGV Fleet – Tow/Unit Load (×6) | D36: Fetch Robotics | E36: USA | F36: USD | G36: 85000 | H36: 6 | I36: =G36*H36 | J36: 8000 | K36: =J36*H36 | L36: 8 | M36: 1.1 | N36: 0.06 | O36: 0 | P36: 6240 | Q36: =M36*P36*'S01_Disclaimer_Assumptions'!$B$8 | R36: Fleet management software license included; warehouse Wi-Fi survey required pre-deployment | S36: PRG-002
A37: RV-004 | B37: Quality / Automation | C37: Vision Inspection System (×3) | D37: Cognex Corporation | E37: USA | F37: USD | G37: 62000 | H37: 3 | I37: =G37*H37 | J37: 6000 | K37: =J37*H37 | L37: 8 | M37: 0.6 | N37: 0.04 | O37: 0 | P37: 6240 | Q37: =M37*P37*'S01_Disclaimer_Assumptions'!$B$8 | R37: In-line case/label inspection; integrates with existing MES via OPC-UA | S37: PRG-002
A38: RV-005 | B38: PLC Control System | C38: Warehouse Control System Integration | D38: Rockwell Automation | E38: USA | F38: USD | G38: 145000 | H38: 1 | I38: =G38*H38 | J38: 25000 | K38: =J38*H38 | L38: 10 | M38: 1 | N38: 0.06 | O38: 0 | P38: 6240 | Q38: =M38*P38*'S01_Disclaimer_Assumptions'!$B$8 | R38: Integrates AGV fleet, conveyor, and WMS; software license + 1yr support included | S38: PRG-002
A39: RV-006 | B39: Material Handling | C39: Conveyor & Sortation System | D39: Dematic Corp | E39: USA | F39: USD | G39: 520000 | H39: 1 | I39: =G39*H39 | J39: 95000 | K39: =J39*H39 | L39: 15 | M39: 26 | N39: 0.04 | O39: 0 | P39: 6240 | Q39: =M39*P39*'S01_Disclaimer_Assumptions'!$B$8 | R39: Longest lead item; civil floor anchoring required; phased cutover to avoid line downtime | S39: PRG-002
A40: PRG-002 TOTAL — Riverside Automation Upgrade Phase I | H40: =SUM(H34:H39) | I40: =SUM(I34:I39) | K40: =SUM(K34:K39) | Q40: =SUM(Q34:Q39)

Sheet S03_Supplier_Dataset
A1: S03 — Supplier & Supply Chain Dataset — Advanced Manufacturing CapEx Program
A2: Last Updated: 2025-Q3 | Owner: Supply Chain / Sourcing Team | Risk Score = (Current LT ÷ Standard LT) × (100 − Reliability Score) | Risk Tier: LOW < 5 | MODERATE 5–15 | HIGH > 15 | Program ID column enables portfolio-wide rollups
A4: Supplier | B4: Component Type | C4: Equip. Ref | D4: Region | E4: Ccy | F4: Std LT (wks) | G4: Current LT (wks) | H4: LT Delta (wks) | I4: Reliability (0-100) | J4: Single Source Risk | K4: Alt Supplier Available | L4: Calc. Risk Score | M4: Risk Tier | N4: Engineering Notes | O4: Program ID
A5: Edwards Vacuum | B5: Dry Screw Vacuum Pumps | C5: EQ-001 | D5: UK | E5: EUR | F5: 14 | G5: 18 | H5: =G5-F5 | I5: 82 | J5: No | K5: Yes | L5: =ROUND((G5/F5)*(100-I5),2) | M5: =IF(L5>15,"HIGH",IF(L5>=5,"MODERATE","LOW")) | N5: Reliability impacted by post-Brexit logistics; alt vendor pre-qual in progress with Busch | O5: PRG-001
A6: Pfeiffer Vacuum | B6: Turbomolecular Pumps | C6: EQ-002 | D6: DE | E6: EUR | F6: 16 | G6: 26 | H6: =G6-F6 | I6: 88 | J6: Yes | K6: No | L6: =ROUND((G6/F6)*(100-I6),2) | M6: =IF(L6>15,"HIGH",IF(L6>=5,"MODERATE","LOW")) | N6: CRITICAL – single source; no qualified alternative; EQ-002 delivery risk HIGH; escalate to program director | O6: PRG-001
A7: Thermco Systems | B7: High-Temp Tube Furnaces | C7: EQ-003 | D7: USA | E7: USD | F7: 18 | G7: 20 | H7: =G7-F7 | I7: 91 | J7: No | K7: Yes | L7: =ROUND((G7/F7)*(100-I7),2) | M7: =IF(L7>15,"HIGH",IF(L7>=5,"MODERATE","LOW")) | N7: Preferred supplier; strong historical performance; alt supplier (BTU International) pre-qualified | O7: PRG-001
A8: Tokyo Electron Ltd (TEL) | B8: Batch Oxidation Furnaces | C8: EQ-004 | D8: JP | E8: JPY | F8: 20 | G8: 28 | H8: =G8-F8 | I8: 85 | J8: No | K8: Yes | L8: =ROUND((G8/F8)*(100-I8),2) | M8: =IF(L8>15,"HIGH",IF(L8>=5,"MODERATE","LOW")) | N8: JPY currency risk; FX hedge executed Q4-2024; alt: Kokusai Electric pre-qualified | O8: PRG-001
A9: Brooks Automation | B9: Wafer Transfer Robots (SCARA) | C9: EQ-005 | D9: USA | E9: USD | F9: 12 | G9: 14 | H9: =G9-F9 | I9: 90 | J9: No | K9: Yes | L9: =ROUND((G9/F9)*(100-I9),2) | M9: =IF(L9>15,"HIGH",IF(L9>=5,"MODERATE","LOW")) | N9: Software integration complexity is primary risk; not supply risk; support SLA confirmed | O9: PRG-001
A10: Daifuku | B10: Overhead Conveyor Track System | C10: EQ-006 | D10: JP | E10: JPY | F10: 22 | G10: 30 | H10: =G10-F10 | I10: 83 | J10: Yes | K10: No | L10: =ROUND((G10/F10)*(100-I10),2) | M10: =IF(L10>15,"HIGH",IF(L10>=5,"MODERATE","LOW")) | N10: Single source for overhead track design; civil interface drawings required 8 wks prior to FAT | O10: PRG-001
A11: Air Liquide Engineering | B11: Process Gas Cabinets | C11: EQ-007 | D11: FR | E11: EUR | F11: 16 | G11: 22 | H11: =G11-F11 | I11: 79 | J11: No | K11: Yes | L11: =ROUND((G11/F11)*(100-I11),2) | M11: =IF(L11>15,"HIGH",IF(L11>=5,"MODERATE","LOW")) | N11: Quote under negotiation; delivery risk moderate; Matheson Gas alt supplier evaluated | O11: PRG-001
A12: Linde Engineering | B12: Bulk Gas Storage & Delivery | C12: EQ-008 | D12: DE | E12: EUR | F12: 24 | G12: 32 | H12: =G12-F12 | I12: 86 | J12: No | K12: Yes | L12: =ROUND((G12/F12)*(100-I12),2) | M12: =IF(L12>15,"HIGH",IF(L12>=5,"MODERATE","LOW")) | N12: Long procurement cycle; requires site permit coordination; 32-wk lead time confirmed by supplier | O12: PRG-001
A13: Siemens AG | B13: Distributed Control Systems | C13: EQ-009 | D13: DE | E13: EUR | F13: 10 | G13: 14 | H13: =G13-F13 | I13: 92 | J13: No | K13: Yes | L13: =ROUND((G13/F13)*(100-I13),2) | M13: =IF(L13>15,"HIGH",IF(L13>=5,"MODERATE","LOW")) | N13: Strong supply reliability; cybersecurity review adds 3-wk internal approval cycle | O13: PRG-001
A14: Inductive Automation | B14: SCADA Platform Licenses | C14: EQ-010 | D14: USA | E14: USD | F14: 4 | G14: 5 | H14: =G14-F14 | I14: 95 | J14: No | K14: Yes | L14: =ROUND((G14/F14)*(100-I14),2) | M14: =IF(L14>15,"HIGH",IF(L14>=5,"MODERATE","LOW")) | N14: Software license only; low supply risk; primary risk is IT/OT integration complexity | O14: PRG-001
A15: ABB Ltd | B15: Dry-Type Transformers | C15: EQ-011 | D15: CH | E15: USD | F15: 14 | G15: 20 | H15: =G15-F15 | I15: 87 | J15: No | K15: Yes | L15: =ROUND((G15/F15)*(100-I15),2) | M15: =IF(L15>15,"HIGH",IF(L15>=5,"MODERATE","LOW")) | N15: Component partially reused from prior program; new units on 20-wk market lead time | O15: PRG-001
A16: Daikin Applied | B16: Process Chiller Systems | C16: EQ-012 | D16: JP | E16: JPY | F16: 16 | G16: 20 | H16: =G16-F16 | I16: 89 | J16: No | K16: Yes | L16: =ROUND((G16/F16)*(100-I16),2) | M16: =IF(L16>15,"HIGH",IF(L16>=5,"MODERATE","LOW")) | N16: Glycol loop interface drawings required prior to FAT; JPY exposure monitored | O16: PRG-001
... A19: Mobile Industrial Robots (MiR) | B19: AMR Fleet – 10 Units | C19: EQ-015 | D19: DK | E19: EUR | F19: 14 | G19: 18 | H19: =G19-F19 | I19: 84 | J19: No | K19: Yes | L19: =ROUND((G19/F19)*(100-I19),2) | M19: =IF(L19>15,"HIGH",IF(L19>=5,"MODERATE","LOW")) | N19: Fleet SW license bundled; Wi-Fi site survey required 6 wks pre-installation | O19: PRG-001
A21: PRG-001 SUPPLY CHAIN RISK SUMMARY — Greenfield Expansion Phase II
A22: Avg Standard Lead Time (wks) | B22: =AVERAGE(F5:F19)
A23: Avg Current Lead Time (wks) | B23: =AVERAGE(G5:G19)
A24: Avg Lead Time Delta (wks) | B24: =AVERAGE(H5:H19)
A25: Avg Reliability Score (0-100) | B25: =AVERAGE(I5:I19)
A26: Avg Calculated Risk Score | B26: =AVERAGE(L5:L19)
A27: Max Risk Score (Worst Supplier) | B27: =MAX(L5:L19)
A28: # Single-Source Components | B28: =COUNTIF(J5:J19,"Yes")
A29: # Components with Alt Supplier | B29: =COUNTIF(K5:K19,"Yes")
A30: # HIGH Risk Tier Suppliers | B30: =COUNTIF(M5:M19,"HIGH")
A32: PRG-002 SUPPLIERS — Riverside Automation Upgrade Phase I
A33: Supplier | B33: Component Type | C33: Equip. Ref | D33: Region | E33: Ccy | F33: Std LT (wks) | G33: Current LT (wks) | H33: LT Delta (wks) | I33: Reliability (0-100) | J33: Single Source Risk | K33: Alt Supplier Available | L33: Calc. Risk Score | M33: Risk Tier | N33: Engineering Notes | O33: Program ID
A34: Fanuc America | B34: Palletizing Robots | C34: RV-001 | D34: USA | E34: USD | F34: 10 | G34: 12 | H34: =G34-F34 | I34: 91 | J34: No | K34: Yes | L34: =ROUND((G34/F34)*(100-I34),2) | M34: =IF(L34>15,"HIGH",IF(L34>=5,"MODERATE","LOW")) | N34: Deep bench of qualified integrators; low supply risk; standard robot platform | O34: PRG-002
A35: Krones AG | B35: Case Packer / Cartoning Systems | C35: RV-002 | D35: DE | E35: EUR | F35: 20 | G35: 24 | H35: =G35-F35 | I35: 86 | J35: Yes | K35: No | L35: =ROUND((G35/F35)*(100-I35),2) | M35: =IF(L35>15,"HIGH",IF(L35>=5,"MODERATE","LOW")) | N35: Single-source specialized cartoning technology; no qualified alternative identified | O35: PRG-002
A36: Fetch Robotics | B36: AGV Fleet Units | C36: RV-003 | D36: USA | E36: USD | F36: 8 | G36: 9 | H36: =G36-F36 | I36: 93 | J36: No | K36: Yes | L36: =ROUND((G36/F36)*(100-I36),2) | M36: =IF(L36>15,"HIGH",IF(L36>=5,"MODERATE","LOW")) | N36: Mature AGV platform; Locus Robotics evaluated as viable alternate | O36: PRG-002
A37: Cognex Corporation | B37: Vision Inspection Systems | C37: RV-004 | D37: USA | E37: USD | F37: 6 | G37: 7 | H37: =G37-F37 | I37: 95 | J37: No | K37: Yes | L37: =ROUND((G37/F37)*(100-I37),2) | M37: =IF(L37>15,"HIGH",IF(L37>=5,"MODERATE","LOW")) | N37: Commodity machine-vision hardware; Keyence pre-qualified as alternate | O37: PRG-002
A38: Rockwell Automation | B38: Warehouse Control System | C38: RV-005 | D38: USA | E38: USD | F38: 8 | G38: 9 | H38: =G38-F38 | I38: 94 | J38: No | K38: Yes | L38: =ROUND((G38/F38)*(100-I38),2) | M38: =IF(L38>15,"HIGH",IF(L38>=5,"MODERATE","LOW")) | N38: Strong integrator relationship; low supply risk; standard PlantPAx platform | O38: PRG-002
A39: Dematic Corp | B39: Conveyor & Sortation Systems | C39: RV-006 | D39: USA | E39: USD | F39: 16 | G39: 20 | H39: =G39-F39 | I39: 88 | J39: No | K39: Yes | L39: =ROUND((G39/F39)*(100-I39),2) | M39: =IF(L39>15,"HIGH",IF(L39>=5,"MODERATE","LOW")) | N39: Complex site-specific integration; Honeywell Intelligrated evaluated as alternate | O39: PRG-002
A41: PRG-002 SUPPLY CHAIN RISK SUMMARY — Riverside Automation Upgrade Phase I
A42: Avg Calculated Risk Score | B42: =AVERAGE(L34:L39)
A43: Max Risk Score (Worst Supplier) | B43: =MAX(L34:L39)
A44: # Single-Source Components | B44: =COUNTIF(J34:J39,"Yes")
A45: # HIGH Risk Tier Suppliers | B45: =COUNTIF(M34:M39,"HIGH")

Sheet S04_Should_Cost_Model
A1: S04 — First-Principles Should-Cost Model — Advanced Manufacturing Capital Equipment
A2: Clean-sheet cost build-up per equipment category | All inputs in BLUE | Formulas in BLACK | Cross-sheet links in GREEN | Independent cost estimate used to challenge supplier quotes and identify cost reduction opportunities.
A4: Equipment Category | B4: Cost Element | C4: Mat. Wt (kg) | D4: Mat. Price (USD/kg) | E4: Mat. Cost | F4: Labor Hrs | G4: Shop Rate | H4: Labor Cost | I4: Subcomp/Electronics | J4: Sub-Total | K4: Overhead (12%) | L4: Supplier Margin | M4: TOTAL Cost | N4: Notes
A5: Vacuum Pump System | B5: Raw Material – Stainless Steel Body | C5: 280 | D5: 3.8 | E5: =C5*D5 | F5: 0 | G5: 0 | H5: =F5*G5 | I5: 0 | J5: =E5+H5+I5 | K5: =J5*0.12 | L5: =(J5+K5)*'S01_Disclaimer_Assumptions'!$B$38 | M5: =J5+K5+L5 | N5: Precision-cast SS housing; 304SS at market rate
A6: Vacuum Pump System | B6: Machining & Fabrication Labor | C6: 0 | D6: 0 | E6: =C6*D6 | F6: 95 | G6: ='S01_Disclaimer_Assumptions'!$B$23 | H6: =F6*G6 | I6: 0 | J6: =E6+H6+I6 | K6: =J6*0.12 | L6: =(J6+K6)*'S01_Disclaimer_Assumptions'!$B$38 | M6: =J6+K6+L6 | N6: CNC turning & milling; pump body, rotor, stator components
A7: Vacuum Pump System | B7: Purchased Subcomponents – Seals/Bearings | C7: 0 | D7: 0 | E7: =C7*D7 | F7: 0 | G7: 0 | H7: =F7*G7 | I7: 18500 | J7: =E7+H7+I7 | K7: =J7*0.12 | L7: =(J7+K7)*'S01_Disclaimer_Assumptions'!$B$38 | M7: =J7+K7+L7 | N7: Ceramic bearings, PTFE seals, shaft seals; sourced from FAG/SKF
A8: Vacuum Pump System | B8: Electronics & Motor Drive System | C8: 0 | D8: 0 | E8: =C8*D8 | F8: 0 | G8: 0 | H8: =F8*G8 | I8: 22000 | J8: =E8+H8+I8 | K8: =J8*0.12 | L8: =(J8+K8)*'S01_Disclaimer_Assumptions'!$B$38 | M8: =J8+K8+L8 | N8: VFD drive, PLC I/O cards, HMI touchscreen, wiring harness
A9: Vacuum Pump System | B9: Assembly Labor | C9: 0 | D9: 0 | E9: =C9*D9 | F9: 32 | G9: ='S01_Disclaimer_Assumptions'!$B$23 | H9: =F9*G9 | I9: 0 | J9: =E9+H9+I9 | K9: =J9*0.12 | L9: =(J9+K9)*'S01_Disclaimer_Assumptions'!$B$38 | M9: =J9+K9+L9 | N9: Final assembly, alignment, internal leak test; 32 hrs per unit
A10: Vacuum Pump System | B10: Quality / Acceptance Testing | C10: 0 | D10: 0 | E10: =C10*D10 | F10: 12 | G10: ='S01_Disclaimer_Assumptions'!$B$24 | H10: =F10*G10 | I10: 0 | J10: =E10+H10+I10 | K10: =J10*0.12 | L10: =(J10+K10)*'S01_Disclaimer_Assumptions'!$B$38 | M10: =J10+K10+L10 | N10: Performance characterization, helium leak test, ultimate pressure verification
A11: High-Temp Furnace | B11: Raw Material – Inconel / Quartz / Refractory | C11: 420 | D11: 6.84 | E11: =C11*D11 | F11: 0 | G11: 0 | H11: =F11*G11 | I11: 0 | J11: =E11+H11+I11 | K11: =J11*0.12 | L11: =(J11+K11)*'S01_Disclaimer_Assumptions'!$B$38 | M11: =J11+K11+L11 | N11: Inconel 625 hot zone; quartz liner; ceramic refractory bricks
A12: High-Temp Furnace | B12: Machining & Fabrication Labor | C12: 0 | D12: 0 | E12: =C12*D12 | F12: 180 | G12: ='S01_Disclaimer_Assumptions'!$B$23 | H12: =F12*G12 | I12: 0 | J12: =E12+H12+I12 | K12: =J12*0.12 | L12: =(J12+K12)*'S01_Disclaimer_Assumptions'!$B$38 | M12: =J12+K12+L12 | N12: Welding, machining, tube bending; complex multi-zone fabrication
A13: High-Temp Furnace | B13: Purchased Subcomponents – Heating Elements | C13: 0 | D13: 0 | E13: =C13*D13 | F13: 0 | G13: 0 | H13: =F13*G13 | I13: 45000 | J13: =E13+H13+I13 | K13: =J13*0.12 | L13: =(J13+K13)*'S01_Disclaimer_Assumptions'!$B$38 | M13: =J13+K13+L13 | N13: SiC heating elements, 8-zone; Kanthal A1 backup; sourced from Kanthal
A14: High-Temp Furnace | B14: Electronics & Control Systems | C14: 0 | D14: 0 | E14: =C14*D14 | F14: 0 | G14: 0 | H14: =F14*G14 | I14: 38000 | J14: =E14+H14+I14 | K14: =J14*0.12 | L14: =(J14+K14)*'S01_Disclaimer_Assumptions'!$B$38 | M14: =J14+K14+L14 | N14: Multi-zone PID controllers, SCR power units, thermocouple arrays
A15: High-Temp Furnace | B15: Assembly Labor | C15: 0 | D15: 0 | E15: =C15*D15 | F15: 65 | G15: ='S01_Disclaimer_Assumptions'!$B$23 | H15: =F15*G15 | I15: 0 | J15: =E15+H15+I15 | K15: =J15*0.12 | L15: =(J15+K15)*'S01_Disclaimer_Assumptions'!$B$38 | M15: =J15+K15+L15 | N15: Zone assembly, insulation packing, wiring, pre-commissioning
A16: High-Temp Furnace | B16: Quality / Acceptance Testing | C16: 0 | D16: 0 | E16: =C16*D16 | F16: 20 | G16: ='S01_Disclaimer_Assumptions'!$B$24 | H16: =F16*G16 | I16: 0 | J16: =E16+H16+I16 | K16: =J16*0.12 | L16: =(J16+K16)*'S01_Disclaimer_Assumptions'!$B$38 | M16: =J16+K16+L16 | N16: Temperature uniformity survey (9-point), ramp rate validation, atmosphere leak test
A17: Robotics / Automation | B17: Raw Material – Aluminum Frame & Structure | C17: 85 | D17: 4.2 | E17: =C17*D17 | F17: 0 | G17: 0 | H17: =F17*G17 | I17: 0 | J17: =E17+H17+I17 | K17: =J17*0.12 | L17: =(J17+K17)*'S01_Disclaimer_Assumptions'!$B$38 | M17: =J17+K17+L17 | N17: 6061 AL structural extrusions, machined joints, end-effector blanks
A18: Robotics / Automation | B18: Machining & Fabrication Labor | C18: 0 | D18: 0 | E18: =C18*D18 | F18: 40 | G18: ='S01_Disclaimer_Assumptions'!$B$23 | H18: =F18*G18 | I18: 0 | J18: =E18+H18+I18 | K18: =J18*0.12 | L18: =(J18+K18)*'S01_Disclaimer_Assumptions'!$B$38 | M18: =J18+K18+L18 | N18: CNC machining of end-effectors, links, flanges; anodizing finish
A19: Robotics / Automation | B19: Purchased Subcomponents – Servo / Drive Train | C19: 0 | D19: 0 | E19: =C19*D19 | F19: 0 | G19: 0 | H19: =F19*G19 | I19: 52000 | J19: =E19+H19+I19 | K19: =J19*0.12 | L19: =(J19+K19)*'S01_Disclaimer_Assumptions'!$B$38 | M19: =J19+K19+L19 | N19: Harmonic drive reducers, servo motors, encoders; Yaskawa / Nabtesco
A20: Robotics / Automation | B20: Electronics & Vision System | C20: 0 | D20: 0 | E20: =C20*D20 | F20: 0 | G20: 0 | H20: =F20*G20 | I20: 28000 | J20: =E20+H20+I20 | K20: =J20*0.12 | L20: =(J20+K20)*'S01_Disclaimer_Assumptions'!$B$38 | M20: =J20+K20+L20 | N20: Robot controller, teach pendant, vision camera + lighting, safety scanner
A21: Robotics / Automation | B21: Software & Integration | C21: 0 | D21: 0 | E21: =C21*D21 | F21: 35 | G21: ='S01_Disclaimer_Assumptions'!$B$24 | H21: =F21*G21 | I21: 0 | J21: =E21+H21+I21 | K21: =J21*0.12 | L21: =(J21+K21)*'S01_Disclaimer_Assumptions'!$B$38 | M21: =J21+K21+L21 | N21: MES/SEMI interface SW development, recipe upload, FAT validation scripts
A22: Robotics / Automation | B22: Quality / Acceptance Testing | C22: 0 | D22: 0 | E22: =C22*D22 | F22: 10 | G22: ='S01_Disclaimer_Assumptions'!$B$24 | H22: =F22*G22 | I22: 0 | J22: =E22+H22+I22 | K22: =J22*0.12 | L22: =(J22+K22)*'S01_Disclaimer_Assumptions'!$B$38 | M22: =J22+K22+L22 | N22: Path accuracy, repeatability ±0.05mm, cycle time validation, safety relay test
A23: Gas Handling System | B23: Raw Material – 316L SS Tubing & Fittings | C23: 60 | D23: 4.56 | E23: =C23*D23 | F23: 0 | G23: 0 | H23: =F23*G23 | I23: 0 | J23: =E23+H23+I23 | K23: =J23*0.12 | L23: =(J23+K23)*'S01_Disclaimer_Assumptions'!$B$38 | M23: =J23+K23+L23 | N23: 316L EP-grade tubing, VCR fittings, valves; electropolished internal surfaces
A24: Gas Handling System | B24: Machining & Fabrication Labor | C24: 0 | D24: 0 | E24: =C24*D24 | F24: 55 | G24: ='S01_Disclaimer_Assumptions'!$B$23 | H24: =F24*G24 | I24: 0 | J24: =E24+H24+I24 | K24: =J24*0.12 | L24: =(J24+K24)*'S01_Disclaimer_Assumptions'!$B$38 | M24: =J24+K24+L24 | N24: Tube bending, orbital welding, manifold assembly; cleanroom fabrication
A25: Gas Handling System | B25: Purchased Subcomponents – Valves & Regulators | C25: 0 | D25: 0 | E25: =C25*D25 | F25: 0 | G25: 0 | H25: =F25*G25 | I25: 32000 | J25: =E25+H25+I25 | K25: =J25*0.12 | L25: =(J25+K25)*'S01_Disclaimer_Assumptions'!$B$38 | M25: =J25+K25+L25 | N25: Swagelok/Parker pneumatic valves, MFCs, pressure regulators, check valves
A26: Gas Handling System | B26: Electronics & Safety Interlock System | C26: 0 | D26: 0 | E26: =C26*D26 | F26: 0 | G26: 0 | H26: =F26*G26 | I26: 18000 | J26: =E26+H26+I26 | K26: =J26*0.12 | L26: =(J26+K26)*'S01_Disclaimer_Assumptions'!$B$38 | M26: =J26+K26+L26 | N26: Gas detection sensors, PLC safety relays, solenoid driver cards, HMI
A27: Gas Handling System | B27: Assembly & Leak Testing | C27: 0 | D27: 0 | E27: =C27*D27 | F27: 28 | G27: ='S01_Disclaimer_Assumptions'!$B$23 | H27: =F27*G27 | I27: 0 | J27: =E27+H27+I27 | K27: =J27*0.12 | L27: =(J27+K27)*'S01_Disclaimer_Assumptions'!$B$38 | M27: =J27+K27+L27 | N27: Assembly, helium leak test (<1E-9 atm·cc/s), pressure hold test, passivation
A28: Gas Handling System | B28: Quality / Acceptance Testing | C28: 0 | D28: 0 | E28: =C28*D28 | F28: 8 | G28: ='S01_Disclaimer_Assumptions'!$B$24 | H28: =F28*G28 | I28: 0 | J28: =E28+H28+I28 | K28: =J28*0.12 | L28: =(J28+K28)*'S01_Disclaimer_Assumptions'!$B$38 | M28: =J28+K28+L28 | N28: Gas purity validation, flow calibration, emergency shutoff functional test
A29: PLC Control System | B29: Purchased Subcomponents – PLC Hardware | C29: 0 | D29: 0 | E29: =C29*D29 | F29: 0 | G29: 0 | H29: =F29*G29 | I29: 42000 | J29: =E29+H29+I29 | K29: =J29*0.12 | L29: =(J29+K29)*'S01_Disclaimer_Assumptions'!$B$38 | M29: =J29+K29+L29 | N29: Siemens S7-1500 CPU, I/O cards, power supplies, HMI panel; list price
A30: PLC Control System | B30: Panel Fabrication & Wiring | C30: 0 | D30: 0 | E30: =C30*D30 | F30: 45 | G30: ='S01_Disclaimer_Assumptions'!$B$23 | H30: =F30*G30 | I30: 0 | J30: =E30+H30+I30 | K30: =J30*0.12 | L30: =(J30+K30)*'S01_Disclaimer_Assumptions'!$B$38 | M30: =J30+K30+L30 | N30: Control panel fabrication, DIN rail mounting, cable management, labeling
A31: PLC Control System | B31: Software Development & Programming | C31: 0 | D31: 0 | E31: =C31*D31 | F31: 80 | G31: ='S01_Disclaimer_Assumptions'!$B$24 | H31: =F31*G31 | I31: 0 | J31: =E31+H31+I31 | K31: =J31*0.12 | L31: =(J31+K31)*'S01_Disclaimer_Assumptions'!$B$38 | M31: =J31+K31+L31 | N31: Ladder logic/FBD development, HMI graphics, alarm management, I/O mapping
A32: PLC Control System | B32: Factory Acceptance Testing | C32: 0 | D32: 0 | E32: =C32*D32 | F32: 16 | G32: ='S01_Disclaimer_Assumptions'!$B$24 | H32: =F32*G32 | I32: 0 | J32: =E32+H32+I32 | K32: =J32*0.12 | L32: =(J32+K32)*'S01_Disclaimer_Assumptions'!$B$38 | M32: =J32+K32+L32 | N32: FAT protocol execution, point-to-point I/O check, interlock simulation
A34: SHOULD-COST SUMMARY BY EQUIPMENT CATEGORY
A35: Equipment Category | B35: Material Cost | C35: Labor Cost | D35: Subcomponents | E35: Sub-Total | F35: Overhead (12%) | G35: Supplier Margin | H35: TOTAL Should-Cost | I35: Supplier Quote (Budget Est.) | J35: Variance (Quote-SC) | K35: Variance %
A36: Vacuum Pump System | B36: =SUM(E5:E10) | C36: =SUM(H5:H10) | D36: =SUM(I5:I10) | E36: =B36+C36+D36 | F36: =E36*0.12 | G36: =(E36+F36)*'S01_Disclaimer_Assumptions'!$B$38 | H36: =E36+F36+G36 | I36: 195000 | J36: =I36-H36 | K36: =J36/H36
A37: High-Temp Furnace | B37: =SUM(E11:E16) | C37: =SUM(H11:H16) | D37: =SUM(I11:I16) | E37: =B37+C37+D37 | F37: =E37*0.12 | G37: =(E37+F37)*'S01_Disclaimer_Assumptions'!$B$38 | H37: =E37+F37+G37 | I37: 540000 | J37: =I37-H37 | K37: =J37/H37
A38: Robotics / Automation | B38: =SUM(E17:E22) | C38: =SUM(H17:H22) | D38: =SUM(I17:I22) | E38: =B38+C38+D38 | F38: =E38*0.12 | G38: =(E38+F38)*'S01_Disclaimer_Assumptions'!$B$38 | H38: =E38+F38+G38 | I38: 285000 | J38: =I38-H38 | K38: =J38/H38
A39: Gas Handling System | B39: =SUM(E23:E28) | C39: =SUM(H23:H28) | D39: =SUM(I23:I28) | E39: =B39+C39+D39 | F39: =E39*0.12 | G39: =(E39+F39)*'S01_Disclaimer_Assumptions'!$B$38 | H39: =E39+F39+G39 | I39: 205000 | J39: =I39-H39 | K39: =J39/H39
A40: PLC Control System | B40: =SUM(E29:E32) | C40: =SUM(H29:H32) | D40: =SUM(I29:I32) | E40: =B40+C40+D40 | F40: =E40*0.12 | G40: =(E40+F40)*'S01_Disclaimer_Assumptions'!$B$38 | H40: =E40+F40+G40 | I40: 175000 | J40: =I40-H40 | K40: =J40/H40
A41: GRAND TOTAL | B41: =SUM(B36:B40) | C41: =SUM(C36:C40) | D41: =SUM(D36:D40) | E41: =SUM(E36:E40) | F41: =SUM(F36:F40) | G41: =SUM(G36:G40) | H41: =SUM(H36:H40) | I41: =SUM(I36:I40) | J41: =SUM(J36:J40) | K41: =J41/H41

Sheet S05_TCO_Downtime_Model
A1: S05 — Total Cost of Ownership (TCO) & Downtime Risk Model — 10-Year Lifecycle Analysis
A2: Compares Supplier A (Premium — TEL/AMAT-type) vs Supplier B (Value — domestic alternative) across purchase, energy, maintenance, downtime, and lifecycle NPV | Discount Rate from S01_Disclaimer_Assumptions
A4: MODEL PARAMETERS (linked from S01_Disclaimer_Assumptions)
A5: Discount Rate (WACC) | B5: ='S01_Disclaimer_Assumptions'!$B$15
A6: Project Horizon (Years) | B6: 10
A7: Energy Price (USD/kWh) | B7: ='S01_Disclaimer_Assumptions'!$B$8
A8: Production Value per Hour (USD/hr) | B8: ='S01_Disclaimer_Assumptions'!$B$33
A9: Inflation Rate | B9: ='S01_Disclaimer_Assumptions'!$B$19
A11: EQUIPMENT COMPARISON — SUPPLIER A (PREMIUM) vs SUPPLIER B (VALUE)
A12: Cost Parameter | B12: Supplier A (Premium) | C12: Supplier B (Value) | D12: Delta (B-A) | E12: Notes
A13: Purchase Price (per unit, USD) | B13: 680000 | C13: 520000 | D13: =C13-B13 | E13: Supplier A = TEL EQ-004 type; Supplier B = domestic alternative
A14: Quantity | B14: 2 | C14: 2 | D14: =C14-B14 | E14: Equal quantity for fair comparison
A15: Installation Cost (per unit, USD) | B15: 52000 | C15: 38000 | D15: =C15-B15 | E15: Supplier A requires specialized installation crew (JPY contract)
A16: Energy Consumption (kWh/hr) | B16: 110 | C16: 98 | D16: =C16-B16 | E16: Supplier A higher thermal efficiency spec; Supplier B 11% higher power draw
A17: Operational Hours (Annual) | B17: 8320 | C17: 8320 | D17: =C17-B17 | E17: Both operate on identical shift schedule
A18: Maintenance Rate (% of purchase) | B18: 0.045 | C18: 0.055 | D18: =C18-B18 | E18: Supplier A lower maint rate; Supplier B higher due to older platform design
A19: Expected MTBF (hrs) | B19: 4200 | C19: 2800 | D19: =C19-B19 | E19: Mean Time Between Failures; Supplier A more robust platform
A20: Expected MTTR (hrs) | B20: 6 | C20: 10 | D20: =C20-B20 | E20: Mean Time To Repair; Supplier A has faster FSE response SLA
A21: Spare Parts Annual Cost (USD) | B21: 18000 | C21: 28000 | D21: =C21-B21 | E21: Supplier A proprietary spares expensive but fewer events; B more frequent
A22: Expected Equipment Lifetime (yrs) | B22: 15 | C22: 12 | D22: =C22-B22 | E22: Supplier A longer qualified life; Supplier B 12 yr basis
A23: Residual Value at End of Life (%) | B23: 0.05 | C23: 0.03 | D23: =C23-B23 | E23: Estimated salvage/residual as % of purchase price
A25: 10-YEAR LIFECYCLE COST MODEL
A26: Cost Component / Supplier | B26: Y1 | C26: Y2 | D26: Y3 | E26: Y4 | F26: Y5 | G26: Y6 | H26: Y7 | I26: Y8 | J26: Y9 | K26: Y10 | L26: 10-Yr Total | M26: NPV (10-Yr)
A27: 1. Purchase Cost (total)
A28: Supplier A | B28: =680000*2 | C28: 0 | D28: 0 | E28: 0 | F28: 0 | G28: 0 | H28: 0 | I28: 0 | J28: 0 | K28: 0 | L28: =SUM(B28:K28) | M28: =NPV('S01_Disclaimer_Assumptions'!$B$15,B28:K28)
A29: Supplier B | B29: =520000*2 | C29: 0 | D29: 0 | E29: 0 | F29: 0 | G29: 0 | H29: 0 | I29: 0 | J29: 0 | K29: 0 | L29: =SUM(B29:K29) | M29: =NPV('S01_Disclaimer_Assumptions'!$B$15,B29:K29)
A30: 2. Installation Cost (total)
A31: Supplier A | B31: =52000*2 | C31: 0 | D31: 0 | E31: 0 | F31: 0 | G31: 0 | H31: 0 | I31: 0 | J31: 0 | K31: 0 | L31: =SUM(B31:K31) | M31: =NPV('S01_Disclaimer_Assumptions'!$B$15,B31:K31)
A32: Supplier B | B32: =38000*2 | C32: 0 | D32: 0 | E32: 0 | F32: 0 | G32: 0 | H32: 0 | I32: 0 | J32: 0 | K32: 0 | L32: =SUM(B32:K32) | M32: =NPV('S01_Disclaimer_Assumptions'!$B$15,B32:K32)
A33: 3. Annual Energy Cost (escalates with inflation from Year 2)
A34: Supplier A | B34: =110*2*8320*'S01_Disclaimer_Assumptions'!$B$8 | C34: =B34*(1+'S01_Disclaimer_Assumptions'!$B$19) | D34: =C34*(1+'S01_Disclaimer_Assumptions'!$B$19) | E34: =D34*(1+'S01_Disclaimer_Assumptions'!$B$19) | F34: =E34*(1+'S01_Disclaimer_Assumptions'!$B$19) | G34: =F34*(1+'S01_Disclaimer_Assumptions'!$B$19) | H34: =G34*(1+'S01_Disclaimer_Assumptions'!$B$19) | I34: =H34*(1+'S01_Disclaimer_Assumptions'!$B$19) | J34: =I34*(1+'S01_Disclaimer_Assumptions'!$B$19) | K34: =J34*(1+'S01_Disclaimer_Assumptions'!$B$19) | L34: =SUM(B34:K34) | M34: =NPV('S01_Disclaimer_Assumptions'!$B$15,B34:K34)
A35: Supplier B | B35: =98*2*8320*'S01_Disclaimer_Assumptions'!$B$8 | C35: =B35*(1+'S01_Disclaimer_Assumptions'!$B$19) | D35: =C35*(1+'S01_Disclaimer_Assumptions'!$B$19) | E35: =D35*(1+'S01_Disclaimer_Assumptions'!$B$19) | F35: =E35*(1+'S01_Disclaimer_Assumptions'!$B$19) | G35: =F35*(1+'S01_Disclaimer_Assumptions'!$B$19) | H35: =G35*(1+'S01_Disclaimer_Assumptions'!$B$19) | I35: =H35*(1+'S01_Disclaimer_Assumptions'!$B$19) | J35: =I35*(1+'S01_Disclaimer_Assumptions'!$B$19) | K35: =J35*(1+'S01_Disclaimer_Assumptions'!$B$19) | L35: =SUM(B35:K35) | M35: =NPV('S01_Disclaimer_Assumptions'!$B$15,B35:K35)
A36: 4. Annual Maintenance Cost (% of purchase; escalates with inflation)
A37: Supplier A | B37: =680000*2*0.045 | C37: =B37*(1+'S01_Disclaimer_Assumptions'!$B$19) | D37: =C37*(1+'S01_Disclaimer_Assumptions'!$B$19) | E37: =D37*(1+'S01_Disclaimer_Assumptions'!$B$19) | F37: =E37*(1+'S01_Disclaimer_Assumptions'!$B$19) | G37: =F37*(1+'S01_Disclaimer_Assumptions'!$B$19) | H37: =G37*(1+'S01_Disclaimer_Assumptions'!$B$19) | I37: =H37*(1+'S01_Disclaimer_Assumptions'!$B$19) | J37: =I37*(1+'S01_Disclaimer_Assumptions'!$B$19) | K37: =J37*(1+'S01_Disclaimer_Assumptions'!$B$19) | L37: =SUM(B37:K37) | M37: =NPV('S01_Disclaimer_Assumptions'!$B$15,B37:K37)
A38: Supplier B | B38: =520000*2*0.055 | C38: =B38*(1+'S01_Disclaimer_Assumptions'!$B$19) | D38: =C38*(1+'S01_Disclaimer_Assumptions'!$B$19) | E38: =D38*(1+'S01_Disclaimer_Assumptions'!$B$19) | F38: =E38*(1+'S01_Disclaimer_Assumptions'!$B$19) | G38: =F38*(1+'S01_Disclaimer_Assumptions'!$B$19) | H38: =G38*(1+'S01_Disclaimer_Assumptions'!$B$19) | I38: =H38*(1+'S01_Disclaimer_Assumptions'!$B$19) | J38: =I38*(1+'S01_Disclaimer_Assumptions'!$B$19) | K38: =J38*(1+'S01_Disclaimer_Assumptions'!$B$19) | L38: =SUM(B38:K38) | M38: =NPV('S01_Disclaimer_Assumptions'!$B$15,B38:K38)
A39: 5. Annual Spare Parts Cost (escalates with inflation)
A40: Supplier A | B40: =18000 | C40: =B40*(1+'S01_Disclaimer_Assumptions'!$B$19) | D40: =C40*(1+'S01_Disclaimer_Assumptions'!$B$19) | E40: =D40*(1+'S01_Disclaimer_Assumptions'!$B$19) | F40: =E40*(1+'S01_Disclaimer_Assumptions'!$B$19) | G40: =F40*(1+'S01_Disclaimer_Assumptions'!$B$19) | H40: =G40*(1+'S01_Disclaimer_Assumptions'!$B$19) | I40: =H40*(1+'S01_Disclaimer_Assumptions'!$B$19) | J40: =I40*(1+'S01_Disclaimer_Assumptions'!$B$19) | K40: =J40*(1+'S01_Disclaimer_Assumptions'!$B$19) | L40: =SUM(B40:K40) | M40: =NPV('S01_Disclaimer_Assumptions'!$B$15,B40:K40)
A41: Supplier B | B41: =28000 | C41: =B41*(1+'S01_Disclaimer_Assumptions'!$B$19) | D41: =C41*(1+'S01_Disclaimer_Assumptions'!$B$19) | E41: =D41*(1+'S01_Disclaimer_Assumptions'!$B$19) | F41: =E41*(1+'S01_Disclaimer_Assumptions'!$B$19) | G41: =F41*(1+'S01_Disclaimer_Assumptions'!$B$19) | H41: =G41*(1+'S01_Disclaimer_Assumptions'!$B$19) | I41: =H41*(1+'S01_Disclaimer_Assumptions'!$B$19) | J41: =I41*(1+'S01_Disclaimer_Assumptions'!$B$19) | K41: =J41*(1+'S01_Disclaimer_Assumptions'!$B$19) | L41: =SUM(B41:K41) | M41: =NPV('S01_Disclaimer_Assumptions'!$B$15,B41:K41)
A42: 6. Downtime Cost (Annual) — (Op Hrs ÷ MTBF) × MTTR × Production Value/hr
A43: Supplier A | B43: =(8320/4200)*6*'S01_Disclaimer_Assumptions'!$B$33 | C43: =(8320/4200)*6*'S01_Disclaimer_Assumptions'!$B$33 | D43: =(8320/4200)*6*'S01_Disclaimer_Assumptions'!$B$33 | E43: =(8320/4200)*6*'S01_Disclaimer_Assumptions'!$B$33 | F43: =(8320/4200)*6*'S01_Disclaimer_Assumptions'!$B$33 | G43: =(8320/4200)*6*'S01_Disclaimer_Assumptions'!$B$33 | H43: =(8320/4200)*6*'S01_Disclaimer_Assumptions'!$B$33 | I43: =(8320/4200)*6*'S01_Disclaimer_Assumptions'!$B$33 | ... K43: =(8320/4200)*6*'S01_Disclaimer_Assumptions'!$B$33 | L43: =SUM(B43:K43) | M43: =NPV('S01_Disclaimer_Assumptions'!$B$15,B43:K43)
A44: Supplier B | B44: =(8320/2800)*10*'S01_Disclaimer_Assumptions'!$B$33 | C44: =(8320/2800)*10*'S01_Disclaimer_Assumptions'!$B$33 | D44: =(8320/2800)*10*'S01_Disclaimer_Assumptions'!$B$33 | E44: =(8320/2800)*10*'S01_Disclaimer_Assumptions'!$B$33 | F44: =(8320/2800)*10*'S01_Disclaimer_Assumptions'!$B$33 | G44: =(8320/2800)*10*'S01_Disclaimer_Assumptions'!$B$33 | H44: =(8320/2800)*10*'S01_Disclaimer_Assumptions'!$B$33 | I44: =(8320/2800)*10*'S01_Disclaimer_Assumptions'!$B$33 | ... K44: =(8320/2800)*10*'S01_Disclaimer_Assumptions'!$B$33 | L44: =SUM(B44:K44) | M44: =NPV('S01_Disclaimer_Assumptions'!$B$15,B44:K44)
A46: TOTAL COST OF OWNERSHIP SUMMARY
A47: Supplier | B47: Y1 | C47: Y2 | D47: Y3 | E47: Y4 | F47: Y5 | G47: Y6 | H47: Y7 | I47: Y8 | J47: Y9 | K47: Y10 | L47: 10-Yr Total | M47: NPV (10-Yr)
A48: A (Premium) | B48: =B28+B31+B34+B37+B40+B43 | C48: =C28+C31+C34+C37+C40+C43 | D48: =D28+D31+D34+D37+D40+D43 | E48: =E28+E31+E34+E37+E40+E43 | F48: =F28+F31+F34+F37+F40+F43 | G48: =G28+G31+G34+G37+G40+G43 | H48: =H28+H31+H34+H37+H40+H43 | I48: =I28+I31+I34+I37+I40+I43 | ... K48: =K28+K31+K34+K37+K40+K43 | L48: =SUM(B48:K48) | M48: =NPV('S01_Disclaimer_Assumptions'!$B$15,B48:K48)
A49: B (Value) | B49: =B29+B32+B35+B38+B41+B44 | C49: =C29+C32+C35+C38+C41+C44 | D49: =D29+D32+D35+D38+D41+D44 | E49: =E29+E32+E35+E38+E41+E44 | F49: =F29+F32+F35+F38+F41+F44 | G49: =G29+G32+G35+G38+G41+G44 | H49: =H29+H32+H35+H38+H41+H44 | I49: =I29+I32+I35+I38+I41+I44 | ... K49: =K29+K32+K35+K38+K41+K44 | L49: =SUM(B49:K49) | M49: =NPV('S01_Disclaimer_Assumptions'!$B$15,B49:K49)
A50: TCO DELTA (B Savings vs A) | B50: =B48-B49 | C50: =C48-C49 | D50: =D48-D49 | E50: =E48-E49 | F50: =F48-F49 | G50: =G48-G49 | H50: =H48-H49 | I50: =I48-I49 | ... M50: =M48-M49

Sheet S06_WBS
A1: S06 — Work Breakdown Structure (WBS) — Greenfield Expansion Phase II
A2: Program: Greenfield Expansion Phase II | Owner: Sourabh Tarodekar | Status: Active | All dates 2025 | WBS hierarchy: Level 1 = Program | Level 2 = Workstream | Level 3 = Work Package | WBS codes used as Activity IDs in S07_CPM_Master_Schedule
A4: WBS Code | B4: Level | C4: Workstream / Work Package | D4: Responsible Function | E4: Duration Est (wks) | F4: Start Wk | G4: End Wk | H4: Deliverable / Exit Criterion
A5: 1.0 | B5: 1 | C5: GREENFIELD EXPANSION PHASE II — PROGRAM | D5: Program Management | E5: 46 | F5: 1 | G5: 46 | H5: Full program from AR approval to production release
A6: 1.1 | B6: 2 | C6: PROGRAM MANAGEMENT | D6: Program Management | E6: 46 | F6: 1 | G6: 46 | H6: Program governance and control
A7: 1.1.1 | B7: 3 | C7: Program kick-off & AR execution | D7: PM / Finance | E7: 1 | F7: 1 | G7: 1 | H7: AR signed, cost centre open, PO authority issued
A8: 1.1.2 | B8: 3 | C8: Stakeholder communication plan | D8: PM / Eng Leadership | E8: 1 | F8: 1 | G8: 2 | H8: RACI matrix, communication cadence agreed
A9: 1.1.3 | B9: 3 | C9: Program schedule baseline | D9: PM / Scheduling | E9: 1 | F9: 1 | G9: 2 | H9: CPM schedule issued, baseline locked
A10: 1.1.4 | B10: 3 | C10: Weekly program review cadence | D10: PM | E10: 45 | F10: 2 | G10: 46 | H10: Weekly status reports issued throughout program
A11: 1.1.5 | B11: 3 | C11: Lessons learned & close-out report | D11: PM | E11: 1 | F11: 46 | G11: 46 | H11: Program close-out document issued
A12: 1.2 | B12: 2 | C12: SOURCING & PROCUREMENT | D12: Supply Chain / Sourcing | E12: 14 | F12: 1 | G12: 14 | H12: All long-lead POs placed; contracts executed
A13: 1.2.1 | B13: 3 | C13: RFQ issue — long-lead equipment (EQ-002,004,008,014) | D13: Sourcing | E13: 1 | F13: 1 | G13: 1 | H13: RFQs issued to shortlisted suppliers
A14: 1.2.2 | B14: 3 | C14: Supplier commercial evaluation & BAFO | D14: Sourcing | E14: 2 | F14: 1 | G14: 3 | H14: Bid tabulations complete; BAFO received
A15: 1.2.3 | B15: 3 | C15: Negotiation & contract award — EQ-014 (AMAT RTP) | D15: Sourcing / Legal | E15: 2 | F15: 2 | G15: 4 | H15: PO issued; 30% deposit paid
A16: 1.2.4 | B16: 3 | C16: Negotiation & contract award — EQ-002 (Pfeiffer TMP) | D16: Sourcing / Legal | E16: 2 | F16: 2 | G16: 4 | H16: PO issued; FX hedge confirmed
... A29: 1.3.7 | B29: 3 | C29: Cybersecurity review — Siemens DCS | D29: InfoSec / Engineering | E29: 3 | F29: 5 | G29: 8 | H29: Cybersecurity approval issued for OT network connection
A30: 1.3.8 | B30: 3 | C30: Engineering change order management | D30: Engineering | E30: ongoing | F30: 1 | G30: 46 | H30: ECO register maintained throughout program
A31: 1.4 | B31: 2 | C31: SUPPLIER FABRICATION & FAT | D31: Supply Chain / Engineering | E31: 26 | F31: 1 | G31: 27 | H31: All equipment at FAT complete; ready to ship
A32: 1.4.1 | B32: 3 | C32: EQ-014 (AMAT RTP) — manufacturing & FAT | D32: AMAT / Engineering | E32: 24 | F32: 1 | G32: 25 | H32: RTP units pass FAT; shipping released
A33: 1.4.2 | B33: 3 | C33: EQ-002 (Pfeiffer TMP) — manufacturing & FAT [CRITICAL PATH] | D33: Pfeiffer / Engineering | E33: 26 | F33: 1 | G33: 27 | H33: CRITICAL PATH: TMPs pass FAT; shipping released
A34: 1.4.3 | B34: 3 | C34: EQ-004 (TEL Batch Furnace) — manufacturing & FAT | D34: TEL / Engineering | E34: 28 | F34: 1 | G34: 29 | H34: Batch furnace FAT complete; JPY invoice settled
A35: 1.4.4 | B35: 3 | C35: EQ-003 (Thermco Tube Furnace) — manufacturing & FAT | D35: Thermco / Engineering | E35: 20 | F35: 2 | G35: 22 | H35: Tube furnace FAT at Austin TX; recipe transfer
A36: 1.4.5 | B36: 3 | C36: EQ-005 (Brooks SCARA) — manufacturing & FAT | D36: Brooks / Engineering | E36: 14 | F36: 3 | G36: 17 | H36: Robot units FAT complete; MES integration tested
A37: 1.4.6 | B37: 3 | C37: EQ-008 (Linde Bulk Gas) — manufacturing | D37: Linde / Facilities | E37: 32 | F37: 1 | G37: 33 | H37: Longest LT: bulk vessel shipped on schedule
A38: 1.4.7 | B38: 3 | C38: Remaining equipment — manufacturing & FAT | D38: Various suppliers | E38: 10-18 | F38: 2 | G38: 20 | H38: All units pass FAT; no open NCRs
A39: 1.5 | B39: 2 | C39: LOGISTICS | D39: Supply Chain / Logistics | E39: 8 | F39: 15 | G39: 28 | H39: All equipment delivered to site; no customs holds
A40: 1.5.1 | B40: 3 | C40: International freight booking — JPY equipment | D40: Logistics | E40: 2 | F40: 15 | G40: 17 | H40: TEL, Daikin, Daifuku freight booked; sea freight
A41: 1.5.2 | B41: 3 | C41: International freight booking — EUR equipment | D41: Logistics | E41: 2 | F41: 15 | G41: 17 | H41: EUR equipment freight arranged; road/air options
A42: 1.5.3 | B42: 3 | C42: Customs clearance — all international equipment | D42: Trade Compliance | E42: 2 | F42: 17 | G42: 24 | H42: Customs cleared; duty paid; no holds
A43: 1.5.4 | B43: 3 | C43: Final delivery & receipt inspection — site | D43: Logistics / Engineering | E43: 3 | F43: 18 | G43: 28 | H43: All equipment received, inspected; CRs raised if needed
A44: 1.6 | B44: 2 | C44: SITE READINESS | D44: Facilities / Civil | E44: 20 | F44: 1 | G44: 20 | H44: All utilities ready; floor loading confirmed; permits
A45: 1.6.1 | B45: 3 | C45: Structural floor reinforcement — EQ-004 zone | D45: Civil Engineering | E45: 6 | F45: 3 | G45: 9 | H45: Floor certified for 680kg/m² furnace load
A46: 1.6.2 | B46: 3 | C46: Electrical infrastructure — transformers & feeds | D46: Electrical Engineering | E46: 10 | F46: 2 | G46: 12 | H46: 480V feeds complete; EQ-011 energized
A47: 1.6.3 | B47: 3 | C47: Cooling loop installation — glycol system | D47: Mechanical Engineering | E47: 8 | F47: 4 | G47: 12 | H47: Glycol loop pressure-tested; chiller tie-in complete
A48: 1.6.4 | B48: 3 | C48: Gas system infrastructure — hazmat permit | D48: Facilities / Regulatory | E48: 12 | F48: 1 | G48: 13 | H48: Hazmat permit received; gas lines installed
A49: 1.6.5 | B49: 3 | C49: Wi-Fi infrastructure upgrade — AMR/OT network | D49: IT/OT Engineering | E49: 6 | F49: 6 | G49: 12 | H49: Wi-Fi survey complete; AP installed; throughput confirmed
A50: 1.6.6 | B50: 3 | C50: Clean room / ESD zone preparation | D50: Facilities | E50: 4 | F50: 8 | G50: 12 | H50: ESD flooring installed; HVAC certified; gown area ready
... A66: 1.8.7 | B66: 3 | C66: G5 production release — handover to Operations | D66: PM / Process Eng / Ops | E66: 2 | F66: 44 | G66: 46 | H66: Formal handover complete; program closed

Sheet S07_CPM_Master_Schedule
A1: S07 — Critical Path Method (CPM) Master Schedule — Greenfield Expansion Phase II
A2: Activity durations in weeks | Program start: Week 1 = Apr-2025 | Owner: Sourabh Tarodekar | Critical path: EQ-002 Pfeiffer TMP chain = 46 weeks | Total Float = LS − ES = LF − EF | Activities with Float = 0 are on the Critical Path.
A4: Act ID | B4: WBS Ref | C4: Activity Description | D4: Responsible | E4: Duration (wks) | F4: Predecessor(s) | G4: Early Start (ES) | H4: Early Finish (EF) | I4: Late Start (LS) | J4: Late Finish (LF) | K4: Total Float | L4: Critical Path? | M4: Risk Flag | N4: Notes
A5: A01 | B5: 1.1.1 | C5: Program Kick-off & AR Execution | D5: PM / Finance | E5: 1 | F5: — | G5: 1 | H5: 1 | I5: 1 | J5: 1 | K5: =I5-G5 | L5: =IF(K5=0,"YES","NO") | M5: LOW | N5: Start node — AR signed, POs authorized
A6: A02 | B6: 1.2.1 | C6: RFQ Issue — Long-Lead Equipment | D6: Sourcing | E6: 1 | F6: A01 | G6: 2 | H6: 2 | I6: 2 | J6: 2 | K6: =I6-G6 | L6: =IF(K6=0,"YES","NO") | M6: LOW | N6: RFQs to Pfeiffer, TEL, AMAT, Linde
A7: A03 | B7: 1.3.1 | C7: Equipment Technical Spec Review | D7: Process Eng | E7: 2 | F7: A01 | G7: 2 | H7: 3 | I7: 2 | J7: 3 | K7: =I7-G7 | L7: =IF(K7=0,"YES","NO") | M7: LOW | N7: Specs signed off before RFQ response due
A8: A04 | B8: 1.2.2 | C8: Supplier Commercial Evaluation & BAFO | D8: Sourcing | E8: 2 | F8: A02,A03 | G8: 4 | H8: 5 | I8: 4 | J8: 5 | K8: =I8-G8 | L8: =IF(K8=0,"YES","NO") | M8: LOW | N8: Bid tabs; BAFO received from all
A9: A05 | B9: 1.2.7 | C9: FX Forward Contract Execution | D9: Finance | E9: 1 | F9: A04 | G9: 5 | H9: 5 | I9: 5 | J9: 5 | K9: =I9-G9 | L9: =IF(K9=0,"YES","NO") | M9: MOD | N9: EUR+JPY hedges before PO — finance gate
A10: A06 | B10: 1.2.4 | C10: PO Award — EQ-002 Pfeiffer TMP (CRITICAL) | D10: Sourcing | E10: 1 | F10: A04,A05 | G10: 6 | H10: 6 | I10: 6 | J10: 6 | K10: =I10-G10 | L10: =IF(K10=0,"YES","NO") | M10: HIGH | N10: CRITICAL PATH anchor — 26-wk mfg starts here
A11: A07 | B11: 1.2.3 | C11: PO Award — EQ-014 AMAT RTP | D11: Sourcing | E11: 1 | F11: A04,A05 | G11: 6 | H11: 6 | I11: 7 | J11: 7 | K11: =I11-G11 | L11: =IF(K11=0,"YES","NO") | M11: MOD | N11: 1-wk float; 30% deposit = $437.5K at PO
A12: A08 | B12: 1.2.5 | C12: PO Award — EQ-004 TEL Batch Furnace | D12: Sourcing | E12: 1 | F12: A04,A05 | G12: 6 | H12: 6 | I12: 8 | J12: 8 | K12: =I12-G12 | L12: =IF(K12=0,"YES","NO") | M12: MOD | N12: 2-wk float; JPY hedge confirmed
A13: A09 | B13: 1.2.6 | C13: PO Award — All Remaining Equipment | D13: Sourcing | E13: 2 | F13: A04,A05 | G13: 6 | H13: 7 | I13: 6 | J13: 7 | K13: =I13-G13 | L13: =IF(K13=0,"YES","NO") | M13: LOW | N13: EQ-001,003,005,006,007,008,009,010,011,012,013,015
A14: A10 | B14: 1.3.4 | C14: Site Layout & Equipment Placement Freeze | D14: Facilities | E14: 3 | F14: A01 | G14: 2 | H14: 4 | I14: 2 | J14: 4 | K14: =I14-G14 | L14: =IF(K14=0,"YES","NO") | M14: LOW | N14: Civil works blocked until layout approved
A15: A11 | B15: 1.6.4 | C15: Gas System / Hazmat Permit | D15: Facilities/Regulatory | E15: 12 | F15: A10 | G15: 5 | H15: 16 | I15: 5 | J15: 16 | K15: =I15-G15 | L15: =IF(K15=0,"YES","NO") | M15: CRIT | N15: CRITICAL — permit on critical path; submit immediately
A16: A12 | B16: 1.6.2 | C16: Electrical Infrastructure (Transformers) | D16: Electrical Eng | E16: 10 | F16: A10 | G16: 5 | H16: 14 | I16: 5 | J16: 14 | K16: =I16-G16 | L16: =IF(K16=0,"YES","NO") | M16: MOD | N16: 480V feeds; EQ-011 transformer on order wk1
... A43: A39 | B43: 1.8.7 | C43: G5 Production Release — Program Close | D43: PM/Ops | E43: 2 | F43: A38 | G43: 46 | H43: 47 | I43: 46 | J43: 47 | K43: =I43-G43 | L43: =IF(K43=0,"YES","NO") | M43: LOW | N43: Formal handover; program closed
A46: CRITICAL PATH SUMMARY
A47: Total program duration (critical path, weeks) | B47: =MAX(H5:H43)
A48: Number of critical path activities (Float = 0) | B48: =COUNTIF(K5:K43,0)
A49: Critical path sequence | B49: A01 → A06 → A15 → A23 → A28 → A31 → A34/35/36/37 → A38 → A39
A50: Longest chain | B50: EQ-002 Pfeiffer TMP: PO → 26-wk mfg → FAT → freight → install → PQ; spans Weeks 6-44
A51: Key schedule risk | B51: A11 Gas System / Hazmat Permit — 12-week permit must start Week 5; any delay blocks gas system install
A52: Key commercial risk | B52: A06 EQ-002 Pfeiffer PO — single-source; no float; 30-day PO delay = 30-day program delay

Sheet S08_Program_Milestone_Roadmap
A1: S08 — Program Milestone Roadmap — Greenfield Expansion Phase II
A2: Phase-gate roadmap from AR approval to production release | Owner: Sourabh Tarodekar | All dates Apr-Dec 2025 | Gates: G0 (Concept) -> G5 (Production Release)
A4: PROGRAM GATES
A5: Gate | B5: Month | C5: Status Label
A6: G0+G1 | B6: Apr-25 | C6: Approved
A7: G2 | B7: Aug-25 | C7: FAT Complete
A8: G3 | B8: Oct-25 | C8: Install
A9: G4 | B9: Nov-25 | C9: PQ Start
A10: G5 | B10: Dec-25 | C10: Production Release
A12: KEY PROGRAM MILESTONES
A13: # | B13: Milestone | C13: Gate | D13: Target Date | E13: Status | F13: Owner | G13: Notes
A14: M01 | B14: AR Approved — Phase II | C14: G0/G1 | D14: 2025-04-07 | E14: APPROVED | F14: Sourabh Tarodekar | G14: Long-lead PO authority granted; cost centre CC-4421 open
A15: M02 | B15: All Long-Lead POs Placed | C15: G1 | D15: 2025-04-28 | E15: COMPLETE | F15: Sourcing | G15: EQ-002,004,008,014 POs placed; FX hedges executed
A16: M03 | B16: Site Layout Frozen | C16: — | D16: 2025-04-14 | E16: APPROVED | F16: Facilities | G16: Civil works can proceed; no further layout changes
A17: M04 | B17: Hazmat Permit Submitted | C17: — | D17: 2025-04-14 | E17: IN PROGRESS | F17: Regulatory | G17: Permit application filed; 12-wk processing time
A18: M05 | B18: All Equipment POs Placed | C18: G1 | D18: 2025-05-12 | E18: COMPLETE | F18: Sourcing | G18: Full PO portfolio placed; supplier schedule confirmed
A19: M06 | B19: Site Utilities Complete (Elec + Cool) | C19: — | D19: 2025-08-11 | E19: ON TRACK | F19: Facilities | G19: Electrical feeds + glycol loop ready before delivery
A20: M07 | B20: Hazmat Permit Received | C20: — | D20: 2025-07-07 | E20: ON TRACK | F20: Regulatory | G20: CRITICAL — blocks gas system install if delayed
A21: M08 | B21: EQ-014 AMAT RTP FAT Complete | C21: G2 | D21: 2025-09-22 | E21: ON TRACK | F21: Engineering | G21: First FAT complete; highest-value item
A22: M09 | B22: EQ-002 Pfeiffer TMP FAT Complete | C22: G2 | D22: 2025-10-20 | E22: CRITICAL PATH | F22: Engineering / Pfeiffer | G22: CRITICAL PATH — no float; monitor weekly
A23: M10 | B23: All Equipment Delivered to Site | C23: G3 | D23: 2025-10-27 | E23: ON TRACK | F23: Logistics | G23: All 15 platforms on-site; receipt inspection complete
A24: M11 | B24: All Equipment Installed | C24: G3 | D24: 2025-11-10 | E24: ON TRACK | F24: Installation | G24: Mechanical install + utility tie-in complete
... A28: M15 | B28: G5 Production Release | C28: G5 | D28: 2025-12-22 | E28: PLANNED | F28: Sourabh Tarodekar | G28: Formal handover to Operations; program closed

Sheet S09_Deployment_Timeline
A1: S09 — Equipment Deployment Timeline & Critical Path Model — CapEx Phase II Program
A2: All durations in weeks | Program Start: Week 1 (2025-Q2) | Critical Path items highlighted in RED | Inputs in BLUE | [MFG] Mfg [FAT] Factory Accept. Test [SHP] Shipping [INS] Installation [UTL] Utility Hookup [PQ] Process Qual
A4: Equipment ID | B4: Equipment / Tool | C4: Supplier | D4: Mfg (wks) | E4: FAT (wks) | F4: Shipping (wks) | G4: Installation (wks) | H4: Utility Hookup (wks) | I4: Process Qual (wks) | J4: Total Deploy Duration (wks) | K4: Program Start Week | L4: Delivery/Install Compl. (Wk#) | M4: PQ Complete (Wk#) | N4: Critical Path? | O4: Float (wks) | P4: Risk Flag | Q4: Predecessor Dependency | R4: Engineering Notes
A5: EQ-014 | B5: RTP – Applied Materials (CRITICAL PATH) | C5: AMAT | D5: 24 | E5: 2 | F5: 3 | G5: 4 | H5: 2 | I5: 6 | J5: =SUM(D5:I5) | K5: 1 | L5: =K5+J5-F5 | M5: =K5+J5 | N5: YES | O5: =IF(N5="YES",0,4) | P5: HIGH | Q5: None — first install | R5: Highest-value item; finance AR approval gate at Week 2; 30% deposit required; longest total duration
A6: EQ-004 | B6: Batch Oxidation Furnace | C6: TEL | D6: 28 | E6: 2 | F6: 3 | G6: 4 | H6: 2 | I6: 5 | J6: =SUM(D6:I6) | K6: 1 | L6: =K6+J6-F6 | M6: =K6+J6 | N6: YES | O6: =IF(N6="YES",0,4) | P6: HIGH | Q6: EQ-013 (pump) must install first | R6: JPY FX exposure; overseas FAT at TEL Japan; import clearance estimated 1 week
A7: EQ-003 | B7: Tube Furnace System | C7: Thermco | D7: 20 | E7: 2 | F7: 3 | G7: 4 | H7: 2 | I7: 5 | J7: =SUM(D7:I7) | K7: 2 | L7: =K7+J7-F7 | M7: =K7+J7 | N7: YES | O7: =IF(N7="YES",0,4) | P7: MODERATE | Q7: EQ-013 (pump) must install first | R7: Parallel install path with EQ-004 possible; process recipe transfer at FAT
A8: EQ-006 | B8: Overhead Track Conveyor | C8: Daifuku | D8: 30 | E8: 2 | F8: 3 | G8: 5 | H8: 2 | I8: 0 | J8: =SUM(D8:I8) | K8: 1 | L8: =K8+J8-F8 | M8: =K8+J8 | N8: YES | O8: =IF(N8="YES",0,4) | P8: HIGH | Q8: Civil mounts must be complete (Week 8) | R8: Civil interface drawings required 8 wks before delivery; structural review required
A9: EQ-002 | B9: Turbomolecular Pump | C9: Pfeiffer | D9: 26 | E9: 2 | F9: 3 | G9: 3 | H9: 1 | I9: 0 | J9: =SUM(D9:I9) | K9: 1 | L9: =K9+J9-F9 | M9: =K9+J9 | N9: YES | O9: =IF(N9="YES",0,4) | P9: CRITICAL | Q9: EQ-003, EQ-004 dependent | R9: SINGLE SOURCE – CRITICAL RISK; no qualified alt; escalated to VP; daily status
A10: EQ-008 | B10: Bulk Gas Storage | C10: Linde | D10: 32 | E10: 2 | F10: 3 | G10: 5 | H10: 3 | I10: 0 | J10: =SUM(D10:I10) | K10: 1 | L10: =K10+J10-F10 | M10: =K10+J10 | N10: YES | O10: =IF(N10="YES",0,4) | P10: HIGH | Q10: EQ-007 (gas cabinet) install after | R10: Longest lead time in portfolio (32 wks mfg); PO must be placed Week 1; civil pad parallel
A11: EQ-001 | B11: Dry Screw Vacuum Pump | C11: Edwards | D11: 18 | E11: 2 | F11: 3 | G11: 3 | H11: 1 | I11: 0 | J11: =SUM(D11:I11) | K11: 2 | L11: =K11+J11-F11 | M11: =K11+J11 | N11: No | O11: =IF(N11="YES",0,4) | P11: MODERATE | Q11: EQ-003 dependent | R11: Alt vendor (Busch) available; paired install with EQ-013; N2 purge line required
A12: EQ-013 | B12: Roots Blower Booster | C12: Busch | D12: 15 | E12: 2 | F12: 3 | G12: 3 | H12: 1 | I12: 0 | J12: =SUM(D12:I12) | K12: 2 | L12: =K12+J12-F12 | M12: =K12+J12 | N12: No | O12: =IF(N12="YES",0,4) | P12: LOW | Q12: EQ-001 must install first | R12: Paired with EQ-001; coordinated delivery schedule; low supply risk
A13: EQ-007 | B13: Gas Cabinet | C13: Air Liquide | D13: 22 | E13: 2 | F13: 3 | G13: 4 | H13: 2 | I13: 0 | J13: =SUM(D13:I13) | K13: 2 | L13: =K13+J13-F13 | M13: =K13+J13 | N13: No | O13: =IF(N13="YES",0,4) | P13: MODERATE | Q13: EQ-008 (bulk gas) commissioned first | R13: Hazmat permit on critical path; permit application must be filed immediately
A14: EQ-005 | B14: SCARA Robot (x6) | C14: Brooks | D14: 14 | E14: 2 | F14: 3 | G14: 4 | H14: 1 | I14: 0 | J14: =SUM(D14:I14) | K14: 3 | L14: =K14+J14-F14 | M14: =K14+J14 | N14: No | O14: =IF(N14="YES",0,4) | P14: MODERATE | Q14: EQ-006 (conveyor) operational first | R14: MES integration requires 4 wks; SW engineer on-site for FAT and site install
A15: EQ-009 | B15: DCS – Siemens S7-1500 (x5) | C15: — | D15: 14 | E15: 2 | F15: 3 | G15: 3 | H15: 1 | I15: 0 | J15: =SUM(D15:I15) | K15: 2 | L15: =K15+J15-F15 | M15: =K15+J15 | N15: No | O15: =IF(N15="YES",0,4) | P15: LOW | Q15: None — independent | R15: Cybersecurity review adds 3 wks; submit InfoSec package 6 wks pre-install
A16: EQ-010 | B16: SCADA Platform | C16: Inductive Automation | D16: 0 | E16: 2 | F16: 0 | G16: 2 | H16: 1 | I16: 0 | J16: =SUM(D16:I16) | K16: 4 | L16: =K16+J16-F16 | M16: =K16+J16 | N16: No | O16: =IF(N16="YES",0,4) | P16: LOW | Q16: EQ-009 DCS must be installed | R16: Software license; no physical shipping; IT infrastructure and server required on-site first
... A19: EQ-015 | B19: AMR Fleet (x10) | C19: MiR | D19: 18 | E19: 2 | F19: 3 | G19: 3 | H19: 1 | I19: 0 | J19: =SUM(D19:I19) | K19: 5 | L19: =K19+J19-F19 | M19: =K19+J19 | N19: No | O19: =IF(N19="YES",0,4) | P19: LOW | Q19: EQ-006 (conveyor) track complete | R19: Wi-Fi infrastructure upgrade required 6 wks before delivery; IT lead time on critical path
A22: PROGRAM SCHEDULE SUMMARY
A23: Earliest Equipment Delivery (Week #) | B23: =MIN(L5:L19)
A24: Latest PQ Completion (Week #) | B24: =MAX(M5:M19)
A25: Critical Path Duration (Program End, weeks) | B25: =MAX(M5:M19)
A26: Total Equipment Platforms | B26: =COUNTA(A5:A19)
A27: Critical Path Items | B27: =COUNTIF(N5:N19,"YES")
A28: HIGH or CRITICAL Risk Items | B28: =COUNTIF(P5:P19,"HIGH")+COUNTIF(P5:P19,"CRITICAL")
A29: Avg Total Deployment Duration (wks) | B29: =AVERAGE(J5:J19)
A30: Items with Zero Float (No Schedule Flexibility) | B30: =COUNTIF(O5:O19,0)

Sheet S10_Capacity_Planning
A1: S10 — Capacity Planning Model — Annual Production Capacity Supported by Equipment Portfolio
A2: Inputs from S02_Equipment_Portfolio and S01_Disclaimer_Assumptions | Identifies bottlenecks | Models +20% demand surge scenario
A4: CAPACITY MODEL PARAMETERS
A5: Parameter | B5: Value | C5: Unit | D5: Source
A6: Equipment Uptime (%) | B6: ='S01_Disclaimer_Assumptions'!$B$30 | D6: S01 — 92% target
A7: Planned Maint Downtime (%) | B7: ='S01_Disclaimer_Assumptions'!$B$31 | D7: S01 — 4% allocated
A8: Effective Uptime (%) | B8: =B6-B7 | D8: Uptime minus Planned Maint (formula)
A9: Process Yield (%) | B9: ='S01_Disclaimer_Assumptions'!$B$32 | D9: S01 — 96% yield
A10: Baseline Demand (units/yr) | B10: 750000 | D10: Engineering baseline — current program requirement
A11: Surge Scenario (+20%) Demand (units/yr) | B11: =B10*1.2 | D11: Stress test: 20% volume increase
A13: EQUIPMENT CAPACITY MODEL — BASELINE vs SURGE SCENARIO
A14: Equipment ID | B14: Equipment Category | C14: Tool Type | D14: Throughput (units/hr) | E14: Quantity | F14: Op Hours/Year | G14: Effective Uptime (%) | H14: Annual Capacity (units/yr) | I14: Baseline Demand (units/yr) | J14: Capacity Cushion (units) | K14: Tool Contribution to Portfolio Cap (%) | L14: Surge Demand (+20%, units/yr) | M14: Surge Contribution (%) | N14: Bottleneck Flag
A15: EQ-001 | B15: Vacuum Pump System | C15: Dry Screw Vacuum Pump | D15: N/A | E15: 4 | F15: 8320 | G15: =$B$8 | H15: — | I15: — | J15: — | K15: — | L15: — | M15: — | N15: SUPPORT EQUIPMENT
A16: EQ-002 | B16: Vacuum Pump System | C16: Turbomolecular Pump Assembly | D16: N/A | E16: 3 | F16: 8320 | G16: =$B$8 | H16: — | I16: — | J16: — | K16: — | L16: — | M16: — | N16: SUPPORT EQUIPMENT
A17: EQ-003 | B17: High-Temp Furnace | C17: Tube Furnace System – 8-zone | D17: 24 | E17: 2 | F17: 8320 | G17: =$B$8 | H17: =D17*E17*F17*G17*$B$9 | I17: =$B$10 | J17: =H17-I17 | K17: =I17/H17 | L17: =$B$11 | M17: =L17/H17 | N17: ⚠ BOTTLENECK (portfolio-level surge >72% utilization)
A18: EQ-004 | B18: High-Temp Furnace | C18: Batch Oxidation Furnace | D18: 18 | E18: 2 | F18: 8320 | G18: =$B$8 | H18: =D18*E18*F18*G18*$B$9 | I18: =$B$10 | J18: =H18-I18 | K18: =I18/H18 | L18: =$B$11 | M18: =L18/H18 | N18: ⚠ BOTTLENECK (portfolio-level surge >72% utilization)
A19: EQ-005 | B19: Robotics / Automation | C19: SCARA Wafer Transfer Robot | D19: N/A | E19: 6 | F19: 8320 | G19: =$B$8 | H19: — | I19: — | J19: — | K19: — | L19: — | M19: — | N19: SUPPORT EQUIPMENT
A20: EQ-006 | B20: Robotics / Automation | C20: Overhead Track Conveyor | D20: N/A | E20: 1 | F20: 8320 | G20: =$B$8 | H20: — | I20: — | J20: — | K20: — | L20: — | M20: — | N20: SUPPORT EQUIPMENT
A21: EQ-007 | B21: Gas Handling System | C21: Process Gas Cabinet | D21: N/A | E21: 4 | F21: 8320 | G21: =$B$8 | H21: — | I21: — | J21: — | K21: — | L21: — | M21: — | N21: SUPPORT EQUIPMENT
A22: EQ-009 | B22: PLC Control System | C22: DCS – Siemens S7-1500 | D22: N/A | E22: 5 | F22: 8320 | G22: =$B$8 | H22: — | I22: — | J22: — | K22: — | L22: — | M22: — | N22: SUPPORT EQUIPMENT
A23: EQ-011 | B23: Facility Infra | C23: Dry-Type Transformer | D23: N/A | E23: 2 | F23: 8760 | G23: =$B$8 | H23: — | I23: — | J23: — | K23: — | L23: — | M23: — | N23: SUPPORT EQUIPMENT
A24: EQ-012 | B24: Facility Infra – Cooling | C24: Process Chiller System | D24: N/A | E24: 3 | F24: 8760 | G24: =$B$8 | H24: — | I24: — | J24: — | K24: — | L24: — | M24: — | N24: SUPPORT EQUIPMENT
A25: EQ-013 | B25: Vacuum Pump System | C25: Roots Blower Booster | D25: N/A | E25: 6 | F25: 8320 | G25: =$B$8 | H25: — | I25: — | J25: — | K25: — | L25: — | M25: — | N25: SUPPORT EQUIPMENT
A26: EQ-014 | B26: High-Temp Furnace | C26: RTP – Rapid Thermal Processor | D26: 32 | E26: 2 | F26: 8320 | G26: =$B$8 | H26: =D26*E26*F26*G26*$B$9 | I26: =$B$10 | J26: =H26-I26 | K26: =I26/H26 | L26: =$B$11 | M26: =L26/H26 | N26: ⚠ BOTTLENECK (portfolio-level surge >72% utilization)
A27: EQ-015 | B27: Robotics / Automation | C27: AMR Fleet (x10) | D27: N/A | E27: 1 | F27: 8320 | G27: =$B$8 | H27: — | I27: — | J27: — | K27: — | L27: — | M27: — | N27: SUPPORT EQUIPMENT
A30: CAPACITY SUMMARY & BOTTLENECK ANALYSIS
A31: Total Annual Capacity (Process Tools Only) | B31: =SUM(H17,H18,H26)
A32: Baseline Demand | B32: =B10
A33: Baseline Capacity Cushion | B33: =B31-B32
A34: Baseline Utilization | B34: =B29/B31
A35: Surge Demand (+20%) | B35: =B11
A36: Bottleneck Equipment (Surge) | B36: Batch Oxidation Furnace (EQ-004) — lowest individual Annual Capacity among process tools
A37: Max Surge Utilization | B37: =B11/B31

Sheet S11_Demand_Forecast
A1: S11 — Demand Forecast Model — Advanced Manufacturing Program (2023-2025)
A2: Time-series demand forecast by product family | Owner: Sourabh Tarodekar | Feeds S10_Capacity_Planning (baseline demand input) | Forecast accuracy tracked quarterly
A4: FORECAST ASSUMPTIONS
A5: Baseline Annual Demand (2025 program target) | B5: 750000
A6: Surge Scenario (+20%) | B6: 900000
A7: Downside Scenario (-20%) | B7: 600000
A8: Committed Customer Volume (Phase II driver, incremental) | B8: 312000
A10: QUARTERLY FORECAST vs ACTUALS — 2023 THROUGH 2025
A11: Period | B11: Baseline Forecast | C11: Upside (+20%) | D11: Downside (-20%) | E11: Actual/Committed | F11: Forecast Accuracy (%) | G11: Rolling 3-Qtr Avg | H11: Variance vs Fcst | I11: Status | J11: Forecast Source | K11: Notes
A12: Q1-2023 | B12: 520000 | C12: =B12*1.2 | D12: =B12*0.8 | E12: 505000 | F12: =E12/B12 | G12: TBC | H12: =E12-B12 | I12: ACTUAL | J12: S&OP Review | K12: Production ramp; new process tools qualified Q1
A13: Q2-2023 | B13: 540000 | C13: =B13*1.2 | D13: =B13*0.8 | E13: 528000 | F13: =E13/B13 | G13: TBC | H13: =E13-B13 | I13: ACTUAL | J13: S&OP Review | K13: Slight volume shortfall; MES integration delay
A14: Q3-2023 | B14: 565000 | C14: =B14*1.2 | D14: =B14*0.8 | E14: 571000 | F14: =E14/B14 | G14: =IFERROR(AVERAGE(E12:E14),AVERAGE(E12:E13)) | H14: =E14-B14 | I14: ACTUAL | J14: S&OP Review | K14: On track; customer pull-in request +6K units
A15: Q4-2023 | B15: 575000 | C15: =B15*1.2 | D15: =B15*0.8 | E15: 567000 | F15: =E15/B15 | G15: =IFERROR(AVERAGE(E13:E15),AVERAGE(E13:E14)) | H15: =E15-B15 | I15: ACTUAL | J15: S&OP Review | K15: Seasonal demand pattern confirmed
A16: Q1-2024 | B16: 590000 | C16: =B16*1.2 | D16: =B16*0.8 | E16: 580000 | F16: =E16/B16 | G16: =IFERROR(AVERAGE(E14:E16),AVERAGE(E14:E15)) | H16: =E16-B16 | I16: ACTUAL | J16: S&OP Review | K16: Q1 softness as expected; customer forecast revised
A17: Q2-2024 | B17: 610000 | C17: =B17*1.2 | D17: =B17*0.8 | E17: 624000 | F17: =E17/B17 | G17: =IFERROR(AVERAGE(E15:E17),AVERAGE(E15:E16)) | H17: =E17-B17 | I17: ACTUAL | J17: S&OP Review | K17: Strong pull; customer volume commitment +35K
A18: Q3-2024 | B18: 630000 | C18: =B18*1.2 | D18: =B18*0.8 | E18: 618000 | F18: =E18/B18 | G18: =IFERROR(AVERAGE(E16:E18),AVERAGE(E16:E17)) | H18: =E18-B18 | I18: ACTUAL | J18: S&OP Review | K18: Slight miss due to competitor product shift
A19: Q4-2024 | B19: 650000 | C19: =B19*1.2 | D19: =B19*0.8 | E19: 661000 | F19: =E19/B19 | G19: =IFERROR(AVERAGE(E17:E19),AVERAGE(E17:E18)) | H19: =E19-B19 | I19: ACTUAL | J19: S&OP Review | K19: Year-end strong; customer forecast upgrade for 2025 Phase II program
A20: Q1-2025 | B20: 680000 | C20: =B20*1.2 | D20: =B20*0.8 | E20: 675000 | F20: =E20/B20 | G20: =IFERROR(AVERAGE(E18:E20),AVERAGE(E18:E19)) | H20: =E20-B20 | I20: ACTUAL | J20: S&OP Review | K20: Phase II program approved; capacity expansion underway
A21: Q2-2025 | B21: 710000 | C21: =B21*1.2 | D21: =B21*0.8 | E21: 718000 | F21: =E21/B21 | G21: =IFERROR(AVERAGE(E19:E21),AVERAGE(E19:E20)) | H21: =E21-B21 | I21: ACTUAL | J21: S&OP Review | K21: All POs placed; equipment in fabrication
A22: Q3-2025 | B22: 735000 | C22: =B22*1.2 | D22: =B22*0.8 | E22: TBC | F22: TBC | G22: =IFERROR(AVERAGE(E20:E22),AVERAGE(E20:E21)) | H22: TBC | I22: FORECAST | J22: S&OP Review | K22: Forecast confirmed; delivery/install on schedule
A23: Q4-2025 | B23: 750000 | C23: =B23*1.2 | D23: =B23*0.8 | E23: TBC | F23: TBC | G23: =IFERROR(AVERAGE(E21:E23),AVERAGE(E21:E22)) | H23: TBC | I23: FORECAST | J23: S&OP Review | K23: TARGET: G5 production release; full capacity online
A26: DEMAND BY PRODUCT FAMILY — 2025 ANNUAL FORECAST
A27: Product Family | B27: Description | C27: 2023 Actual | D27: 2024 Actual | E27: Q1-2025 | F27: Q2-2025 | G27: Q3-2025 | H27: Q4-2025 | I27: 2025 Forecast | J27: CAGR 2023->25 | K27: Required Capacity (u/hr) | L27: Constrained by Equip | M27: Priority
A28: PF-A | B28: Advanced Process Products (High-Temp Furnace) | C28: 210000 | D28: 260000 | E28: 70000 | F28: 73000 | G28: 78000 | H28: 79000 | I28: =SUM(E28:H28) | J28: =IFERROR((I28/C28)^(1/2)-1,0) | K28: =I28/8320/0.88/0.96 | L28: EQ-003/004 | M28: 1
A29: PF-B | B29: Precision Robotics Assembly | C29: 150000 | D29: 190000 | E29: 54000 | F29: 56000 | G29: 58000 | H29: 57000 | I29: =SUM(E29:H29) | J29: =IFERROR((I29/C29)^(1/2)-1,0) | K29: =I29/8320/0.88/0.96 | L29: EQ-005 | M29: 2
A30: PF-C | B30: Gas-Phase Deposition (RTP Products) | C30: 115000 | D30: 142000 | E30: 36000 | F30: 37000 | G30: 38000 | H30: 39000 | I30: =SUM(E30:H30) | J30: =IFERROR((I30/C30)^(1/2)-1,0) | K30: =I30/8320/0.88/0.96 | L30: EQ-014 | M30: 3
A31: PF-D | B31: Infrastructure / Support Builds | C31: 75000 | D31: 58000 | E31: 18000 | F31: 18500 | G31: 19000 | H31: 19500 | I31: =SUM(E31:H31) | J31: =IFERROR((I31/C31)^(1/2)-1,0) | K31: =I31/8320/0.88/0.96 | L31: EQ-009/010 | M31: 4
A32: TOTAL | B32: All Product Families | C32: =SUM(C28:C31) | D32: =SUM(D28:D31) | E32: =SUM(E28:E31) | F32: =SUM(F28:F31) | G32: =SUM(G28:G31) | H32: =SUM(H28:H31) | I32: =SUM(I28:I31)

Sheet S12_AR_Summary
A1: S12 — Capital Appropriations Request (AR) Summary — Greenfield Expansion Phase II
A2: Prepared by: Sourabh Tarodekar, Program Manager | Submitted to: VP Engineering & CFO | Date: 2025-Q1 | AR Number: AR-2025-0082
A4: PROGRAM INFORMATION
A5: Program Name | B5: Greenfield Expansion Phase II — Advanced Manufacturing Facility | C5: Business Unit | D5: Semiconductor & Advanced Process Division
A6: Program Manager | B6: Sourabh Tarodekar | C6: Finance Partner | D6: R. Patel
A7: AR Reference | B7: AR-2025-0082 | C7: Revision | D7: Rev 1.0 — Initial Submission
A8: Submission Date | B8: 2025-03-19 | C8: Required Approval By | D8: 2025-04-07 (Week 4 — Long-lead PO gate)
A9: Program Start | B9: 2025-Q2 (Week 1) | C9: Program End | D9: 2025-Q4 (Week 47 — PQ Complete)
A10: Approval Authority | B10: VP Engineering + CFO (>$10M threshold) | C10: Cost Centre | D10: CC-4421 — Manufacturing Capital Projects
A12: BUSINESS CASE SUMMARY
A13: This appropriations request funds the capital equipment procurement, installation, and qualification of 15 equipment platforms required to establish a new advanced manufacturing process line within the Greenfield Expansion Phase II facility. The program supports a committed customer volume increase of 35% beginning 2025-Q4, requiring new process capacity that cannot be delivered by existing installed equipment. The recommended investment (Scenario B — Baseline Program) delivers 312,000 units/year annual capacity at 92% uptime, with a 10-year NPV of $9.5M over the minimum-CapEx alternative. The program is expected to achieve first production output by Week 47 (2025-Q4).
A15: CAPITAL BUDGET SUMMARY
A16: Cost Category | B16: Equipment Count | C16: Unit Cost Range (USD) | D16: Total Equipment Cost (USD) | E16: Installation Cost (USD) | F16: Total Line Item (USD) | G16: % of Total CapEx
A17: Vacuum Pump Systems | B17: 3 | C17: $125K-$310K | D17: 2420000 | E17: 256000 | F17: =D17+E17 | G17: =F17/$F$23
A18: High-Temperature Furnaces | B18: 3 | C18: $520K-$875K | D18: 4150000 | E18: 314000 | F18: =D18+E18 | G18: =F18/$F$23
A19: Robotics & Automation | B19: 3 | C19: $275K-$420K | D19: 2450000 | E19: 238000 | F19: =D19+E19 | G19: =F19/$F$23
A20: Gas Handling Systems | B20: 2 | C20: $195K-$340K | D20: 1120000 | E20: 248000 | F20: =D20+E20 | G20: =F20/$F$23
A21: PLC / Control Systems | B21: 2 | C21: $85K-$165K | D21: 1080000 | E21: 99000 | F21: =D21+E21 | G21: =F21/$F$23
A22: Facility Infrastructure | B22: 2 | C22: $210K-$295K | D22: 1305000 | E22: 190000 | F22: =D22+E22 | G22: =F22/$F$23
A23: SUBTOTAL — Equipment + Installation | D23: =SUM(D17:D22) | E23: =SUM(E17:E22) | F23: =D23+E23 | G23: 1
A24: Contingency Reserve (10% of CapEx) | F24: =F23*0.10
A25: FX Hedge Reserve (EUR + JPY exposure) | F25: 485000
A26: Engineering NRE & Program Management | F26: 320000
A27: TOTAL APPROPRIATIONS REQUEST (USD) | F27: =F23+F24+F25+F26
A29: Budget Reconciliation Note: Equipment and installation totals above are derived directly from S02_Equipment_Portfolio (Equipment Purchase Total, Installation Total, Combined CapEx). Scenario Analysis (S13) Scenario B budget of $40.04M represents a broader multi-phase strategic program comparison with different cost assumptions and is not directly comparable to this Phase II AR.
A31: FINANCIAL JUSTIFICATION & RETURN METRICS
A32: Metric | B32: Value | C32: Unit | D32: Basis / Source
A33: 10-Year NPV of Investment (vs Min-CapEx alternative) | B33: 9520000 | C33: $ | D33: Linked to S13 Scenario B vs A NPV calculation
A34: Estimated IRR | B34: 0.142 | C34: % | D34: Based on incremental OpEx savings over 10 years at 8% WACC
A35: Simple Payback Period | B35: 4.2 | C35: yrs | D35: Payback of incremental CapEx vs Scenario A through OpEx savings
A36: Annual Production Capacity Enabled | B36: 312000 | C36: units | D36: At 92% uptime; S10 Capacity Planning model
A37: Annual OpEx Savings vs Scenario A | B37: 1390000 | C37: $/yr | D37: Energy + maintenance + downtime reduction
A38: Equipment Depreciation Method | B38: MACRS 7-yr | C38: — | D38: Per Finance / Tax Counsel guidance
A39: After-Tax IRR (21% effective rate) | B39: 0.112 | C39: % | D39: Estimated; Finance to confirm in detailed model
A40: Revenue Enabled (at $145/unit avg selling price) | B40: 45240000 | C40: $/yr | D40: Based on 312K units x $145 ASP
A42: KEY RISKS & MITIGATIONS (SUMMARY FOR APPROVERS)
A43: Risk | B43: Impact | C43: Probability | D43: Mitigation | E43: Residual Risk
A44: EQ-002 Pfeiffer single-source — no qualified alt supplier | B44: Schedule delay 4-8 wks if pump fails or delivery slips | C44: MODERATE | D44: Safety stock of 2 units; alt vendor qual in parallel (Shimadzu) | E44: LOW-MODERATE
A45: EQ-007 hazmat permit lead time exceeds program schedule | B45: Gas system install delayed 2+ wks — blocks furnace PQ | C45: MODERATE | D45: Expedited permit via regulatory consultant; contingency bottle gas supply | E45: LOW
A46: JPY/EUR FX adverse movement (>5%) | B46: Up to $285K budget overrun on EUR/JPY equipment | C46: LOW | D46: Forward FX contracts executed; FX reserve in AR | E46: LOW
A47: EQ-004 structural floor reinforcement scope growth | B47: Additional $30-50K if reinforcement scope expands | C47: LOW | D47: Structural engineer engaged; early assessment complete | E47: VERY LOW
A48: Customer demand shortfall vs forecast | B48: Reduced ROI; excess capacity created | C48: LOW | D48: Program phased — Phase III expansion deferred if demand misses | E48: LOW
A50: EXECUTIVE RECOMMENDATION
A51: RECOMMENDATION: APPROVE — Scenario B Baseline Program ($40.04M total budget)
A52: The investment delivers a 14.2% IRR against an 8.0% hurdle rate, a 4.2-year payback, and $9.5M NPV over 10 years vs the minimum-CapEx alternative. Revenue enabled of $45.2M/yr supports the committed customer volume increase of 35% from 2025-Q4. All financial metrics exceed approval thresholds.

Sheet S13_Scenario_Analysis
A1: S13 — Scenario Analysis — CapEx Program Investment Decision Framework
A2: Compares three capital investment scenarios across NPV, TCO, capacity, supply chain risk, and schedule | Scenario A = Minimum CapEx (Low Upfront / Higher OpEx) | Scenario B = Baseline Program (Balanced) | Scenario C = Premium Build (High CapEx / Lowest OpEx)
A4: CAPITAL EXPENDITURE (CAPEX)
A5: Parameter | B5: Units | C5: Scenario A | D5: Scenario B | E5: Scenario C | F5: B vs A Delta | G5: C vs B Delta | H5: Best Scenario | I5: Notes
A6: Total Equipment Purchase Cost | B6: $ | C6: 24500000 | D6: 32800000 | E6: 38500000 | F6: =D6-C6 | G6: =E6-D6 | H6: Scenario B | I6: Scenario A uses domestic/value suppliers; C uses premium OEM across all platforms
A7: Total Installation Cost | B7: $ | C7: 2800000 | D7: 3600000 | E7: 4200000 | F7: =D7-C7 | G7: =E7-D7 | H7: Scenario A | I7: Installation costs scale with equipment complexity and supplier requirements
A8: Total CapEx (Equipment + Install) | B8: $ | C8: 27300000 | D8: 36400000 | E8: 42700000 | F8: =D8-C8 | G8: =E8-D8 | H8: Scenario A | I8: Formula: Purchase + Install; Scenario A ~33% lower CapEx than C
A9: Contingency Reserve (10% of CapEx) | B9: $ | C9: 2730000 | D9: 3640000 | E9: 4270000 | F9: =D9-C9 | G9: =E9-D9 | H9: Scenario A | I9: Standard 10% contingency; Scenario C highest absolute contingency
A10: Total Program Budget (incl. contingency) | B10: $ | C10: 30030000 | D10: 40040000 | E10: 46970000 | F10: =D10-C10 | G10: =E10-D10 | H10: Scenario A | I10: Total appropriations request basis for each scenario
A12: OPERATING EXPENDITURE (OPEX — ANNUAL)
A13: Parameter | B13: Units | C13: Scenario A | D13: Scenario B | E13: Scenario C | F13: B vs A Delta | G13: C vs B Delta | H13: Best Scenario | I13: Notes
A14: Annual Energy Cost (all equipment) | B14: $/yr | C14: 1850000 | D14: 1620000 | E14: 1380000 | F14: =D14-C14 | G14: =E14-D14 | H14: Scenario C | I14: Scenario A older/less efficient equipment; Scenario C latest-gen low-energy platforms
A15: Annual Maintenance Cost | B15: $/yr | C15: 1960000 | D15: 1475000 | E15: 1225000 | F15: =D15-C15 | G15: =E15-D15 | H15: Scenario C | I15: Scenario A value-tier has higher failure rate and maint burden
A16: Annual Spare Parts Cost | B16: $/yr | C16: 520000 | D16: 385000 | E16: 295000 | F16: =D16-C16 | G16: =E16-D16 | H16: Scenario C | I16: Premium OEM (Scenario C) has longer MTBF; fewer spare parts events
A17: Annual Downtime Cost (MTBF/MTTR model) | B17: $/yr | C17: 1260000 | D17: 720000 | E17: 396000 | F17: =D17-C17 | G17: =E17-D17 | H17: Scenario C | I17: MTBF-based: Sc A avg MTBF 2,400hr; Sc B 3,500hr; Sc C 5,200hr
A18: Total Annual OpEx | B18: $/yr | C18: 5590000 | D18: 4200000 | E18: 3296000 | F18: =D18-C18 | G18: =E18-D18 | H18: Scenario C | I18: Formula: Sum of above OpEx lines; C saves $2.3M/yr vs A
A20: FINANCIAL MODEL (10-YEAR HORIZON)
A21: Parameter | B21: Units | C21: Scenario A | D21: Scenario B | E21: Scenario C | F21: B vs A Delta | G21: C vs B Delta | H21: Best Scenario | I21: Notes
A22: 10-Year Cumulative OpEx | B22: $ | C22: 55900000 | D22: 42000000 | E22: 32960000 | F22: =D22-C22 | G22: =E22-D22 | H22: Scenario C | I22: Escalated at 2.5%/yr inflation; C significantly lower over 10-yr horizon
A23: NPV of OpEx Savings vs Scenario A | B23: $ | C23: 0 | D23: 9520000 | E23: 14630000 | F23: =D23-C23 | G23: =E23-D23 | H23: Scenario C | I23: NPV at 8% discount rate; Scenario C generates $14.6M NPV savings vs A
A24: Estimated IRR | B24: % | C24: N/A | D24: 0.142 | E24: 0.187 | F24: N/A | G24: =E24-D24 | H24: Scenario C | I24: IRR on incremental investment relative to Scenario A baseline
A25: Simple Payback vs Scenario A (yrs) | B25: yrs | C25: N/A | D25: 4 | E25: 4 | F25: N/A | G25: =E25-D25 | H25: Scenario C | I25: Payback of incremental CapEx premium through OpEx savings
A27: CAPACITY & PERFORMANCE
A28: Parameter | B28: Units | C28: Scenario A | D28: Scenario B | E28: Scenario C | F28: B vs A Delta | G28: C vs B Delta | H28: Best Scenario | I28: Notes
A29: Annual Production Capacity (units/yr) | B29: units | C29: 228000 | D29: 312000 | E29: 368000 | F29: =D29-C29 | G29: =E29-D29 | H29: Scenario C | I29: Scenario C premium equipment delivers highest throughput and uptime
A30: Equipment Uptime (%) | B30: % | C30: 0.88 | D30: 0.92 | E30: 0.955 | F30: =D30-C30 | G30: =E30-D30 | H30: Scenario C | I30: Scenario A value-tier has higher unplanned downtime; C has best SLA terms
A31: Process Yield (%) | B31: % | C31: 0.935 | D31: 0.96 | E31: 0.975 | F31: =D31-C31 | G31: =E31-D31 | H31: Scenario C | I31: Process yield linked to equipment precision and repeatability spec
A33: SUPPLY CHAIN RISK
A34: Parameter | B34: Units | C34: Scenario A | D34: Scenario B | E34: Scenario C | F34: B vs A Delta | G34: C vs B Delta | H34: Best Scenario | I34: Notes
A35: Single-Source Components | B35: count | C35: 8 | D35: 5 | E35: 3 | F35: =D35-C35 | G35: =E35-D35 | H35: Scenario C | I35: Scenario A relies on more sole-source suppliers due to cost-driven selection
A36: Avg Supplier Lead Time (wks) | B36: wks | C36: 23.4 | D36: 19.8 | E36: 17.2 | F36: =D36-C36 | G36: =E36-D36 | H36: Scenario C | I36: Premium suppliers (Scenario C) have better supply chain infrastructure
A37: Supply Chain Risk Index (composite) | B37: score | C37: 38.5 | D37: 24.2 | E37: 16.8 | F37: =D37-C37 | G37: =E37-D37 | H37: Scenario C | I37: Composite index; lower = lower risk
A39: SCHEDULE & DEPLOYMENT
A40: Parameter | B40: Units | C40: Scenario A | D40: Scenario B | E40: Scenario C | F40: B vs A Delta | G40: C vs B Delta | H40: Best Scenario | I40: Notes
A41: Critical Path Duration (weeks) | B41: wks | C41: 46 | D41: 42 | E41: 38 | F41: =D41-C41 | G41: =E41-D41 | H41: Scenario C | I41: Scenario C suppliers have shorter manufacturing lead times and dedicated PM support
A42: Program End Date (Week # from start) | B42: wks | C42: 52 | D42: 47 | E42: 43 | F42: =D42-C42 | G42: =E42-D42 | H42: Scenario C | I42: Earlier qualification in Scenario C allows faster ramp to production revenue
A43: Schedule Risk Items | B43: count | C43: 7 | D43: 5 | E43: 3 | F43: =D43-C43 | G43: =E43-D43 | H43: Scenario C | I43: Fewer risk items in Scenario C; better supplier program management
A45: WEIGHTED DECISION SCORECARD & PROGRAM RECOMMENDATION
A46: Dimension | B46: Weight | C46: Score A (1-5) | D46: Score B (1-5) | E46: Score C (1-5) | F46: Wtd Score A | G46: Wtd Score B | H46: Wtd Score C | I46: Winner
A47: Capital Cost (Lower = Better) | B47: 0.2 | C47: 5 | D47: 3 | E47: 2 | F47: =B47*C47 | G47: =B47*D47 | H47: =B47*E47 | I47: A
A48: 10-Yr Total Cost of Ownership | B48: 0.2 | C48: 2 | D48: 4 | E48: 5 | F48: =B48*C48 | G48: =B48*D48 | H48: =B48*E48 | I48: C
A49: Financial Return (NPV/IRR) | B49: 0.15 | C49: 1 | D49: 4 | E49: 5 | F49: =B49*C49 | G49: =B49*D49 | H49: =B49*E49 | I49: C
A50: Production Capacity | B50: 0.1 | C50: 2 | D50: 4 | E50: 5 | F50: =B50*C50 | G50: =B50*D50 | H50: =B50*E50 | I50: C
A51: Supply Chain Risk | B51: 0.15 | C51: 2 | D51: 4 | E51: 5 | F51: =B51*C51 | G51: =B51*D51 | H51: =B51*E51 | I51: C
A52: Schedule & Deployment Risk | B52: 0.1 | C52: 2 | D52: 4 | E52: 5 | F52: =B52*C52 | G52: =B52*D52 | H52: =B52*E52 | I52: C
A53: Operational Reliability / Uptime | B53: 0.1 | C53: 2 | D53: 4 | E53: 5 | F53: =B53*C53 | G53: =B53*D53 | H53: =B53*E53 | I53: C
A54: TOTAL WEIGHTED SCORE | B54: =SUM(B47:B53) | F54: =SUM(F47:F53) | G54: =SUM(G47:G53) | H54: =SUM(H47:H53)
A56: PROGRAM RECOMMENDATION
A57: RECOMMENDED SCENARIO: SCENARIO B — Baseline Program (APPROVED)
A58: Scenario B delivers 312,000 units/yr capacity, 14.2% IRR, and $9.5M NPV over 10 years vs Scenario A. While Scenario C scores marginally higher on the weighted scorecard, it was not selected because the $47M total budget exceeds the divisional CapEx approval ceiling for a single program phase. Scenario B provides the optimal balance of financial return, risk profile, and capital efficiency within approved limits. Total budget $40.04M is within the $42M divisional CapEx approval ceiling; 14.2% IRR exceeds the 8% hurdle rate with a 4.2-year payback; 312,000 units/yr capacity supports the committed 35% customer volume increase. AR-2025-0082 was submitted and approved on this basis.

Sheet S14_CashFlow_Model
A1: S14 — CapEx Cash Flow Model — Monthly Detail & Quarterly Summary (2025 Program)
A2: Program: Greenfield Expansion Phase II | Owner: Sourabh Tarodekar | Merged monthly/quarterly model — quarterly totals derived from monthly rows (SUMIF). Payment terms: 25% Deposit / 40% Milestone / 35% Delivery.
A4: PAYMENT & PROGRAM ASSUMPTIONS
A5: Deposit % at PO Placement | B5: 0.25
A6: Manufacturing Milestone % | B6: 0.4
A7: Delivery Payment % | B7: 0.35
A8: Total AR Budget | B8: ='S12_AR_Summary'!F27
A10: MONTHLY SPEND PROFILE — Apr 2025 through Dec 2025
A11: # | B11: Month | C11: Equip. Purchases (USD) | D11: Install & Commissioning (USD) | E11: Facility Infra & FX Reserve (USD) | F11: NRE/Engineering (USD) | G11: Total Period Spend (USD) | H11: Cumulative Spend (USD) | I11: % of AR Budget | J11: Quarter | K11: Planned Milestone | L11: Notes
A12: 1 | B12: Apr-25 | C12: 3312500 | D12: 0 | E12: 512000 | F12: 122500 | G12: =SUM(C12:F12) | H12: =G12 | I12: =H12/$B$8 | J12: Q2-2025 | K12: G1: AR approved; long-lead POs placed | L12: Deposits: EQ-001/2/3/5/9/11/13/14/15; hazmat permit submitted
A13: 2 | B13: May-25 | C13: 412500 | D13: 0 | E13: 431000 | F13: 97500 | G13: =SUM(C13:F13) | H13: =H12+G13 | I13: =H13/$B$8 | J13: Q2-2025 | K13: EQ-004/006/012 deposits; civil works begin | L13: TEL furnace + Daifuku conveyor + Daikin chiller deposits
A14: 3 | B14: Jun-25 | C14: 660000 | D14: 78000 | E14: 283000 | F14: 95000 | G14: =SUM(C14:F14) | H14: =H13+G14 | I14: =H14/$B$8 | J14: Q2-2025 | K14: EQ-005 milestone; robot FAT prep | L14: Brooks SCARA manufacturing milestone payment
A15: 4 | B15: Jul-25 | C15: 948000 | D15: 138000 | E15: 227000 | F15: 90000 | G15: =SUM(C15:F15) | H15: =H14+G15 | I15: =H15/$B$8 | J15: Q3-2025 | K15: EQ-001/009/013 milestones; electrical infra | L15: Pump + DCS milestones; electrical feeds energized
A16: 5 | B16: Aug-25 | C16: 1168000 | D16: 207000 | E16: 252000 | F16: 85000 | G16: =SUM(C16:F16) | H16: =H15+G16 | I16: =H16/$B$8 | J16: Q3-2025 | K16: EQ-003/011 milestones; cooling loop | L16: Thermco furnace + ABB transformer manufacturing milestone
A17: 6 | B17: Sep-25 | C17: 700000 | D17: 258000 | E17: 305000 | F17: 80000 | G17: =SUM(C17:F17) | H17: =H16+G17 | I17: =H17/$B$8 | J17: Q3-2025 | K17: EQ-007/015 milestones; hazmat permit rcvd | L17: Air Liquide gas + MiR AMR milestones; permit closes
A18: 7 | B18: Oct-25 | C18: 912500 | D18: 323000 | E18: 250000 | F18: 75000 | G18: =SUM(C18:F18) | H18: =H17+G18 | I18: =H18/$B$8 | J18: Q4-2025 | K18: EQ-014 milestone; deliveries begin | L18: AMAT RTP manufacturing milestone; EUR equipment deliveries
A19: 8 | B19: Nov-25 | C19: 577500 | D19: 353000 | E19: 230000 | F19: 70000 | G19: =SUM(C19:F19) | H19: =H18+G19 | I19: =H19/$B$8 | J19: Q4-2025 | K19: EQ-001/009/013 deliveries; installation peak | L19: Pump sets + DCS delivered; mechanical installation begins
A20: 9 | B20: Dec-25 | C20: 637000 | D20: 405000 | E20: 60000 | F20: 65000 | G20: =SUM(C20:F20) | H20: =H19+G20 | I20: =H20/$B$8 | J20: Q4-2025 | K20: G3/G4: final deliveries; PQ begins | L20: Thermco + Air Liquide + Daikin + MiR delivered; PQ start
B21: TOTAL 2025 | C21: =SUM(C12:C20) | D21: =SUM(D12:D20) | E21: =SUM(E12:E20) | F21: =SUM(F12:F20) | G21: =SUM(G12:G20) | H21: =H20 | I21: =I20
A23: QUARTERLY CASH FLOW SUMMARY — DERIVED FROM MONTHLY DETAIL
A24: Quarter | B24: Equip. Purchases | C24: Install & Commissioning | D24: Facility Infra & FX Reserve | E24: NRE/Engineering | F24: Total Quarter Spend | G24: Cumul. Spend | H24: % of AR Budget
A25: Q2-2025 | B25: =SUMIF($J$12:$J$20,A25,C12:C20) | C25: =SUMIF($J$12:$J$20,A25,D12:D20) | D25: =SUMIF($J$12:$J$20,A25,E12:E20) | E25: =SUMIF($J$12:$J$20,A25,F12:F20) | F25: =SUM(B25:E25) | G25: =F25 | H25: =G25/$B$8
A26: Q3-2025 | B26: =SUMIF($J$12:$J$20,A26,C12:C20) | C26: =SUMIF($J$12:$J$20,A26,D12:D20) | D26: =SUMIF($J$12:$J$20,A26,E12:E20) | E26: =SUMIF($J$12:$J$20,A26,F12:F20) | F26: =SUM(B26:E26) | G26: =G25+F26 | H26: =G26/$B$8
A27: Q4-2025 | B27: =SUMIF($J$12:$J$20,A27,C12:C20) | C27: =SUMIF($J$12:$J$20,A27,D12:D20) | D27: =SUMIF($J$12:$J$20,A27,E12:E20) | E27: =SUMIF($J$12:$J$20,A27,F12:F20) | F27: =SUM(B27:E27) | G27: =G26+F27 | H27: =G27/$B$8
A29: PROGRAM TOTAL | B29: =SUM(B25:B27) | C29: =SUM(C25:C27) | D29: =SUM(D25:D27) | E29: =SUM(E25:E27) | F29: =SUM(F25:F27) | G29: =G27 | H29: =H27

Sheet S15_FX_Exposure_Model
A1: S15 — FX Exposure & Currency Risk Model — EUR / JPY Equipment Purchases
A2: Program: Greenfield Expansion Phase II | ~40% of portfolio denominated in EUR or JPY | All baseline/stress rates from S01_Disclaimer_Assumptions | Hedge status linked to cash flow schedule
A4: FX RATE ASSUMPTIONS (Linked from S01_Disclaimer_Assumptions)
A5: Rate Parameter | B5: Baseline | C5: Adverse | D5: Favorable | E5: Notes
A6: USD/EUR (baseline, USD per EUR) | B6: ='S01_Disclaimer_Assumptions'!$B$56 | C6: ='S01_Disclaimer_Assumptions'!$B$58 | D6: ='S01_Disclaimer_Assumptions'!$B$59 | E6: 1% move in EUR/USD ~ $85K portfolio impact
A7: USD/JPY (baseline, JPY per USD) | B7: ='S01_Disclaimer_Assumptions'!$B$57 | C7: ='S01_Disclaimer_Assumptions'!$B$60 | D7: ='S01_Disclaimer_Assumptions'!$B$61 | E7: Stronger JPY (lower rate) = higher USD cost
A9: EQUIPMENT-LEVEL FX EXPOSURE ANALYSIS
A10: Equip ID | B10: Tool Description | C10: Ccy | D10: Contract Value (Local Ccy) | E10: Baseline FX Rate | F10: Baseline USD Cost | G10: Adverse FX Rate | H10: Adverse USD Cost | I10: Adverse Impact (USD) | J10: Favorable FX Rate | K10: Favorable USD Cost | L10: Hedge Status | M10: Hedge Rate | N10: Notes
A11: EQ-001 | B11: Dry Screw Vacuum Pump (x4) | C11: EUR | D11: ='S02_Equipment_Portfolio'!I5/'S01_Disclaimer_Assumptions'!$B$56 | E11: ='S01_Disclaimer_Assumptions'!$B$56 | F11: =D11*E11 | G11: ='S01_Disclaimer_Assumptions'!$B$58 | H11: =D11*G11 | I11: =H11-F11 | J11: ='S01_Disclaimer_Assumptions'!$B$59 | K11: =D11*J11 | L11: HEDGED | M11: 1.085 | N11: Forward contract executed; rate locked at 1.085 through Q3-2025
A12: EQ-002 | B12: Turbomolecular Pump (x3) | C12: EUR | D12: ='S02_Equipment_Portfolio'!I6/'S01_Disclaimer_Assumptions'!$B$56 | E12: ='S01_Disclaimer_Assumptions'!$B$56 | F12: =D12*E12 | G12: ='S01_Disclaimer_Assumptions'!$B$58 | H12: =D12*G12 | I12: =H12-F12 | J12: ='S01_Disclaimer_Assumptions'!$B$59 | K12: =D12*J12 | L12: HEDGED | M12: 1.09 | N12: Forward contract at baseline rate; expires Q3-2025
A13: EQ-004 | B13: Batch Oxidation Furnace — TEL (x2) | C13: JPY | D13: ='S02_Equipment_Portfolio'!I8*'S01_Disclaimer_Assumptions'!$B$57 | E13: ='S01_Disclaimer_Assumptions'!$B$57 | F13: =D13/E13 | G13: ='S01_Disclaimer_Assumptions'!$B$60 | H13: =D13/G13 | I13: =H13-F13 | J13: ='S01_Disclaimer_Assumptions'!$B$61 | K13: =D13/J13 | L13: HEDGED | M13: 149 | N13: Forward contract at 149.0 JPY/USD; DEC-003 + CR-008 reference
A14: EQ-006 | B14: Overhead Conveyor — Daifuku | C14: JPY | D14: ='S02_Equipment_Portfolio'!I10*'S01_Disclaimer_Assumptions'!$B$57 | E14: ='S01_Disclaimer_Assumptions'!$B$57 | F14: =D14/E14 | G14: ='S01_Disclaimer_Assumptions'!$B$60 | H14: =D14/G14 | I14: =H14-F14 | J14: ='S01_Disclaimer_Assumptions'!$B$61 | K14: =D14/J14 | L14: HEDGED | M14: 149 | N14: Hedged as part of JPY program-wide forward contract
A15: EQ-007 | B15: Gas Handling Cabinet (x4) | C15: EUR | D15: ='S02_Equipment_Portfolio'!I11/'S01_Disclaimer_Assumptions'!$B$56 | E15: ='S01_Disclaimer_Assumptions'!$B$56 | F15: =D15*E15 | G15: ='S01_Disclaimer_Assumptions'!$B$58 | H15: =D15*G15 | I15: =H15-F15 | J15: ='S01_Disclaimer_Assumptions'!$B$59 | K15: =D15*J15 | L15: OPEN | M15: N/A | N15: Quote under negotiation; PO not yet placed; unhedged exposure
A16: EQ-008 | B16: Bulk Gas Storage — Linde | C16: EUR | D16: ='S02_Equipment_Portfolio'!I12/'S01_Disclaimer_Assumptions'!$B$56 | E16: ='S01_Disclaimer_Assumptions'!$B$56 | F16: =D16*E16 | G16: ='S01_Disclaimer_Assumptions'!$B$58 | H16: =D16*G16 | I16: =H16-F16 | J16: ='S01_Disclaimer_Assumptions'!$B$59 | K16: =D16*J16 | L16: HEDGED | M16: 1.09 | N16: Hedged at PO placement; long-lead item requires early hedge
A17: EQ-009 | B17: DCS — Siemens S7-1500 (x5) | C17: EUR | D17: ='S02_Equipment_Portfolio'!I13/'S01_Disclaimer_Assumptions'!$B$56 | E17: ='S01_Disclaimer_Assumptions'!$B$56 | F17: =D17*E17 | G17: ='S01_Disclaimer_Assumptions'!$B$58 | H17: =D17*G17 | I17: =H17-F17 | J17: ='S01_Disclaimer_Assumptions'!$B$59 | K17: =D17*J17 | L17: HEDGED | M17: 1.09 | N17: Hedged with EUR program forward; expires Q2-2025
A18: EQ-012 | B18: Process Chiller — Daikin (x3) | C18: JPY | D18: ='S02_Equipment_Portfolio'!I16*'S01_Disclaimer_Assumptions'!$B$57 | E18: ='S01_Disclaimer_Assumptions'!$B$57 | F18: =D18/E18 | G18: ='S01_Disclaimer_Assumptions'!$B$60 | H18: =D18/G18 | I18: =H18-F18 | J18: ='S01_Disclaimer_Assumptions'!$B$61 | K18: =D18/J18 | L18: HEDGED | M18: 149 | N18: Included in JPY hedge package; Daikin invoice in JPY
A19: EQ-013 | B19: Roots Blower Booster (x6) | C19: EUR | D19: ='S02_Equipment_Portfolio'!I17/'S01_Disclaimer_Assumptions'!$B$56 | E19: ='S01_Disclaimer_Assumptions'!$B$56 | F19: =D19*E19 | G19: ='S01_Disclaimer_Assumptions'!$B$58 | H19: =D19*G19 | I19: =H19-F19 | J19: ='S01_Disclaimer_Assumptions'!$B$59 | K19: =D19*J19 | L19: HEDGED | M19: 1.085 | N19: Forward at 1.085; coordinated with EQ-001 Edwards delivery schedule
A20: EQ-015 | B20: AMR Fleet — MiR (x10) | C20: EUR | D20: ='S02_Equipment_Portfolio'!I19/'S01_Disclaimer_Assumptions'!$B$56 | E20: ='S01_Disclaimer_Assumptions'!$B$56 | F20: =D20*E20 | G20: ='S01_Disclaimer_Assumptions'!$B$58 | H20: =D20*G20 | I20: =H20-F20 | J20: ='S01_Disclaimer_Assumptions'!$B$59 | K20: =D20*J20 | L20: HEDGED | M20: 1.09 | N20: Hedged at PO placement; forward expires Q3-2025
A21: FX PORTFOLIO TOTALS | D21: =SUM(D11:D20) | F21: =SUM(F11:F20) | H21: =SUM(H11:H20) | I21: =SUM(I11:I20) | K21: =SUM(K11:K20)
A23: FX EXPOSURE SUMMARY & HEDGE EFFECTIVENESS
A24: Total EUR-Denominated Spend (baseline USD) | B24: =SUMIF(C11:C20,"EUR",F11:F20)
A25: Total JPY-Denominated Spend (baseline USD) | B25: =SUMIF(C11:C20,"JPY",F11:F20)
A26: Total Portfolio FX-Exposed Spend (baseline USD) | B26: =F21
A27: Adverse FX Impact (if fully unhedged) | B27: =I21
A28: Items Fully Hedged | B28: =COUNTIF(L11:L20,"HEDGED")
A29: Items with Open Unhedged Exposure | B29: =COUNTIF(L11:L20,"OPEN")
A30: FX Reserve in AR Budget (USD) | B30: 485000
A31: Net FX Risk After Reserve | B31: =I21+B30

Sheet S16_Supply_Chain_Risk
A1: S16 — Supply Chain Risk & Lead-Time Analysis — CapEx Equipment Program
A2: Risk Score = Delay Probability x Schedule Impact Score x Replacement Difficulty | Heatmap tiers: LOW / MODERATE / HIGH / CRITICAL | Single-source components auto-flagged CRITICAL if Risk Score > 20 | Program ID column enables portfolio-wide rollups
A4: Equip Ref | B4: Supplier | C4: Component / Sub-System | D4: Std Lead (wks) | E4: Current Lead (wks) | F4: Delay Prob. (0-1) | G4: Sched. Impact (1-5) | H4: Replace Difficulty (1-5) | I4: Composite Risk Score | J4: Risk Tier | K4: Single Source? | L4: Buffer Stock? | M4: Mitigation Action | N4: Status | O4: Program ID
A5: EQ-001 | B5: Edwards Vacuum | C5: Dry Screw Pump – Complete Unit | D5: 14 | E5: 18 | F5: 0.35 | G5: 3 | H5: 2 | I5: =F5*G5*H5 | J5: =IF(OR(K5="YES",I5>20),IF(I5>20,"CRITICAL",IF(K5="YES","CRITICAL","HIGH")),IF(I5>8,"HIGH",IF(I5>2,"MODERATE","LOW"))) | K5: No | L5: No | M5: Expedite order; confirm delivery schedule with supplier weekly; pre-qualify Busch as alt | N5: IN PROGRESS | O5: PRG-001
A6: EQ-002 | B6: Pfeiffer Vacuum | C6: Turbomolecular Pump – Complete Unit | D6: 16 | E6: 26 | F6: 0.55 | G6: 5 | H6: 5 | I6: =F6*G6*H6 | J6: =IF(OR(K6="YES",I6>20),IF(I6>20,"CRITICAL",IF(K6="YES","CRITICAL","HIGH")),IF(I6>8,"HIGH",IF(I6>2,"MODERATE","LOW"))) | K6: YES | L6: No | M6: CRITICAL PATH: Escalate to VP Supply Chain; evaluate rebuilt unit as bridge; initiate alt vendor qual | N6: ESCALATED | O6: PRG-001
A7: EQ-002 | B7: Pfeiffer Vacuum | C7: Turbomolecular Controller Electronics | D7: 12 | E7: 18 | F7: 0.45 | G7: 4 | H7: 5 | I7: =F7*G7*H7 | J7: =IF(OR(K7="YES",I7>20),IF(I7>20,"CRITICAL",IF(K7="YES","CRITICAL","HIGH")),IF(I7>8,"HIGH",IF(I7>2,"MODERATE","LOW"))) | K7: YES | L7: No | M7: Controller firmware proprietary; no drop-in alt; request safety stock commitment from supplier | N7: ESCALATED | O7: PRG-001
A8: EQ-003 | B8: Thermco Systems | C8: Tube Furnace – Hot Zone Assembly | D8: 18 | E8: 20 | F8: 0.2 | G8: 4 | H8: 3 | I8: =F8*G8*H8 | J8: =IF(OR(K8="YES",I8>20),IF(I8>20,"CRITICAL",IF(K8="YES","CRITICAL","HIGH")),IF(I8>8,"HIGH",IF(I8>2,"MODERATE","LOW"))) | K8: No | L8: No | M8: BTU International validated as alt; maintain contact; include alt option in RFQ | N8: MONITORED | O8: PRG-001
A9: EQ-003 | B9: Thermco Systems | C9: 8-Zone Heating Element Set | D9: 10 | E9: 12 | F9: 0.15 | G9: 3 | H9: 2 | I9: =F9*G9*H9 | J9: =IF(OR(K9="YES",I9>20),IF(I9>20,"CRITICAL",IF(K9="YES","CRITICAL","HIGH")),IF(I9>8,"HIGH",IF(I9>2,"MODERATE","LOW"))) | K9: No | L9: Yes | M9: 2-set buffer stock maintained; supplier reliability high; no immediate action required | N9: OK | O9: PRG-001
A10: EQ-004 | B10: Tokyo Electron (TEL) | C10: Batch Furnace – Complete System | D10: 20 | E10: 28 | F10: 0.4 | G10: 5 | H10: 4 | I10: =F10*G10*H10 | J10: =IF(OR(K10="YES",I10>20),IF(I10>20,"CRITICAL",IF(K10="YES","CRITICAL","HIGH")),IF(I10>8,"HIGH",IF(I10>2,"MODERATE","LOW"))) | K10: No | L10: No | M10: JPY FX hedge confirmed; increase FAT scope to 3 weeks; dedicated TEL PM assigned | N10: IN PROGRESS | O10: PRG-001
A11: EQ-004 | B11: Tokyo Electron (TEL) | C11: Process Recipe Transfer Package | D11: N/A | E11: N/A | F11: 0.3 | G11: 4 | H11: 4 | I11: =F11*G11*H11 | J11: =IF(OR(K11="YES",I11>20),IF(I11>20,"CRITICAL",IF(K11="YES","CRITICAL","HIGH")),IF(I11>8,"HIGH",IF(I11>2,"MODERATE","LOW"))) | K11: YES | L11: No | M11: Non-tangible risk: recipe IP held by TEL; require contractual data transfer clause at PO stage | N11: LEGAL REVIEW | O11: PRG-001
A12: EQ-005 | B12: Brooks Automation | C12: SCARA Robot – Mechanical Assembly | D12: 12 | E12: 14 | F12: 0.15 | G12: 3 | H12: 3 | I12: =F12*G12*H12 | J12: =IF(OR(K12="YES",I12>20),IF(I12>20,"CRITICAL",IF(K12="YES","CRITICAL","HIGH")),IF(I12>8,"HIGH",IF(I12>2,"MODERATE","LOW"))) | K12: No | L12: No | M12: Brooks delivery historically reliable; no action required; standard monitoring | N12: OK | O12: PRG-001
A13: EQ-005 | B13: Brooks Automation | C13: MES Software Integration Module | D13: N/A | E13: N/A | F13: 0.45 | G13: 4 | H13: 4 | I13: =F13*G13*H13 | J13: =IF(OR(K13="YES",I13>20),IF(I13>20,"CRITICAL",IF(K13="YES","CRITICAL","HIGH")),IF(I13>8,"HIGH",IF(I13>2,"MODERATE","LOW"))) | K13: YES | L13: No | M13: Integration complexity risk — not supply risk; assign Brooks SW engineer on-site 4 wks pre-FAT | N13: IN PROGRESS | O13: PRG-001
A14: EQ-006 | B14: Daifuku | C14: Overhead Track System – Civil Interface | D14: 22 | E14: 30 | F14: 0.5 | G14: 4 | H14: 5 | I14: =F14*G14*H14 | J14: =IF(OR(K14="YES",I14>20),IF(I14>20,"CRITICAL",IF(K14="YES","CRITICAL","HIGH")),IF(I14>8,"HIGH",IF(I14>2,"MODERATE","LOW"))) | K14: YES | L14: No | M14: Civil drawings required 8 wks pre-install; freeze layout by Week 6; no alt track supplier | N14: ESCALATED | O14: PRG-001
A15: EQ-007 | B15: Air Liquide Eng. | C15: Gas Cabinet – Complete Assembly | D15: 16 | E15: 22 | F15: 0.4 | G15: 3 | H15: 3 | I15: =F15*G15*H15 | J15: =IF(OR(K15="YES",I15>20),IF(I15>20,"CRITICAL",IF(K15="YES","CRITICAL","HIGH")),IF(I15>8,"HIGH",IF(I15>2,"MODERATE","LOW"))) | K15: No | L15: No | M15: Quote under negotiation; delay increases if PO not placed by target date; expedite sourcing decision | N15: IN PROGRESS | O15: PRG-001
A16: EQ-007 | B16: Air Liquide Eng. | C16: Hazmat Permit – Regulatory | D16: N/A | E16: N/A | F16: 0.35 | G16: 5 | H16: 5 | I16: =F16*G16*H16 | J16: =IF(OR(K16="YES",I16>20),IF(I16>20,"CRITICAL",IF(K16="YES","CRITICAL","HIGH")),IF(I16>8,"HIGH",IF(I16>2,"MODERATE","LOW"))) | K16: YES | L16: No | M16: Permit lead time 8-12 wks; submit application immediately; failure impacts entire gas system install | N16: ACTION REQ'D | O16: PRG-001
A17: EQ-008 | B17: Linde Engineering | C17: Bulk Gas Storage Vessel | D17: 24 | E17: 32 | F17: 0.35 | G17: 4 | H17: 3 | I17: =F17*G17*H17 | J17: =IF(OR(K17="YES",I17>20),IF(I17>20,"CRITICAL",IF(K17="YES","CRITICAL","HIGH")),IF(I17>8,"HIGH",IF(I17>2,"MODERATE","LOW"))) | K17: No | L17: No | M17: Long-lead vessel; PO must be placed by program Week 4; civil pad work parallel path | N17: IN PROGRESS | O17: PRG-001
A18: EQ-009 | B18: Siemens AG | C18: S7-1500 PLC Hardware Set | D18: 10 | E18: 14 | F18: 0.15 | G18: 2 | H18: 2 | I18: =F18*G18*H18 | J18: =IF(OR(K18="YES",I18>20),IF(I18>20,"CRITICAL",IF(K18="YES","CRITICAL","HIGH")),IF(I18>8,"HIGH",IF(I18>2,"MODERATE","LOW"))) | K18: No | L18: Yes | M18: Strong supply reliability; buffer stock of 1 spare CPU maintained; low risk | N18: OK | O18: PRG-001
A19: EQ-009 | B19: Siemens AG | C19: Cybersecurity Compliance Review | D19: N/A | E19: N/A | F19: 0.25 | G19: 3 | H19: 3 | I19: =F19*G19*H19 | J19: =IF(OR(K19="YES",I19>20),IF(I19>20,"CRITICAL",IF(K19="YES","CRITICAL","HIGH")),IF(I19>8,"HIGH",IF(I19>2,"MODERATE","LOW"))) | K19: YES | L19: No | M19: Internal InfoSec review adds 3 wks; submit documentation package 6 wks pre-installation | N19: IN PROGRESS | O19: PRG-001
A20: EQ-011 | B20: ABB Ltd | C20: 2 MVA Dry-Type Transformer | D20: 14 | E20: 20 | F20: 0.25 | G20: 4 | H20: 3 | I20: =F20*G20*H20 | J20: =IF(OR(K20="YES",I20>20),IF(I20>20,"CRITICAL",IF(K20="YES","CRITICAL","HIGH")),IF(I20>8,"HIGH",IF(I20>2,"MODERATE","LOW"))) | K20: No | L20: No | M20: Reuse of legacy unit partially mitigates; new unit on order; monitor delivery | N20: MONITORED | O20: PRG-001
A21: EQ-012 | B21: Daikin Applied | C21: Chiller – Complete Package | D21: 16 | E21: 20 | F21: 0.2 | G21: 3 | H21: 2 | I21: =F21*G21*H21 | J21: =IF(OR(K21="YES",I21>20),IF(I21>20,"CRITICAL",IF(K21="YES","CRITICAL","HIGH")),IF(I21>8,"HIGH",IF(I21>2,"MODERATE","LOW"))) | K21: No | L21: No | M21: Glycol loop interface design must be finalized prior to FAT; coordinate with mechanical team | N21: IN PROGRESS | O21: PRG-001
A22: EQ-014 | B22: Applied Materials | C22: RTP Tool – Complete System | D22: 20 | E22: 24 | F22: 0.25 | G22: 5 | H22: 4 | I22: =F22*G22*H22 | J22: =IF(OR(K22="YES",I22>20),IF(I22>20,"CRITICAL",IF(K22="YES","CRITICAL","HIGH")),IF(I22>8,"HIGH",IF(I22>2,"MODERATE","LOW"))) | K22: No | L22: No | M22: Highest-value item; AMAT requires 30% deposit at PO; finance pre-approval gate required | N22: ACTION REQ'D | O22: PRG-001
A23: EQ-015 | B23: MiR (Mobile Industrial Robots) | C23: AMR Fleet – 10 Units | D23: 14 | E23: 18 | F23: 0.3 | G23: 2 | H23: 2 | I23: =F23*G23*H23 | J23: =IF(OR(K23="YES",I23>20),IF(I23>20,"CRITICAL",IF(K23="YES","CRITICAL","HIGH")),IF(I23>8,"HIGH",IF(I23>2,"MODERATE","LOW"))) | K23: No | L23: No | M23: Wi-Fi infrastructure survey required 6 wks pre-delivery; coordinate with IT/OT team | N23: MONITORED | O23: PRG-001
A26: SUPPLY CHAIN RISK HEATMAP SUMMARY — PRG-001 Greenfield Expansion Phase II
A27: Risk Tier | B27: Count | C27: % of Items | D27: Action Required
A28: CRITICAL | B28: =COUNTIF(J5:J23,A28) | C28: =B28/19 | D28: Immediate VP-level escalation; daily status; dedicated mitigation team
A29: HIGH | B29: =COUNTIF(J5:J23,A29) | C29: =B29/19 | D29: Weekly executive review; mitigation plan required within 5 business days
A30: MODERATE | B30: =COUNTIF(J5:J23,A30) | C30: =B30/19 | D30: Bi-weekly review; mitigation plan in place; monitor for deterioration
A31: LOW | B31: =COUNTIF(J5:J23,A31) | C31: =B31/19 | D31: Standard monitoring; quarterly supplier check-in sufficient
A33: AGGREGATE RISK STATISTICS — PRG-001 Greenfield Expansion Phase II
A34: Total Components Tracked | B34: =COUNTA(A5:A23)
A35: Single-Source Components | B35: =COUNTIF(K5:K23,"YES")
A36: Avg Composite Risk Score | B36: =AVERAGE(I5:I23)
A37: Max Risk Score (Worst Item) | B37: =MAX(I5:I23)
A38: CRITICAL Tier Items | B38: =COUNTIF(J5:J23,"CRITICAL")
A39: HIGH Tier Items | B39: =COUNTIF(J5:J23,"HIGH")
A41: PRG-002 RISK REGISTER — Riverside Automation Upgrade Phase I
A42: Equip Ref | B42: Supplier | C42: Component / Sub-System | D42: Std Lead (wks) | E42: Current Lead (wks) | F42: Delay Prob. (0-1) | G42: Sched. Impact (1-5) | H42: Replace Difficulty (1-5) | I42: Composite Risk Score | J42: Risk Tier | K42: Single Source? | L42: Buffer Stock? | M42: Mitigation Action | N42: Status | O42: Program ID
A43: RV-001 | B43: Fanuc America | C43: Palletizing Robot – Complete Unit | D43: 10 | E43: 12 | F43: 0.15 | G43: 2 | H43: 2 | I43: =F43*G43*H43 | J43: =IF(OR(K43="YES",I43>20),IF(I43>20,"CRITICAL",IF(K43="YES","CRITICAL","HIGH")),IF(I43>8,"HIGH",IF(I43>2,"MODERATE","LOW"))) | K43: No | L43: No | M43: Standard robot platform; low risk; monitor delivery per standard cadence | N43: OK | O43: PRG-002
A44: RV-002 | B44: Krones AG | C44: Cartoning System – Complete Unit | D44: 20 | E44: 24 | F44: 0.3 | G44: 4 | H44: 4 | I44: =F44*G44*H44 | J44: =IF(OR(K44="YES",I44>20),IF(I44>20,"CRITICAL",IF(K44="YES","CRITICAL","HIGH")),IF(I44>8,"HIGH",IF(I44>2,"MODERATE","LOW"))) | K44: YES | L44: No | M44: Single-source specialized tech; no qualified alt; monitor delivery weekly during build | N44: IN PROGRESS | O44: PRG-002
A45: RV-003 | B45: Fetch Robotics | C45: AGV Fleet – Complete Units | D45: 8 | E45: 9 | F45: 0.1 | G45: 2 | H45: 1 | I45: =F45*G45*H45 | J45: =IF(OR(K45="YES",I45>20),IF(I45>20,"CRITICAL",IF(K45="YES","CRITICAL","HIGH")),IF(I45>8,"HIGH",IF(I45>2,"MODERATE","LOW"))) | K45: No | L45: No | M45: Mature platform; low supply risk; standard monitoring | N45: OK | O45: PRG-002
A46: RV-004 | B46: Cognex Corporation | C46: Vision Inspection – Complete Units | D46: 6 | E46: 7 | F46: 0.1 | G46: 2 | H46: 1 | I46: =F46*G46*H46 | J46: =IF(OR(K46="YES",I46>20),IF(I46>20,"CRITICAL",IF(K46="YES","CRITICAL","HIGH")),IF(I46>8,"HIGH",IF(I46>2,"MODERATE","LOW"))) | K46: No | L46: Yes | M46: Commodity vision hardware; Keyence pre-qualified alt on file | N46: OK | O46: PRG-002
A47: RV-005 | B47: Rockwell Automation | C47: WCS Integration – Software/Hardware | D47: 8 | E47: 9 | F47: 0.2 | G47: 3 | H47: 2 | I47: =F47*G47*H47 | J47: =IF(OR(K47="YES",I47>20),IF(I47>20,"CRITICAL",IF(K47="YES","CRITICAL","HIGH")),IF(I47>8,"HIGH",IF(I47>2,"MODERATE","LOW"))) | K47: No | L47: No | M47: Standard PlantPAx platform; integrator has strong track record | N47: MONITORED | O47: PRG-002
A48: RV-006 | B48: Dematic Corp | C48: Conveyor & Sortation – Complete System | D48: 16 | E48: 20 | F48: 0.25 | G48: 3 | H48: 3 | I48: =F48*G48*H48 | J48: =IF(OR(K48="YES",I48>20),IF(I48>20,"CRITICAL",IF(K48="YES","CRITICAL","HIGH")),IF(I48>8,"HIGH",IF(I48>2,"MODERATE","LOW"))) | K48: No | L48: No | M48: Complex site-specific integration; phased cutover plan mitigates schedule risk | N48: MONITORED | O48: PRG-002
A50: AGGREGATE RISK STATISTICS — PRG-002 Riverside Automation Upgrade Phase I
A51: Total Components Tracked | B51: =COUNTA(A43:A48)
A52: Single-Source Components | B52: =COUNTIF(K43:K48,"YES")
A53: Avg Composite Risk Score | B53: =AVERAGE(I43:I48)
A54: Max Risk Score (Worst Item) | B54: =MAX(I43:I48)
A55: CRITICAL Tier Items | B55: =COUNTIF(J43:J48,"CRITICAL")
A56: HIGH Tier Items | B56: =COUNTIF(J43:J48,"HIGH")

Sheet S17_Supply_Market_Analysis
A1: S17 — Supply Market Structure Analysis — Commodity Concentration & Pricing
A2: Program: Greenfield Expansion Phase II | Owner: Sourabh Tarodekar / Strategic Sourcing | HHI = Herfindahl-Hirschman Index (sum of squared market shares x10,000) | HHI > 2500 = highly concentrated market
A4: Commodity / Category | B4: # Global Suppliers | C4: Top-3 Market Share (%) | D4: HHI (Concentration Index) | E4: 12-Mo Price Trend | F4: Lead Time Trend | G4: Key Market Risk / Notes
A5: Vacuum Pumps (Turbo/Dry Screw) | B5: 6 | C5: 0.72 | D5: 2450 | E5: +4.2% | F5: Extending | G5: Pfeiffer/Edwards/Busch concentration; semiconductor demand surge
A6: High-Temp Furnace Systems | B6: 5 | C6: 0.81 | D6: 3100 | E6: +6.8% | F6: Extending | G6: TEL/Thermco/Kokusai oligopoly; long qualification cycles limit new entrants
A7: Precision Robotics (SCARA/6-axis) | B7: 8 | C7: 0.65 | D7: 1980 | E7: +2.1% | F7: Stable | G7: Brooks/Yaskawa/Fanuc/Kawasaki competitive field; servo chip shortage easing
A8: Process Gas Handling Systems | B8: 7 | C8: 0.58 | D8: 1620 | E8: +3.5% | F8: Extending | G8: Air Liquide/Linde/Matheson; hazmat regulatory burden raises entry barriers
A9: PLC / DCS Control Systems | B9: 4 | C9: 0.85 | D9: 3400 | E9: +1.8% | F9: Stable | G9: Siemens/Rockwell/ABB/Schneider dominate; software licensing model shift
A10: Facility Power Infrastructure (Transformers) | B10: 9 | C10: 0.52 | D10: 1340 | E10: +8.5% | F10: Extending | G10: Grid-scale transformer demand surge (data centers); 18-24mo lead times industry-wide
A11: Industrial Chillers / Cooling | B11: 6 | C11: 0.61 | D11: 1710 | E11: +3.0% | F11: Stable | G11: Daikin/Trane/Carrier; refrigerant transition (R-454B) driving redesigns
A12: Mobile Robotics (AMR Fleets) | B12: 10 | C12: 0.48 | D12: 1120 | E12: -2.5% | F12: Improving | G12: MiR/Locus/Omron/Fetch; maturing market with price competition intensifying
A15: MARKET INTELLIGENCE SUMMARY
A16: Commodities Tracked | B16: =COUNTA(A5:A12)
A17: Avg HHI (Portfolio Commodities) | B17: =AVERAGE(D5:D12)
A18: Highly Concentrated Markets (HHI>2500) | B18: =COUNTIF(D5:D12,">2500")
A19: Avg Top-3 Market Share | B19: =AVERAGE(C5:C12)

Sheet S18_Supply_Chain_Network
A1: S18 — Supply Chain Network Map — Supplier Geography, Routes & Tier-2 Visibility
A2: Program: Greenfield Expansion Phase II | Owner: Sourabh Tarodekar / Logistics | 15 suppliers across 5 countries | Feeds S19 Sourcing Pipeline and S14 Cash Flow logistics timing
A4: Supplier | B4: Country | C4: City / Site | D4: Equip Ref | E4: Transport Mode | F4: Ocean/Intl Transit (wks) | G4: Incoterm | H4: Tier-2 Sub-Supplier Visibility | I4: Customs Complexity
A5: Edwards Vacuum | B5: UK | C5: Crawley | D5: EQ-001 | E5: Ocean + Road | F5: 3 | G5: DDP | H5: Partial | I5: Moderate — post-Brexit customs
A6: Pfeiffer Vacuum | B6: DE | C6: Asslar | D6: EQ-002 | E6: Ocean + Road | F6: 3 | G6: DDP | H6: Partial | I6: Low — EU/US standard lanes
A7: Thermco Systems | B7: USA | C7: Austin, TX | D7: EQ-003 | E7: Road | F7: 1 | G7: FOB Origin | H7: Full | I7: Low — domestic
A8: Tokyo Electron Ltd | B8: JP | C8: Tokyo | D8: EQ-004 | E8: Ocean | F8: 4 | G8: DDP | H8: Partial | I8: High — JPY invoicing, import duty
A9: Brooks Automation | B9: USA | C9: Chelmsford, MA | D9: EQ-005 | E9: Road | F9: 1 | G9: FOB Origin | H9: Full | I9: Low — domestic
A10: Daifuku | B10: JP | C10: Osaka | D10: EQ-006 | E10: Ocean | F10: 4 | G10: DDP | H10: Low — custom civil scope | I10: High — custom project logistics
A11: Air Liquide Engineering | B11: FR | C11: Frankfurt (hub) | D11: EQ-007 | E11: Ocean + Road | F11: 3 | G11: DDP | H11: Partial | I11: Moderate — hazmat classification
A12: Linde Engineering | B12: DE | C12: Pullach | D12: EQ-008 | E12: Ocean + Road | F12: 4 | G12: DDP | H12: Partial | I12: Moderate — pressure vessel cert
A13: Siemens AG | B13: DE | C13: Karlsruhe | D13: EQ-009 | E13: Ocean + Road | F13: 3 | G13: DDP | H13: Full | I13: Low — standard EU/US lanes
A14: Inductive Automation | B14: USA | C14: Folsom, CA | D14: EQ-010 | E14: N/A — Software | F14: 0 | G14: N/A | H14: Full | I14: None — digital delivery
A15: ABB Ltd | B15: CH | C15: Zurich | D15: EQ-011 | E15: Ocean + Road | F15: 3 | G15: DDP | H15: Full | I15: Low — standard EU/US lanes
A16: Daikin Applied | B16: JP | C16: Osaka | D16: EQ-012 | E16: Ocean | F16: 3 | G16: DDP | H16: Partial | I16: High — JPY invoicing, import duty
... A19: Mobile Industrial Robots (MiR) | B19: DK | C19: Odense | D19: EQ-015 | E19: Ocean + Road | F19: 3 | G19: DDP | H19: Full | I19: Moderate — EU export docs
A22: NETWORK SUMMARY
A23: Total Suppliers in Network | B23: =COUNTA(A5:A19)
A24: Countries Represented | B24: =SUMPRODUCT(1/COUNTIF(B5:B19,B5:B19))
A25: Avg Ocean/International Transit (wks) | B25: =AVERAGE(F5:F19)
A26: Suppliers Requiring Ocean Freight | B26: =COUNTIF(E5:E19,"*Ocean*")
A27: Domestic (Road-Only) Suppliers | B27: =COUNTIF(E5:E19,"Road")

Sheet S19_Strategic_Sourcing_Pipeline
A1: S19 — Strategic Sourcing Pipeline — RFI to Award, Contract Status & Savings
A2: Program: Greenfield Expansion Phase II | Owner: Sourabh Tarodekar / Strategic Sourcing | FEL = Front-End Loading (1=Concept, 2=Feasibility, 3=Definition) | 12 sourcing categories tracked
A4: Sourcing Category | B4: Equipment Ref | C4: FEL Phase | D4: RFI Date | E4: RFQ Date | F4: Award Date | G4: # Suppliers Bid | H4: Awarded / Leading Supplier | I4: Savings vs Budget (USD) | J4: Status
A5: Vacuum Pump Systems | B5: EQ-001/002/013 | C5: FEL-3 | D5: 2024-09-15 | E5: 2024-10-15 | F5: 2025-01-15 | G5: 4 | H5: Edwards / Pfeiffer / Busch | I5: 93000 | J5: AWARDED
A6: High-Temp Furnace Systems | B6: EQ-003/004/014 | C6: FEL-3 | D6: 2024-08-01 | E6: 2024-09-01 | F6: 2025-01-01 | G6: 3 | H6: Thermco / TEL / AMAT | I6: 207000 | J6: AWARDED
A7: Robotics & Automation | B7: EQ-005/006/015 | C7: FEL-3 | D7: 2024-09-01 | E7: 2024-10-01 | F7: 2025-01-01 | G7: 4 | H7: Brooks / Daifuku / MiR | I7: 119000 | J7: AWARDED
A8: Gas Handling Systems | B8: EQ-007/008 | C8: FEL-2 | D8: 2024-10-01 | E8: 2024-11-15 | F8: 2025-02-15 (target) | G8: 3 | H8: Air Liquide (pending) / Linde | I8: 22000 | J8: IN NEGOTIATION
A9: PLC / Control Systems | B9: EQ-009/010 | C9: FEL-3 | D9: 2024-08-15 | E9: 2024-09-15 | F9: 2024-12-15 | G9: 3 | H9: Siemens / Inductive Automation | I9: 55000 | J9: AWARDED
A10: Facility Infrastructure — Power | B10: EQ-011 | C10: FEL-3 | D10: 2024-09-01 | E10: 2024-10-01 | F10: 2025-01-01 | G10: 2 | H10: ABB Ltd | I10: 0 | J10: AWARDED
A11: Facility Infrastructure — Cooling | B11: EQ-012 | C11: FEL-3 | D11: 2024-09-15 | E11: 2024-10-15 | F11: 2025-01-15 | G11: 3 | H11: Daikin Applied | I11: 41000 | J11: AWARDED
A12: Spare Parts & Consumables | B12: S23 register | C12: FEL-2 | D12: 2025-01-15 | E12: 2025-02-15 | F12: 2025-04-01 (target) | G12: 5 | H12: Multiple | I12: 0 | J12: IN PROGRESS
A13: Field Service Contracts | B13: All platforms | C13: FEL-1 | D13: 2025-02-01 | E13: 2025-03-01 (target) | F13: TBD | G13: — | H13: TBD | I13: 0 | J13: PLANNED
A14: Alt-Source Qualification — TMP | B14: EQ-002 | C14: FEL-2 | D14: 2025-02-01 | E14: 2025-03-01 | F14: 2025-06-01 (target) | G14: 1 | H14: Shimadzu (qualifying) | I14: 0 | J14: IN QUALIFICATION
A15: Alt-Source Qualification — Gas Cabinet | B15: EQ-007 | C15: FEL-1 | D15: 2025-03-01 | E15: TBD | F15: TBD | G15: 1 | H15: Matheson Gas (RFQ issued) | I15: 0 | J15: RFQ ISSUED
A16: IT/OT Network Infrastructure | B16: EQ-009/010 DMZ | C16: FEL-2 | D16: 2025-04-15 | E16: 2025-05-01 | F16: 2025-06-01 (target) | G16: 3 | H16: TBD | I16: 0 | J16: IN PROGRESS
A19: SOURCING PIPELINE SUMMARY
A20: Total Sourcing Categories | B20: =COUNTA(A5:A16)
A21: Categories Awarded | B21: =COUNTIF(J5:J16,"AWARDED")
A22: Categories In Progress / Negotiation | B22: =COUNTA(A5:A16)-COUNTIF(J5:J16,"AWARDED")
A23: Total Savings vs Budget (USD) | B23: =SUM(I5:I16)
A24: Avg Suppliers Bid per Category | B24: =AVERAGE(G5:G16)

Sheet S20_Dual_MultiSource_Strategy
A1: S20 — Dual / Multi-Source Strategy — Qualification Status & Risk Reduction
A2: Program: Greenfield Expansion Phase II | Owner: Sourabh Tarodekar / Strategic Sourcing | 8 commodities with active or completed dual-source programs | Directly reduces S16 supply chain risk exposure
A4: Commodity | B4: Primary Supplier | C4: Equip Ref | D4: Alternate Supplier | E4: Qualification Status | F4: Risk Reduction Rationale | G4: Target Completion | H4: Notes
A5: Turbomolecular Pumps | B5: Pfeiffer Vacuum | C5: EQ-002 | D5: Shimadzu Corp (TMP-3203L) | E5: IN QUALIFICATION | F5: Eliminates single-source CRITICAL risk on program's highest-risk item | G5: 2025-Q3 | H5: 90-day qualification program initiated per CR-007; test units requested
A6: Dry Screw Vacuum Pumps | B6: Edwards Vacuum | C6: EQ-001 | D6: Busch Vacuum | E6: AVL — QUALIFIED | F6: Already-qualified alt reduces post-Brexit logistics exposure | G6: COMPLETE | H6: Busch already supplies EQ-013; cross-qualified as backup to Edwards
A7: High-Temp Tube Furnaces | B7: Thermco Systems | C7: EQ-003 | D7: BTU International | E7: AVL — QUALIFIED | F7: Reduces exposure to single furnace OEM for core process step | G7: COMPLETE | H7: BTU pre-qualified; compatible process performance confirmed
A8: Batch Oxidation Furnaces | B8: Tokyo Electron Ltd | C8: EQ-004 | D8: Kokusai Electric | E8: PRE-QUALIFIED | F8: Mitigates JPY/TEL concentration risk on second-largest CapEx line | G8: 2025-Q4 (monitoring) | H8: Pre-qualified but not activated; TEL relationship strategic, monitored not urgent
A9: Process Gas Cabinets | B9: Air Liquide Engineering | C9: EQ-007 | D9: Matheson Gas | E9: RFQ ISSUED | F9: Provides commercial leverage during active EQ-007 negotiation | G9: 2025-Q2 | H9: RFQ issued in parallel with Air Liquide negotiation; pricing/delivery under review
A10: Bulk Gas Storage & Delivery | B10: Linde Engineering | C10: EQ-008 | D10: Air Products | E10: RFQ ISSUED | F10: Commercial leverage; long lead-time category benefits from dual-source | G10: 2025-Q3 | H10: Used as competitive tension during Linde negotiation (closed favorably)
A11: SCARA Robots | B11: Brooks Automation | C11: EQ-005 | D11: Kawasaki Robotics | E11: TECHNICAL EVAL | F11: Reduces dependency on single robotics OEM for material handling | G11: 2025-Q4 | H11: Technical evaluation only; no immediate qualification driver — moderate priority
A12: Roots Blower Boosters | B12: Busch Vacuum | C12: EQ-013 | D12: Edwards Vacuum | E12: AVL — QUALIFIED | F12: Mutual cross-qualification with EQ-001 Edwards / EQ-013 Busch pairing | G12: COMPLETE | H12: Edwards and Busch mutually qualified as alternates across both platforms
A15: DUAL-SOURCE PROGRAM IMPACT SUMMARY
A16: Commodities with Dual-Source Program | B16: =COUNTA(A5:A12)
A17: Qualified / AVL-Ready Alternates | B17: =COUNTIF(E5:E12,"AVL — QUALIFIED")
A18: Active Qualification Programs | B18: =COUNTIF(E5:E12,"IN QUALIFICATION")+COUNTIF(E5:E12,"PRE-QUALIFIED")
A19: RFQ / Early-Stage Programs | B19: =COUNTIF(E5:E12,"RFQ ISSUED")+COUNTIF(E5:E12,"TECHNICAL EVAL")

Sheet S21_Negotiation_Tracker
A1: S21 — Negotiation Tracker — Commercial Negotiation Log & Savings Portfolio
A2: Tracks all active and completed negotiations | Owner: Sourabh Tarodekar | BATNA = Best Alternative to Negotiated Agreement | Feeds S19 Strategic Sourcing Pipeline
A4: Neg ID | B4: Supplier | C4: Category | D4: Contract Value | E4: Neg Type | F4: Start | G4: Close | H4: Initial Quote (USD) | I4: Internal Target (USD) | J4: Walk-Away (USD) | K4: Key Leverage | L4: BATNA | M4: Final Agreed (USD) | N4: Savings (USD) | O4: Savings % | P4: Status
A5: N-001 | B5: Pfeiffer Vacuum | C5: TMP Systems (EQ-002) | D5: 930000 | E5: Initial Award | F5: 2024-Q4 | G5: 2025-Q1 | H5: 975000 | I5: 920000 | J5: 1000000 | K5: Single-source risk acknowledged; Shimadzu qual threat | L5: Shimadzu TMP-3203L qualification | M5: 930000 | N5: =H5-M5 | O5: =N5/H5 | P5: CLOSED
A6: N-002 | B6: Thermco Systems | C6: Tube Furnaces (EQ-003) | D6: 1040000 | E6: Competitive Award | F6: 2024-Q3 | G6: 2024-Q4 | H6: 1122000 | I6: 1030000 | J6: 1180000 | K6: BTU International valid alt; multi-unit volume | L6: BTU International — pre-qualified | M6: 1040000 | N6: =H6-M6 | O6: =N6/H6 | P6: CLOSED
A7: N-003 | B7: Applied Materials | C7: RTP Tool (EQ-014) | D7: 1750000 | E7: Strategic Negotiation | F7: 2024-Q2 | G7: 2025-Q1 | H7: 1875000 | I7: 1720000 | J7: 1900000 | K7: Multi-unit commitment (2 units); Phase III expansion signal | L7: TEL — RTP alternative evaluated | M7: 1750000 | N7: =H7-M7 | O7: =N7/H7 | P7: CLOSED
A8: N-004 | B8: Brooks Automation | C8: SCARA Robots (EQ-005) | D8: 1650000 | E8: Competitive Award | F8: 2024-Q3 | G8: 2024-Q4 | H8: 1745000 | I8: 1630000 | J8: 1800000 | K8: 6-unit volume; Kawasaki technical evaluation in parallel | L8: Kawasaki Robotics — technical eval | M8: 1650000 | N8: =H8-M8 | O8: =N8/H8 | P8: CLOSED
A9: N-005 | B9: Siemens AG | C9: DCS Platform (EQ-009) | D9: 825000 | E9: LTA Renewal | F9: 2023-Q4 | G9: 2024-Q1 | H9: 880000 | I9: 810000 | J9: 920000 | K9: Existing relationship; Phase II expansion commitment; SCADA alt | L9: Rockwell Automation as alt DCS | M9: 825000 | N9: =H9-M9 | O9: =N9/H9 | P9: CLOSED — LTA active
A10: N-006 | B10: Air Liquide Eng. | C10: Gas Cabinets (EQ-007) | D10: TBC (target) | E10: Active Negotiation | F10: 2025-Q1 | G10: 2025-Q2 target | H10: 840000 | I10: 760000 | J10: 850000 | K10: Matheson Gas RFQ in parallel; hazmat permit dependency | L10: Matheson Gas — RFQ issued parallel | M10: TBC | N10: TBC | O10: TBC | P10: IN NEGOTIATION
A11: N-007 | B11: Linde Engineering | C11: Bulk Gas (EQ-008) | D11: 340000 | E11: Competitive Award | F11: 2024-Q4 | G11: 2025-Q1 | H11: 362000 | I11: 330000 | J11: 380000 | K11: Existing site contract leverage; 32-wk LT accepted | L11: Air Products — RFQ issued | M11: 340000 | N11: =H11-M11 | O11: =N11/H11 | P11: CLOSED
A12: N-008 | B12: Edwards Vacuum | C12: Dry Screw Pumps (EQ-001) | D12: 740000 | E12: Competitive — Dual Source | F12: 2024-Q4 | G12: 2025-Q1 | H12: 788000 | I12: 725000 | J12: 810000 | K12: Busch as dual-source alt; volume split threat | L12: Busch Vacuum — already qualified | M12: 740000 | N12: =H12-M12 | O12: =N12/H12 | P12: CLOSED
A13: N-009 | B13: Daikin Applied | C13: Process Chillers (EQ-012) | D13: 885000 | E13: Competitive Award | F13: 2024-Q4 | G13: 2025-Q1 | H13: 926000 | I13: 870000 | J13: 950000 | K13: Carrier as competitive alt; glycol loop specification leverage | L13: Carrier Corporation | M13: 885000 | N13: =H13-M13 | O13: =N13/H13 | P13: CLOSED
A14: N-010 | B14: Mobile Industrial Robots | C14: AMR Fleet (EQ-015) | D14: 380000 | E14: Competitive Award | F14: 2024-Q4 | G14: 2025-Q1 | H14: 404000 | I14: 370000 | J14: 420000 | K14: Locus Robotics and Omron in parallel eval; fleet SW requirement | L14: Omron AMR — evaluated but lower capability | M14: 380000 | N14: =H14-M14 | O14: =N14/H14 | P14: CLOSED
A17: SAVINGS PORTFOLIO SUMMARY
A18: Total Negotiations Logged | B18: =COUNTA(A5:A14)
A19: Closed Negotiations | B19: =COUNTIF(P5:P14,"CLOSED")+COUNTIF(P5:P14,"CLOSED — LTA active")
A20: Total Confirmed Savings (Closed Negotiations, USD) | B20: =SUMIF(P5:P14,"CLOSED",N5:N14)+SUMIF(P5:P14,"CLOSED — LTA active",N5:N14)
A21: Average Savings % (vs Initial Quote, Closed Only) | B21: =AVERAGEIF(P5:P14,"CLOSED",O5:O14)

Sheet S22_Capacity_Supplier_Facing
A1: S22 — Supplier Capacity Assessment — Program Demand vs Supplier Available Capacity
A2: Identifies capacity concentration risk at supplier level | Owner: Sourabh Tarodekar | Complements S10 Capacity Planning (equipment-side view) with a supply-side capacity view
A4: Equip Ref | B4: Supplier | C4: Component | D4: Est. Supplier Annual Capacity (units/yr) | E4: Program Volume Required (units/yr) | F4: % of Supplier Capacity Consumed | G4: Capacity Constraint Risk | H4: Lead Time to Add'l Capacity (wks) | I4: Flex Capacity Available (units) | J4: MOQ | K4: Order Frequency | L4: Safety Stock Coverage (wks) | M4: Buffer Recommendation | N4: Notes
A5: EQ-001 | B5: Edwards Vacuum | C5: Dry Screw Vacuum Pumps | D5: 120 | E5: 4 | F5: =E5/D5 | G5: LOW | H5: 16 | I5: 20 | J5: 1 | K5: Per program | L5: 8 | M5: 2-unit buffer on-site | N5: Edwards produces ~120 units/yr globally; 4 units = low concentration
A6: EQ-002 | B6: Pfeiffer Vacuum | C6: Turbomolecular Pumps | D6: 60 | E6: 3 | F6: =E6/D6 | G6: HIGH | H6: 18 | I6: 10 | J6: 1 | K6: Per program | L6: 12 | M6: 2-unit safety stock critical | N6: Pfeiffer TMP production ~60 units/yr globally; 3 units = 5% of output. Supply constraint at volume. Alt qualification essential.
A7: EQ-003 | B7: Thermco Systems | C7: High-Temp Tube Furnaces | D7: 45 | E7: 2 | F7: =E7/D7 | G7: LOW-MOD | H7: 20 | I7: 8 | J7: 1 | K7: Per program | L7: 10 | M7: 1 spare hot-zone set | N7: Thermco capacity adequate; BTU alt available
A8: EQ-004 | B8: Tokyo Electron Ltd | C8: Batch Oxidation Furnaces | D8: 150 | E8: 2 | F8: =E8/D8 | G8: LOW | H8: 24 | I8: 15 | J8: 1 | K8: Per program | L8: 14 | M8: Coordinated with TEL FSE | N8: TEL large OEM; 2 units = minimal fraction of global capacity
A9: EQ-005 | B9: Brooks Automation | C9: SCARA Robots | D9: 800 | E9: 6 | F9: =E9/D9 | G9: VERY LOW | H9: 12 | I9: 50 | J9: 2 | K9: Per program | L9: 6 | M9: Standard stock level | N9: Brooks Automation high-volume producer; 6 units trivial
A10: EQ-006 | B10: Daifuku | C10: Overhead Track Conveyor | D10: 25 | E10: 1 | F10: =E10/D10 | G10: MOD — custom design | H10: 30 | I10: 5 | J10: 1 | K10: Per project | L10: 0 | M10: No standard buffer — custom | N10: Each Daifuku conveyor is a custom civil project; capacity = design+install bandwidth, not inventory
A11: EQ-007 | B11: Air Liquide Eng. | C11: Process Gas Cabinets | D11: 200 | E11: 4 | F11: =E11/D11 | G11: LOW | H11: 16 | I11: 20 | J11: 1 | K11: Per program | L11: 8 | M11: 1 spare manifold assembly | N11: Air Liquide Eng. large manufacturer; 4 units = low share
A12: EQ-008 | B12: Linde Engineering | C12: Bulk Gas Storage Vessels | D12: 80 | E12: 1 | F12: =E12/D12 | G12: LOW | H12: 28 | I12: 5 | J12: 1 | K12: Per program | L12: 0 | M12: Long-lead only — no buffer | N12: Vessel is bespoke; 32-wk LT is design/fabrication not inventory
A13: EQ-009 | B13: Siemens AG | C13: DCS PLC S7-1500 | D13: 50000 | E13: 5 | F13: =E13/D13 | G13: VERY LOW | H13: 10 | I13: 500 | J13: 5 | K13: Annual blanket | L13: 12 | M13: Standard depot stock — Siemens USA | N13: Mass-manufactured; 5 units = negligible supply risk
A14: EQ-010 | B14: Inductive Automation | C14: SCADA Software Licenses | D14: Unlimited (SaaS) | E14: 3 | F14: N/A | G14: VERY LOW | H14: 0 | I14: N/A | J14: 1 | K14: On demand | L14: 0 | M14: Software — no physical buffer needed | N14: SaaS-adjacent model; license delivery instantaneous
A15: EQ-011 | B15: ABB Ltd | C15: Dry-Type Transformers | D15: 300 | E15: 2 | F15: =E15/D15 | G15: LOW | H15: 18 | I15: 10 | J15: 1 | K15: Per program | L15: 0 | M15: Long-lead; no buffer practical | N15: ABB large transformer OEM; 2 units = negligible share
A16: EQ-012 | B16: Daikin Applied | C16: Process Chiller Systems | D16: 400 | E16: 3 | F16: =E16/D16 | G16: LOW | H16: 18 | I16: 15 | J16: 1 | K16: Per program | L16: 6 | M16: Standard refrigerant spares kit | N16: Daikin Applied large US/JP manufacturer; low concentration
A17: EQ-013 | B17: Busch Vacuum | C17: Roots Blower Boosters | D17: 250 | E17: 6 | F17: =E17/D17 | G17: LOW | H17: 14 | I17: 20 | J17: 1 | K17: Per program | L17: 8 | M17: 2-unit buffer coordinated with EQ-001 | N17: Busch high-volume vacuum manufacturer; 6 units = low share
A18: EQ-014 | B18: Applied Materials | C18: RTP Tools | D18: 40 | E18: 2 | F18: =E18/D18 | G18: MOD-HIGH | H18: 24 | I18: 5 | J18: 1 | K18: Per program | L18: 0 | M18: No buffer — high-value; 30% deposit commitment | N18: AMAT RTP production limited; 2 units = notable share. Finance pre-approval required.
A19: EQ-015 | B19: Mobile Industrial Robots | C19: AMR Fleet (x10 robots) | D19: 5000 | E19: 10 | F19: =E19/D19 | G19: VERY LOW | H19: 14 | I19: 100 | J19: 10 | K19: Per program | L19: 0 | M19: Standard warranty + software update coverage | N19: MiR high-volume AMR producer; 10 units negligible

Sheet S23_Inventory_Buffer_Planning
A1: S23 — Inventory & Buffer Planning — Consumables, Spare Parts & Safety Stock
A2: Covers production consumables, critical spares (MTBF/MTTR model), and safety stock | Owner: Sourabh Tarodekar | Carrying cost = 20% | Production value from S01_Disclaimer_Assumptions
A4: SECTION A — CRITICAL SPARE PARTS (MTBF / MTTR MODEL)
A5: Part ID | B5: Part Description | C5: Equip Ref | D5: Supplier | E5: Class | F5: MTBF (hrs) | G5: MTTR (hrs) | H5: Annual Failures (Est.) | I5: Safety Stock (units) | J5: Unit Cost (USD) | K5: Annual Consumption (units) | L5: Inventory Value (USD) | M5: Annual Carry Cost (20%) | N5: Downtime Avoidance (hrs/yr) | O5: Annual Downtime Value Avoided (USD/yr) | P5: Notes
A6: SP-001 | B6: Dry Screw Pump Seal Set | C6: EQ-001 | D6: Edwards Vacuum | E6: A | F6: 8760 | G6: 4 | H6: 1 | I6: 2 | J6: 3200 | K6: 2 | L6: =J6*I6 | M6: =L6*0.2 | N6: =G6*H6 | O6: =N6*'S01_Disclaimer_Assumptions'!$B$33 | P6: Seals degrade; annual replacement expected; 2-set safety stock
A7: SP-002 | B7: Turbomolecular Pump Bearing | C7: EQ-002 | D7: Pfeiffer Vacuum | E7: A | F7: 4380 | G7: 8 | H7: 2 | I7: 2 | J7: 8500 | K7: 4 | L7: =J7*I7 | M7: =L7*0.2 | N7: =G7*H7 | O7: =N7*'S01_Disclaimer_Assumptions'!$B$33 | P7: CRITICAL — bearing failure = tool down; 2-set stock maintained
A8: SP-003 | B8: Turbomolecular Pump Controller | C8: EQ-002 | D8: Pfeiffer Vacuum | E8: A | F8: 8760 | G8: 16 | H8: 1 | I8: 1 | J8: 12000 | K8: 1 | L8: =J8*I8 | M8: =L8*0.2 | N8: =G8*H8 | O8: =N8*'S01_Disclaimer_Assumptions'!$B$33 | P8: Proprietary controller; no drop-in alt; Pfeiffer safety stock commitment
A9: SP-004 | B9: Furnace Heating Elements (8-zone set) | C9: EQ-003 | D9: Thermco Systems | E9: B | F9: 4380 | G9: 6 | H9: 2 | I9: 2 | J9: 4800 | K9: 4 | L9: =J9*I9 | M9: =L9*0.2 | N9: =G9*H9 | O9: =N9*'S01_Disclaimer_Assumptions'!$B$33 | P9: Zone element failure predictable; 2-set buffer; 2-4 wk replacement
A10: SP-005 | B10: Batch Furnace Process Tube | C10: EQ-004 | D10: Tokyo Electron Ltd | E10: B | F10: 8760 | G10: 12 | H10: 1 | I10: 1 | J10: 6500 | K10: 1 | L10: =J10*I10 | M10: =L10*0.2 | N10: =G10*H10 | O10: =N10*'S01_Disclaimer_Assumptions'!$B$33 | P10: Quartz tube — 12-wk lead time from TEL; must stock 1 spare
A11: SP-006 | B11: SCARA Robot Servo Drive | C11: EQ-005 | D11: Brooks Automation | E11: B | F11: 8760 | G11: 4 | H11: 1 | I11: 2 | J11: 3800 | K11: 2 | L11: =J11*I11 | M11: =L11*0.2 | N11: =G11*H11 | O11: =N11*'S01_Disclaimer_Assumptions'!$B$33 | P11: Drive failure low frequency; 2-unit stock adequate
A12: SP-007 | B12: Gas Cabinet MFC Assembly | C12: EQ-007 | D12: Air Liquide Eng. | E12: A | F12: 4380 | G12: 8 | H12: 2 | I12: 2 | J12: 5200 | K12: 4 | L12: =J12*I12 | M12: =L12*0.2 | N12: =G12*H12 | O12: =N12*'S01_Disclaimer_Assumptions'!$B$33 | P12: MFC drift = recalibration or replacement; high-use spare
A13: SP-008 | B13: DCS CPU Module — S7-1500 | C13: EQ-009 | D13: Siemens AG | E13: A | F13: 43800 | G13: 2 | H13: 0.2 | I13: 2 | J13: 4200 | K13: 1 | L13: =J13*I13 | M13: =L13*0.2 | N13: =G13*H13 | O13: =N13*'S01_Disclaimer_Assumptions'!$B$33 | P13: CPU failure rare; 2 on-site + Siemens depot replenishment
A14: SP-009 | B14: Chiller Compressor Capacitor Kit | C14: EQ-012 | D14: Daikin Applied | E14: C | F14: 8760 | G14: 2 | H14: 1 | I14: 2 | J14: 850 | K14: 2 | L14: =J14*I14 | M14: =L14*0.2 | N14: =G14*H14 | O14: =N14*'S01_Disclaimer_Assumptions'!$B$33 | P14: Capacitor kit; standard maintenance item; low cost
A15: SP-010 | B15: RTP Lamp Array (set of 12) | C15: EQ-014 | D15: Applied Materials | E15: A | F15: 4380 | G15: 8 | H15: 2 | I15: 2 | J15: 18500 | K15: 4 | L15: =J15*I15 | M15: =L15*0.2 | N15: =G15*H15 | O15: =N15*'S01_Disclaimer_Assumptions'!$B$33 | P15: Highest-value spare; AMAT recommends 2-set safety stock; 8-wk LT
A16: SP-011 | B16: AMR Battery Pack | C16: EQ-015 | D16: MiR | E16: C | F16: 4380 | G16: 1 | H16: 2 | I16: 4 | J16: 1200 | K16: 8 | L16: =J16*I16 | M16: =L16*0.2 | N16: =G16*H16 | O16: =N16*'S01_Disclaimer_Assumptions'!$B$33 | P16: Battery degradation predictable; 4-pack standard; MiR swap warranty
A17: SP-012 | B17: Roots Blower Booster Rotor | C17: EQ-013 | D17: Busch Vacuum | E17: B | F17: 8760 | G17: 6 | H17: 1 | I17: 1 | J17: 2800 | K17: 1 | L17: =J17*I17 | M17: =L17*0.2 | N17: =G17*H17 | O17: =N17*'S01_Disclaimer_Assumptions'!$B$33 | P17: Coordinated with Edwards EQ-001 maintenance schedule
A18: SPARE PARTS TOTAL | L18: =SUM(L6:L17) | M18: =SUM(M6:M17)
A20: SECTION B — PRODUCTION CONSUMABLES & RAW MATERIALS
A21: Item ID | B21: Item Description | C21: Category | D21: Supplier | E21: Lead Time (wks) | F21: Avg Weekly Demand (units) | G21: Demand Std Dev | H21: Service Level Target | I21: Safety Stock (units) | J21: Reorder Point (units) | K21: EOQ (units) | L21: Current Stock | M21: Unit Cost (USD) | N21: Inventory Value (USD) | O21: Notes
A22: CM-001 | B22: Process N2 Gas (cylinder sets) | C22: Process Gas | D22: Air Liquide / Linde | E22: 2 | F22: 12 | G22: 3 | H22: 0.98 | I22: 10 | J22: 34 | K22: 50 | L22: 45 | M22: 380 | N22: =M22*L22 | O22: High-consumption; order weekly; dual-source reduces stockout risk
A23: CM-002 | B23: Quartz Process Tubes (spare) | C23: Process Consumable | D23: Heraeus / Shin-Etsu | E23: 6 | F23: 0.5 | G23: 0.2 | H23: 0.99 | I23: 4 | J23: 7 | K23: 6 | L23: 8 | M23: 2200 | N23: =M23*L23 | O23: Long-lead quartz; 6-wk LT drives high safety stock
A24: CM-003 | B24: Photoresist (process grade) | C24: Process Chemical | D24: JSR Corporation | E24: 4 | F24: 8 | G24: 2.5 | H24: 0.99 | I24: 10 | J24: 42 | K24: 60 | L24: 55 | M24: 1800 | N24: =M24*L24 | O24: High-value chemical; 4-wk LT; temperature-controlled storage
A25: CM-004 | B25: Argon Gas (bulk, per cylinder) | C25: Process Gas | D25: Linde Engineering | E25: 1 | F25: 6 | G25: 1.5 | H25: 0.97 | I25: 5 | J25: 17 | K25: 40 | L25: 30 | M25: 290 | N25: =M25*L25 | O25: Low risk; Linde on-site contract; auto-replenishment
A26: CM-005 | B26: Chemical Mechanical Planarization Slurry | C26: Process Chemical | D26: Cabot Microelectronics | E26: 3 | F26: 4 | G26: 1.5 | H26: 0.99 | I26: 8 | J26: 20 | K26: 40 | L26: 25 | M26: 1500 | N26: =M26*L26 | O26: Specialty chemical; 2 approved sources; shelf life 6 months
A27: CM-006 | B27: Cleaning Solvents (IPA, Acetone) | C27: Facility Chemical | D27: VWR / Fisher Scientific | E27: 1 | F27: 10 | G27: 3 | H27: 0.95 | I27: 8 | J27: 18 | K27: 80 | L27: 65 | M27: 45 | N27: =M27*L27 | O27: Commodity; easy dual-source; low-cost; broad availability
A28: CONSUMABLES TOTAL | N28: =SUM(N22:N27)

Sheet S24_Asset_Tracking
A1: S24 — Asset Tracking Register — Equipment Fleet Lifecycle & Physical Status
A2: Tracks all 45 physical assets by serial/tag, location, lifecycle state, maintenance & warranty | Owner: Sourabh Tarodekar | Register is platform-level (15 rows); Qty column expands to 45 physical units total | Feeds S29 ROI Tracker and S25 Milestone Gate Tracker
A4: Asset Tag | B4: Equip Ref | C4: Asset Description | D4: Serial # (Synthetic) | E4: Qty | F4: Location (Zone/Bay) | G4: Current Status | H4: Purchase Date | I4: Install Date | J4: Commiss. Date | K4: Remaining Lifetime (yrs) | L4: Replace Target Year | M4: Replacement Cost Est. (USD) | N4: Warranty Expiry | O4: Support Contract | P4: Notes
A5: AST-001 | B5: EQ-001 | C5: Dry Screw Vacuum Pump (x4) | D5: VSP-2025-001/004 | E5: 4 | F5: Bay A — Vacuum Zone | G5: IN PRODUCTION | H5: 2025-02-15 | I5: 2025-09-01 | J5: 2025-11-15 | K5: 10 | L5: 2035 | M5: 890000 | N5: 2025-Q4 (see contract) | O5: Edwards Annual PM | P5: Post-Brexit logistics; Busch backup activated
A6: AST-002 | B6: EQ-002 | C6: Turbomolecular Pump (x3) | D6: TMP-2025-101/103 | E6: 3 | F6: Bay A — Vacuum Zone | G6: IN PRODUCTION | H6: 2025-02-20 | I6: 2025-11-01 | J6: 2025-12-15 | K6: 8 | L6: 2033 | M6: 1200000 | N6: 2025-Q4 (see contract) | O6: Pfeiffer 24/7 support | P6: CRITICAL path item; bearing safety stock maintained
A7: AST-003 | B7: EQ-003 | C7: Tube Furnace System (x2) | D7: THF-2025-201/202 | E7: 2 | F7: Bay B — Thermal Zone | G7: IN PRODUCTION | H7: 2025-01-20 | I7: 2025-09-15 | J7: 2025-11-20 | K7: 13 | L7: 2038 | M7: 1350000 | N7: 2025-Q4 (see contract) | O7: Thermco 3yr full service | P7: FAT completed Austin TX; recipe transfer done
A8: AST-004 | B8: EQ-004 | C8: Batch Oxidation Furnace (x2) | D8: BOF-2025-301/302 | E8: 2 | F8: Bay B — Thermal Zone | G8: QUALIFIED — PQ in progress | H8: 2025-02-10 | I8: 2025-11-15 | J8: Pending | K8: 13 | L8: 2038 | M8: 1700000 | N8: 2025-Q4 (see contract) | O8: TEL 3yr comprehensive | P8: JPY FX hedged; structural reinforcement complete
A9: AST-005 | B9: EQ-005 | C9: SCARA Robot (x6) | D9: SCR-2025-401/406 | E9: 6 | F9: Bay C — Robotics Zone | G9: IN PRODUCTION | H9: 2025-01-15 | I9: 2025-09-01 | J9: 2025-11-10 | K9: 8 | L9: 2033 | M9: 2200000 | N9: 2025-Q4 (see contract) | O9: Brooks MES+mech 2yr | P9: MES integration verified; OEE above plan
A10: AST-006 | B10: EQ-006 | C10: Overhead Conveyor (x1 system) | D10: OTC-2025-501 | E10: 1 | F10: Bays A-C — Overhead Track | G10: INSTALLED — commissioning | H10: 2025-02-20 | I10: 2025-11-20 | J10: Pending | K10: 10 | L10: 2035 | M10: 560000 | N10: 2025-Q4 (see contract) | O10: Daifuku civil+mech 2yr | P10: Civil interface complete; Wi-Fi nav calibration in progress
A11: AST-007 | B11: EQ-007 | C11: Process Gas Cabinet (x4) | D11: PGC-2025-601/604 | E11: 4 | F11: Bay D — Gas Room | G11: IN PRODUCTION | H11: 2025-02-28 | I11: 2025-10-01 | J11: 2025-11-30 | K11: 10 | L11: 2035 | M11: 1040000 | N11: 2025-Q4 (see contract) | O11: Air Liquide annual cert | P11: Hazmat permit closed; MFC calibration schedule active
A12: AST-008 | B12: EQ-008 | C12: Bulk Gas Storage (x1 system) | D12: BGS-2025-701 | E12: 1 | F12: External — Tank Farm | G12: IN PRODUCTION | H12: 2025-02-20 | I12: 2025-11-10 | J12: 2025-12-01 | K12: 18 | L12: 2043 | M12: 450000 | N12: 2025-Q4 (see contract) | O12: Linde site contract | P12: 32-wk LT; on-site Linde maintenance contract
A13: AST-009 | B13: EQ-009 | C13: DCS — Siemens S7-1500 (x5) | D13: DCS-2025-801/805 | E13: 5 | F13: Control Room | G13: IN PRODUCTION | H13: 2025-01-28 | I13: 2025-09-01 | J13: 2025-11-01 | K13: 8 | L13: 2033 | M13: 1100000 | N13: 2025-Q4 (see contract) | O13: Siemens Gold Support | P13: Cybersecurity audit Month 4; LTA pricing locked
A14: AST-010 | B14: EQ-010 | C14: SCADA Platform (x3 licenses) | D14: SCA-2025-901/903 | E14: 3 | F14: Control Room (virtual) | G14: IN PRODUCTION | H14: 2025-02-05 | I14: 2025-09-01 | J14: 2025-11-01 | K14: 6 | L14: 2031 | M14: 330000 | N14: 2025-Q4 (see contract) | O14: Inductive Auto subscription | P14: Annual license renewal; IT/OT integration stable
A15: AST-011 | B15: EQ-011 | C15: Dry-Type Transformer (x2) | D15: TRF-2025-1001/1002 | E15: 2 | F15: Electrical Room | G15: IN PRODUCTION | H15: 2025-02-01 | I15: 2025-08-15 | J15: 2025-10-01 | K15: 23 | L15: 2048 | M15: 560000 | N15: 2050-02-01 | O15: ABB manufacturer warranty | P15: Reused partial from prior program; new units installed
A16: AST-012 | B16: EQ-012 | C16: Process Chiller (x3) | D16: PCH-2025-1101/1103 | E16: 3 | F16: Mechanical Room | G16: IN PRODUCTION | H16: 2025-01-30 | I16: 2025-09-15 | J16: 2025-11-20 | K16: 13 | L16: 2038 | M16: 1150000 | N16: 2025-Q4 (see contract) | O16: Daikin annual PM | P16: Glycol loop stable; JPY FX hedged
... A19: AST-015 | B19: EQ-015 | C19: AMR Fleet (x10 robots) | D19: AMR-2025-1401/1410 | E19: 10 | F19: All Bays — Fleet routing | G19: IN PRODUCTION | H19: 2025-02-05 | I19: 2025-09-15 | J19: 2025-11-15 | K19: 6 | L19: 2031 | M19: 500000 | N19: 2025-Q4 (see contract) | O19: MiR fleet management sub | P19: Wi-Fi integration stable; Phase 2 routing optimization pending
A22: FLEET SUMMARY
A23: Total Assets Tracked (sum of Qty) | B23: =SUM(E5:E19)
A24: Equipment Platforms | B24: =COUNTA(A5:A19)
A25: Assets In Production (platforms) | B25: =COUNTIF(G5:G19,"IN PRODUCTION")
A26: Total Replacement Value (Portfolio, USD) | B26: =SUM(M5:M19)
A27: Average Remaining Lifetime (yrs) | B27: =AVERAGE(K5:K19)

Sheet S25_Milestone_Gate_Tracker
A1: S25 — Program Milestone & Gate Review Tracker — Greenfield Expansion Phase II
A2: Gate-controlled program: G0 Concept -> G1 Definition -> G2 Execution -> G3 Commissioning -> G4 Qualification -> G5 Production Release | All gate entry criteria must be GREEN before approval; AMBER items require documented acceptance; RED items are blockers.
A4: GATE REVIEW STATUS SUMMARY
A5: Gate | B5: Gate Name | C5: Target Date | D5: Actual/Forecast Date | E5: Gate Status | F5: Entry Criteria Met | G5: Approver | H5: Approval Date | I5: Open Blockers (count) | J5: Decision | K5: Notes
A6: G0 | B6: Program Concept & Business Case | C6: 2025-02-28 | D6: 2025-03-10 | E6: APPROVED | F6: 1 | G6: VP Engineering + CFO | H6: 2025-03-10 | I6: 0 | J6: GO | K6: Business case approved. Scenario B selected. AR-2025-0082 submitted. All G0 criteria met.
A7: G1 | B7: Supplier Selection & AR Approval | C7: 2025-04-07 | D7: 2025-04-05 | E7: APPROVED | F7: 0.95 | G7: VP Engineering + CFO | H7: 2025-04-07 | I7: 1 | J7: CONDITIONAL GO | K7: AR approved. All POs placed except EQ-007 (Air Liquide quote negotiation ongoing). Conditional GO: EQ-007 PO must be placed within 2 weeks.
A8: G2 | B8: Equipment Build & FAT Complete | C8: 2025-09-01 | D8: 2025-09-08 | E8: IN PROGRESS | F8: 0.6 | G8: Director of Engineering | H8: TBD | I8: 3 | J8: PENDING | K8: EQ-003 FAT complete. EQ-004, EQ-014 FAT scheduled. EQ-002 at risk due to Pfeiffer lead time. 3 open blockers: EQ-002 delivery, EQ-007 hazmat permit, EQ-006 civil drawing freeze.
A9: G3 | B9: Site Installation & Utility Commissioning | C9: 2025-10-27 | D9: 2025-10-27 | E9: NOT STARTED | F9: 0 | G9: Program Manager | H9: TBD | I9: 0 | J9: TBD | K9: Gate G3 not yet in scope. Entry criteria to be reviewed at G2 approval. Key dependency: all equipment delivered and installed; utility hookup complete.
A10: G4 | B10: Process Qualification (PQ) Complete | C10: 2025-11-24 | D10: 2025-11-24 | E10: NOT STARTED | F10: 0 | G10: Director of Engineering | H10: TBD | I10: 0 | J10: TBD | K10: Gate G4 requires: PQ protocol approved; first-article wafer data reviewed; yield >94%; equipment uptime demonstrated >90% over 30-day window.
A11: G5 | B11: Production Release & Ramp | C11: 2025-12-08 | D11: 2025-12-08 | E11: NOT STARTED | F11: 0 | G11: VP Engineering | H11: TBD | I11: 0 | J11: TBD | K11: Gate G5 requires: G4 approved; SOP training complete; spare parts inventory stocked; maintenance schedule published; manufacturing handover signed off.
A14: DETAILED PROGRAM MILESTONES
A15: Milestone ID | B15: Gate | C15: Milestone Description | D15: Equipment Ref | E15: Planned Date | F15: Forecast Date | G15: Actual Date | H15: Owner | I15: Status | J15: % Complete | K15: Predecessor | L15: Notes
A16: M-001 | B16: G0 | C16: Business case and scenario analysis | D16: ALL | E16: 2025-03-10 | F16: 2025-03-10 | G16: 2025-03-10 | H16: Sourabh Tarodekar | I16: COMPLETE | J16: 1 | K16: — | L16: Scenario B approved; S13 model signed off by Finance
A17: M-002 | B17: G0 | C17: Capital AR (AR-2025-0082) submitted to Finance | D17: ALL | E17: 2025-03-19 | F17: 2025-03-19 | G17: 2025-03-19 | H17: R. Patel | I17: COMPLETE | J17: 1 | K17: M-001 | L17: AR submitted with full TCO and NPV justification
A18: M-003 | B18: G1 | C18: AR approval received from VP Eng + CFO | D18: ALL | E18: 2025-04-07 | F18: 2025-04-05 | G18: 2025-04-05 | H18: Sourabh Tarodekar | I18: COMPLETE | J18: 1 | K18: M-002 | L18: Approved ahead of schedule — enables early PO placement
A19: M-004 | B19: G1 | C19: Long-lead POs placed (EQ-002, EQ-004, EQ-008, EQ-014) | D19: Multiple | E19: 2025-04-07 | F19: 2025-04-05 | G19: 2025-04-05 | H19: S. Kim | I19: COMPLETE | J19: 1 | K19: M-003 | L19: All 4 long-lead POs placed. Supplier delivery schedules confirmed.
A20: M-005 | B20: G1 | C20: EQ-007 hazmat permit application filed | D20: EQ-007 | E20: 2025-03-24 | F20: 2025-03-22 | G20: 2025-03-22 | H20: D. Walsh | I20: COMPLETE | J20: 1 | K20: M-003 | L20: Filed 2 days early. Consultant engaged. Permit approval pending.
A21: M-006 | B21: G1 | C21: All remaining equipment POs placed | D21: Multiple | E21: 2025-04-21 | F21: 2025-04-18 | G21: 2025-04-18 | H21: S. Kim | I21: COMPLETE | J21: 1 | K21: M-003 | L21: 11 remaining POs placed. Full portfolio committed.
A22: M-007 | B22: G1 | C22: FX hedge contracts executed (EUR + JPY) | D22: EQ-004/007 | E22: 2025-05-08 | F22: 2025-05-08 | G22: 2025-05-08 | H22: R. Patel | I22: COMPLETE | J22: 1 | K22: M-004 | L22: Forward contracts locked. EUR 1.09, JPY 149.0.
A23: M-008 | B23: G2 | C23: EQ-003 Thermco FAT complete | D23: EQ-003 | E23: 2025-07-14 | F23: 2025-07-14 | G23: — | H23: M. Chen | I23: IN PROGRESS | J23: 0.4 | K23: M-006 | L23: Protocol approved. FAT scheduled Week 22. Recipe transfer plan agreed.
A24: M-009 | B24: G2 | C24: EQ-001 & EQ-013 pump FATs complete | D24: EQ-001/013 | E24: 2025-07-28 | F24: 2025-07-28 | G24: — | H24: S. Kim | I24: NOT STARTED | J24: 0 | K24: M-006 | L24: Coordinated FAT schedule required; confirm with both suppliers
A25: M-010 | B25: G2 | C25: EQ-004 TEL batch furnace FAT complete (Japan) | D25: EQ-004 | E25: 2025-08-11 | F25: 2025-08-18 | G25: — | H25: M. Chen | I25: AT RISK | J25: 0.15 | K25: M-006 | L25: Extended lead time (28 wks) puts FAT at Week 29 — 1 week behind plan
A26: M-011 | B26: G2 | C26: EQ-014 AMAT RTP FAT complete | D26: EQ-014 | E26: 2025-08-04 | F26: 2025-08-04 | G26: — | H26: M. Chen | I26: IN PROGRESS | J26: 0.25 | K26: M-004 | L26: AMAT FAT protocol approved. Edge ring lot included. Site visit booked.
A27: M-012 | B27: G2 | C27: EQ-002 Pfeiffer TMP FAT complete | D27: EQ-002 | E27: 2025-08-18 | F27: 2025-09-01 | G27: — | H27: S. Kim | I27: AT RISK | J27: 0.05 | K27: M-004 | L27: CRITICAL: 26-wk LT pushes FAT to Week 30. Single-source risk active.
... A36: M-021 | B36: G5 | C36: Manufacturing handover and production release | D36: ALL | E36: 2025-12-08 | F36: 2025-12-08 | G36: — | H36: A. Novak | I36: NOT STARTED | J36: 0 | K36: M-020 | L36: SOP training, spare parts stocked, maintenance schedule published
A39: PROGRAM PROGRESS SUMMARY
A40: Total Milestones | B40: =COUNTA(A16:A36)
A41: Milestones Complete | B41: =COUNTIF(I16:I36,"COMPLETE")
A42: Milestones In Progress | B42: =COUNTIF(I16:I36,"IN PROGRESS")
A43: Milestones At Risk or Blocked | B43: =COUNTIF(I16:I36,"AT RISK")
A44: Overall Program % | B44: =AVERAGE(J16:J36)
A45: Gates Complete / Approved | B45: =COUNTIF(E6:E11,"APPROVED")
A46: Open Blockers Across All Gates | B46: =SUM(I6:I11)

Sheet S26_Engineering_Change_Orders
A1: S26 — Engineering Change Orders (ECO) Register — Phase II Program
A2: Formal ECO register for all design changes — internal, customer-driven & regulatory | Owner: Sourabh Tarodekar | Related VDCs tracked in S27_Vendor_Design_Changes
A4: ECO ID | B4: ECO Title | C4: Originator | D4: Origin Type | E4: Affected Equip | F4: Change Description | G4: Reason | H4: Cost Impact (USD) | I4: Schedule Impact (wks) | J4: Quality/Yield Impact | K4: Requalif. Required? | L4: ECO Status | M4: Design Auth. Approval Date | N4: Submitted Date | O4: Impl. Date | P4: Linked VDC
A5: ECO-001 | B5: Gas Cabinet Safety Interlock Upgrade | C5: Facilities / Safety | D5: Regulatory | E5: EQ-007 | F5: Add secondary pressure interlock and emergency shutoff valve per updated NFPA 72 guidance | G5: Regulatory compliance — permit condition | H5: 28500 | I5: 2 | J5: No yield impact; safety-critical improvement | K5: YES — re-FAT on gas cabinet | L5: IMPLEMENTED | M5: 2025-03-10 | N5: 2025-03-24 | O5: 2025-05-15 | P5: —
A6: ECO-002 | B6: TEL Furnace Recipe Parameter Change | C6: Process Engineering | D6: Customer-Driven | E6: EQ-004 | F6: Update oxidation time profile on Recipe Set B3 to achieve customer-specified film uniformity +/-1.5% | G6: Customer quality requirement tightened for Phase III product | H6: 12000 | I6: 1 | J6: Yield improvement expected +0.5% on PF-A | K6: YES — PQ re-run for Recipe B3 | L6: IMPLEMENTED | M6: 2025-04-02 | N6: 2025-04-08 | O6: 2025-07-20 | P6: VDC-003
A7: ECO-003 | B7: RTP Edge Ring Material Substitution | C7: Process Engineering / AMAT | D7: Internal Engineering | E7: EQ-014 | F7: Replace SiC edge ring with high-purity CVD SiC — improved thermal uniformity at >900C | G7: Process optimization — reduce edge exclusion zone | H7: 15000 | I7: 0 | J7: Yield improvement +0.8% at wafer edge | K7: YES — thermal profile re-validation | L7: IMPLEMENTED | M7: 2025-02-15 | N7: 2025-02-28 | O7: 2025-06-10 | P7: VDC-001
A8: ECO-004 | B8: MES Integration Protocol Revision | C8: Controls / IT-OT | D8: Internal Engineering | E8: EQ-005/009/010 | F8: Update SCADA-to-MES data handshake to use REST API v2.1 (replace deprecated SOAP endpoints) | G8: IT/OT architecture upgrade — eliminates latency bug | H8: 8000 | I8: 1 | J8: No yield impact; +15ms improvement in alarm response | K8: NO — software change only | L8: IMPLEMENTED | M8: 2025-05-10 | N8: 2025-05-17 | O8: 2025-07-01 | P8: —
A9: ECO-005 | B9: Chiller Glycol Concentration Adjustment | C9: Facilities Engineering | D9: Internal Engineering | E9: EQ-012 | F9: Increase inhibited glycol concentration from 30% to 35% to reduce corrosion in stainless loop | G9: Preventive — loop inspection found minor oxidation at fittings | H9: 3500 | I9: 0 | J9: No yield impact; improved system longevity | K9: NO | L9: IMPLEMENTED | M9: 2025-06-01 | N9: 2025-06-05 | O9: 2025-06-15 | P9: —
A10: ECO-006 | B10: Dry Screw Pump N2 Purge Line Upgrade | C10: Engineering / Edwards | D10: Internal Engineering | E10: EQ-001/013 | F10: Increase N2 purge flow from 8 L/min to 12 L/min to reduce pump seal degradation rate | G10: Reliability improvement — seal MTBF extended by ~20% | H10: 18000 | I10: 1 | J10: No yield impact; MTBF improvement 8,760 -> 10,500 hrs | K10: NO — purge line change only | L10: IN REVIEW | M10: 2025-07-12 | N10: Pending | O10: TBC | P10: —
A11: ECO-007 | B11: DCS Cybersecurity Firmware Update | C11: Controls / InfoSec | D11: Regulatory | E11: EQ-009 | F11: Apply Siemens TIA Portal firmware patch v19.0.3 per ICS-CERT advisory ICSA-2025-089 | G11: Security patch — critical vulnerability mitigation | H11: 5000 | I11: 0 | J11: No yield impact; mandatory security update | K11: NO — firmware only; controlled change | L11: IN REVIEW | M11: 2025-07-20 | N11: Pending | O11: 2025-08-15 target | P11: —
A12: ECO-008 | B12: AMR Fleet Route Optimization v2 | C12: Operations / MiR | D12: Internal Engineering | E12: EQ-015 | F12: Implement MiR Fleet Manager route algorithm Phase 2 to reduce carrier wait time by ~18% | G12: Operational efficiency — program improvement | H12: 6000 | I12: 0 | J12: No yield impact; +18% throughput improvement for AMR | K12: NO — software update | L12: IMPLEMENTED | M12: 2025-08-01 | N12: 2025-08-05 | O12: 2025-09-01 | P12: —
A13: ECO-009 | B13: Bulk Gas Vessel Pressure Relief Resetting | C13: Safety / Linde | D13: Regulatory | E13: EQ-008 | F13: Recalibrate PRV setpoints from 320 PSI to 300 PSI per updated site pressure vessel code | G13: Regulatory requirement — insurance inspection finding | H13: 4200 | I13: 0 | J13: No yield impact; safety compliance | K13: YES — pressure test re-cert required | L13: IN REVIEW | M13: 2025-08-10 | N13: Pending | O13: 2025-09-15 target | P13: VDC-005
A14: ECO-010 | B14: Furnace Zone Controller Firmware Upgrade | C14: Process Engineering / Thermco | D14: Internal Engineering | E14: EQ-003 | F14: Upgrade Thermco zone controller firmware v4.1->v4.3 for improved PID auto-tune algorithm | G14: Process stability improvement — temperature uniformity +/-0.3C better | H14: 7000 | I14: 0 | J14: Yield improvement expected +0.2% | K14: YES — process re-qualification run required | L14: DRAFT | M14: 2025-09-05 | N14: Pending | O14: TBC | P14: —
A17: ECO SUMMARY
A18: Total ECOs Raised | B18: =COUNTA(A5:A14)
A19: Implemented / Closed | B19: =COUNTIF(L5:L14,"IMPLEMENTED")
A20: In Review | B20: =COUNTIF(L5:L14,"IN REVIEW")
A21: Total Cost Impact (USD) | B21: =SUM(H5:H14)
A22: Requalification Required (count of YES) | B22: =COUNTIF(K5:K14,"YES*")

Sheet S27_Vendor_Design_Changes
A1: S27 — Vendor Design Changes (VDC) Register — Supplier-Initiated Changes
A2: Tracks all supplier-initiated design changes — approval, risk, disposition | Owner: Sourabh Tarodekar | Linked ECOs in S26_Engineering_Change_Orders
A4: VDC ID | B4: Linked ECO | C4: Supplier | D4: Equip Ref | E4: Change Description | F4: Change Type | G4: Supplier Reason | H4: Notified Date | I4: Customer Approval Req? | J4: Risk Assessment | K4: Disposition | L4: Conditions | M4: Requalif. Req? | N4: Approval Date | O4: Notes
A5: VDC-001 | B5: ECO-003 | C5: Applied Materials | D5: EQ-014 | E5: CVD SiC edge ring material substitution (SiC density >=3.12 g/cm3 -> premium CVD SiC grade) | F5: Function | G5: Improved dimensional stability at high temp; supplier quality improvement | H5: 2025-02-10 | I5: YES | J5: LOW — dimensional spec maintained; thermal improvement expected | K5: ACCEPT — CONDITIONAL | L5: Re-validate thermal profile; confirm +/-1.5% uniformity spec met | M5: YES | N5: 2025-02-28 | O5: Triggered ECO-003; AMAT FSE on-site for re-validation
A6: VDC-002 | B6: — | C6: Pfeiffer Vacuum | D6: EQ-002 | E6: Magnet assembly supplier change — from EU Tier-2 to Asian Tier-2 supplier (equivalent grade spec) | F6: Form | G6: Tier-2 supplier consolidation; cost reduction in Pfeiffer supply chain | H6: 2025-03-05 | I6: YES | J6: HIGH — magnetic performance critical to TMP speed/accuracy | K6: REJECT | L6: Pfeiffer to provide full equivalency test data; re-submit with material certs | M6: YES | N6: — | O6: REJECTED: insufficient test data provided. Pfeiffer re-submitting with test certs Q3-2025
A7: VDC-003 | B7: ECO-002 | C7: Tokyo Electron Ltd | D7: EQ-004 | E7: PID zone controller firmware update v3.8 -> v4.0 — new thermal ramp algorithm | F7: Fit/Function | G7: TEL global platform update — improved uniformity for 65nm+ processes | H7: 2025-03-20 | I7: YES | J7: LOW-MOD — algorithm change; verified by TEL at factory on identical system | K7: ACCEPT — CONDITIONAL | L7: Run 3-wafer PQ qualification lot before production release | M7: YES | N7: 2025-04-08 | O7: TEL global platform upgrade; triggered ECO-002 for recipe B3 update
A8: VDC-004 | B8: — | C8: Brooks Automation | D8: EQ-005 | E8: SCARA servo drive firmware update v2.3 -> v2.5 — improved torque compensation | F8: Function | G8: Bug fix — eliminates 0.05mm positional drift under thermal load | H8: 2025-04-01 | I8: NO | J8: LOW — positional improvement; no form/fit change | K8: ACCEPT | L8: No requalification required; monitor 30-day performance after update | M8: NO | N8: 2025-04-08 | O8: Brooks minor update; no qualification re-trigger required
A9: VDC-005 | B9: ECO-009 | C9: Linde Engineering | D9: EQ-008 | E9: Pressure relief valve manufacturer change (same setpoint; different brand — Leser -> Emerson) | F9: Form | G9: Leser discontinuing model; Emerson equivalent specification | H9: 2025-05-15 | I9: YES | J9: MOD — safety-critical component; must verify setpoint and certification | K9: ACCEPT — CONDITIONAL | L9: Provide Emerson PED certification and hydrostatic test report | M9: YES | N9: Pending | O9: Triggered ECO-009 for pressure re-certification; Emerson certs received; review in progress
A10: VDC-006 | B10: — | C10: Siemens AG | D10: EQ-009 | E10: TIA Portal software v18 -> v19 migration — new tag management structure | F10: Fit | G10: Siemens mandatory platform migration for security patch compatibility | H10: 2025-06-10 | I10: YES | J10: LOW — software change; backward compatible; Siemens certified | K10: ACCEPT | L10: Apply per cybersecurity ECO-007 schedule; backup current config before update | M10: NO | N10: 2025-06-20 | O10: Coordinated with ECO-007 cybersecurity update; Siemens migration guide followed
A11: VDC-007 | B11: — | C11: Daikin Applied | D11: EQ-012 | E11: Refrigerant change R-410A -> R-454B (HFO blend) — regulatory compliance | F11: Function | G11: ASHRAE 34 update and EU F-Gas regulation phase-down of HFC refrigerants | H11: 2025-07-01 | I11: YES | J11: MOD — different refrigerant chemistry; system pressure slightly lower; seals reviewed | K11: ACCEPT — CONDITIONAL | L11: Daikin to provide updated system performance data and seal compatibility certs | M11: NO | N11: Pending | O11: Regulatory-driven; R-454B lower GWP. Daikin submitting updated commissioning data.
A14: VDC SUMMARY
A15: Total VDCs Logged | B15: =COUNTA(A5:A11)
A16: Accepted (incl. Conditional) | B16: =COUNTIF(K5:K11,"ACCEPT*")
A17: Rejected | B17: =COUNTIF(K5:K11,"REJECT")
A18: Requalification Required | B18: =COUNTIF(M5:M11,"YES")

Sheet S28_Yield_Production_Metrics
A1: S28 — Yield & Production Metrics — OEE, Process Yield & Quality Tracking
A2: OEE = Availability x Performance x Quality | Yield target: 96% (S01 Assumptions) | Owner: Sourabh Tarodekar | Monthly reporting by process tool | Feeds S29 ROI Tracker
A4: Equip ID | B4: Tool | C4: Period | D4: Availability (%) | E4: Performance (%) | F4: Quality Rate (%) | G4: OEE (%) | H4: Planned Yield (%) | I4: Actual Yield (%) | J4: Yield Variance (pp) | K4: Units Produced | L4: Units Scrapped | M4: Scrap Rate (%) | N4: Top Defect Mode | O4: Corrective Action
A5: EQ-003 | B5: Tube Furnace — Thermco | C5: Jul-2025 | D5: 0.905 | E5: 0.96 | F5: 0.978 | G5: =D5*E5*F5 | H5: 0.96 | I5: 0.941 | J5: =I5-H5 | K5: 15200 | L5: 890 | M5: =L5/K5 | N5: Zone 3 temp uniformity +/-1.8C | O5: TEL FSE reviewed; zone 3 element replaced; uniformity now +/-1.2C
A6: EQ-003 | B6: Tube Furnace — Thermco | C6: Aug-2025 | D6: 0.92 | E6: 0.97 | F6: 0.983 | G6: =D6*E6*F6 | H6: 0.96 | I6: 0.958 | J6: =I6-H6 | K6: 16400 | L6: 277 | M6: =L6/K6 | N6: Minor particle contamination — wafer edge | O6: Cleaning protocol updated; edge exclusion improved
A7: EQ-003 | B7: Tube Furnace — Thermco | C7: Sep-2025 | D7: 0.93 | E7: 0.97 | F7: 0.987 | G7: =D7*E7*F7 | H7: 0.96 | I7: 0.966 | J7: =I7-H7 | K7: 17200 | L7: 228 | M7: =L7/K7 | N7: Within spec — no dominant defect | O7: No action required
A8: EQ-004 | B8: Batch Oxidation Furnace — TEL | C8: Jul-2025 | D8: 0.91 | E8: 0.955 | F8: 0.975 | G8: =D8*E8*F8 | H8: 0.96 | I8: 0.933 | J8: =I8-H8 | K8: 10800 | L8: 270 | M8: =L8/K8 | N8: Batch loading uniformity — slot 1/24 variation | O8: TEL batch loading algorithm updated; batch review at G4 gate
A9: EQ-004 | B9: Batch Oxidation Furnace — TEL | C9: Aug-2025 | D9: 0.91 | E9: 0.965 | F9: 0.978 | G9: =D9*E9*F9 | H9: 0.96 | I9: 0.941 | J9: =I9-H9 | K9: 11200 | L9: 246 | M9: =L9/K9 | N9: Improving — loading fix effective | O9: Monitor; target 95%+ OEE next period
A10: EQ-004 | B10: Batch Oxidation Furnace — TEL | C10: Sep-2025 | D10: 0.92 | E10: 0.97 | F10: 0.982 | G10: =D10*E10*F10 | H10: 0.96 | I10: 0.954 | J10: =I10-H10 | K10: 11850 | L10: 195 | M10: =L10/K10 | N10: Minor recipe drift — within SPC control | O10: SPC limits tightened; no action required
A11: EQ-005 | B11: SCARA Robot — Brooks (x6) | C11: Jul-2025 | D11: 0.935 | E11: 0.985 | F11: 0.999 | G11: =D11*E11*F11 | H11: N/A | I11: 0.956 | J11: N/A | K11: 62800 | L11: 63 | M11: =L11/K11 | N11: Isolated pick error — Wrist B calibration | O11: Calibration corrected; all 6 robots re-verified
A12: EQ-005 | B12: SCARA Robot — Brooks (x6) | C12: Aug-2025 | D12: 0.945 | E12: 0.99 | F12: 1 | G12: =D12*E12*F12 | H12: N/A | I12: 0.971 | J12: N/A | K12: 66200 | L12: 0 | M12: =L12/K12 | N12: None — zero defects this period | O12: No action required
A13: EQ-005 | B13: SCARA Robot — Brooks (x6) | C13: Sep-2025 | D13: 0.94 | E13: 0.99 | F13: 1 | G13: =D13*E13*F13 | H13: N/A | I13: 0.967 | J13: N/A | K13: 67100 | L13: 0 | M13: =L13/K13 | N13: None | O13: No action required
A14: EQ-014 | B14: RTP — Applied Materials (x2) | C14: Jul-2025 | D14: 0.93 | E14: 0.975 | F14: 0.983 | G14: =D14*E14*F14 | H14: 0.96 | I14: 0.959 | J14: =I14-H14 | K14: 8900 | L14: 107 | M14: =L14/K14 | N14: Edge ring thermal non-uniformity — pre-ECO-003 | O14: ECO-003 CVD SiC edge ring replacement — resolved
A15: EQ-014 | B15: RTP — Applied Materials (x2) | C15: Aug-2025 | D15: 0.935 | E15: 0.98 | F15: 0.991 | G15: =D15*E15*F15 | H15: 0.96 | I15: 0.971 | J15: =I15-H15 | K15: 9200 | L15: 56 | M15: =L15/K15 | N15: Below spec — none; edge exclusion improved | O15: ECO-003 effective; no action required
A16: EQ-014 | B16: RTP — Applied Materials (x2) | C16: Sep-2025 | D16: 0.94 | E16: 0.98 | F16: 0.993 | G16: =D16*E16*F16 | H16: 0.96 | I16: 0.973 | J16: =I16-H16 | K16: 9450 | L16: 47 | M16: =L16/K16 | N16: Within spec — lamp uniformity nominal | O16: AMAT lamp performance meeting spec; no action
A19: PROGRAM OEE SUMMARY
A20: OEE Target (Avail 92% x Perf 97% x Quality 96%) | B20: =0.92*0.97*0.96
A21: Average Actual OEE (Process Tools, Q3-2025) | B21: =AVERAGE(G5:G16)
A22: Yield Target (S01 Assumptions) | B22: 0.96
A23: Average Actual Yield (Q3-2025) | B23: =AVERAGE(I5:I16)
A24: Tools Below OEE Target this Period | B24: =COUNTIF(G5:G16,"<"&0.92*0.97*0.96)
A25: Total Units Produced (Q3-2025) | B25: =SUM(K5:K16)
A26: Total Units Scrapped (Q3-2025) | B26: =SUM(L5:L16)

Sheet S29_Equipment_ROI_Tracker
A1: S29 — Equipment ROI & Performance Tracker — Actual vs Plan (Post-Commissioning)
A2: Program: Greenfield Expansion Phase II | Populated after G5 Production Release | 30-day / 90-day / 180-day checkpoints | Actual inputs in BLUE | Variances auto-calculated | Planned values pulled from S02 (throughput/uptime) and S10 (capacity model)
A4: Equipment ID | B4: Equipment / Tool | C4: Planned Throughput (u/hr) | D4: Actual Throughput (u/hr) | E4: Throughput Variance | F4: Planned Uptime % | G4: Actual Uptime % | H4: Uptime Variance | I4: Planned Annual Energy Cost | J4: Actual Annual Energy Cost | K4: Checkpoint | L4: Status | M4: Notes
A5: EQ-003 | B5: Tube Furnace — Thermco | C5: 24 | D5: 23 | E5: =D5-C5 | F5: 0.92 | G5: 0.905 | H5: =G5-F5 | I5: 86944 | J5: Pending | K5: 30-Day | L5: IN PROGRESS | M5: Monitor zone temperature uniformity; recipe 3 showing 0.3% yield below target
A6: EQ-004 | B6: Batch Oxidation Furnace — TEL | C6: 18 | D6: 18 | E6: =D6-C6 | F6: 0.92 | G6: 0.91 | H6: =G6-F6 | I6: 100672 | J6: Pending | K6: 30-Day | L6: IN PROGRESS | M6: TEL FSE reviewing batch loading algorithm; minor throughput shortfall under investigation
A7: EQ-005 | B7: SCARA Robot — Brooks (x6) | C7: 120 | D7: 118 | E7: =D7-C7 | F7: 0.92 | G7: 0.935 | H7: =G7-F7 | I7: 3844 | J7: Pending | K7: 30-Day | L7: ABOVE PLAN | M7: Robot uptime exceeding plan. MES integration performing well. No action required.
A8: EQ-014 | B8: RTP — Applied Materials (x2) | C8: 32 | D8: 32 | E8: =D8-C8 | F8: 0.92 | G8: 0.93 | H8: =G8-F8 | I8: 77792 | J8: Pending | K8: 30-Day | L8: ABOVE PLAN | M8: Edge ring yield at 97.2% vs 96% target. Lamp array performing well. No action.
A9: EQ-001 | B9: Dry Screw Vacuum Pump (x4) | C9: N/A | D9: Pending | E9: — | F9: 0.92 | G9: 0.88 | H9: =G9-F9 | I9: 16931 | J9: Pending | K9: 90-Day | L9: BELOW PLAN | M9: Uptime below plan — bearing set replacement needed on pump 2. CR raised.
A10: EQ-002 | B10: Turbomolecular Pump — Pfeiffer (x3) | C10: N/A | D10: Pending | E10: — | F10: 0.92 | G10: Pending | H10: — | I10: 10982 | J10: Pending | K10: 90-Day | L10: PENDING | M10: 90-day checkpoint pending. Safety stock in place.
A11: EQ-006 | B11: Overhead Conveyor — Daifuku | C11: N/A | D11: Pending | E11: — | F11: 0.92 | G11: Pending | H11: — | I11: 20134 | J11: Pending | K11: 90-Day | L11: PENDING | M11: Track system performing nominally. Wi-Fi integration stable. No issues to date.
A12: EQ-007 | B12: Gas Handling Cabinet — Air Liquide (x4) | C12: N/A | D12: Pending | E12: — | F12: 0.92 | G12: Pending | H12: — | I12: 732 | J12: Pending | K12: 90-Day | L12: PENDING | M12: Gas cabinet operational. MFC calibration rotation in schedule. No events.
A13: EQ-009 | B13: DCS — Siemens S7-1500 (x5) | C13: N/A | D13: Pending | E13: — | F13: 0.92 | G13: Pending | H13: — | I13: 1098 | J13: Pending | K13: 180-Day | L13: PENDING | M13: DCS fully operational. Cybersecurity audit scheduled Month 4.
A14: EQ-011 | B14: Dry-Type Transformer (x2) | C14: N/A | D14: Pending | E14: — | F14: 0.99 | G14: Pending | H14: — | I14: 0 | J14: Pending | K14: 180-Day | L14: PENDING | M14: Transformer operating within thermal limits. Cooling fans checked. No issues.
A15: EQ-012 | B15: Process Chiller — Daikin (x3) | C15: N/A | D15: Pending | E15: — | F15: 0.99 | G15: Pending | H15: — | I15: 65525 | J15: Pending | K15: 180-Day | L15: PENDING | M15: Glycol loop stable. Compressor discharge pressure nominal. 180-day checkpoint due.
A16: EQ-015 | B16: AMR Fleet — MiR (x10) | C16: N/A | D16: Pending | E16: — | F16: 0.92 | G16: Pending | H16: — | I16: 5491 | J16: Pending | K16: 180-Day | L16: PENDING | M16: Fleet routing optimisation Phase 2 scheduled Month 5. Battery health nominal.
A19: POST-COMMISSIONING PERFORMANCE SUMMARY
A20: Equipment Platforms Tracked | B20: =COUNTA(A5:A16)
A21: Platforms with 30-Day Data | B21: =COUNTIF(K5:K16,"30-Day")
A22: Platforms Above or On Plan | B22: =COUNTIF(L5:L16,"ABOVE PLAN")
A23: Platforms Below Plan | B23: =COUNTIF(L5:L16,"BELOW PLAN")
A24: Platforms Pending Data | B24: =COUNTIF(L5:L16,"PENDING")

Sheet S30_Executive_Dashboard
A1: S30 — CAPEX PROGRAM EXECUTIVE DASHBOARD
A2: Program: Greenfield Expansion Phase II · Program Manager: Sourabh Tarodekar · AR Reference: AR-2025-0082 · Status as of: 2025-Q3 · All values linked live from program model sheets (S01-S32)
A4: KEY PERFORMANCE INDICATORS — PROGRAM SNAPSHOT
A5: TOTAL CAPEX PORTFOLIO | C5: APPROVED PROGRAM BUDGET | E5: 10-YR NPV (vs Min-CapEx) | G5: ESTIMATED IRR | I5: ANNUAL ENERGY COST
A6: ='S02_Equipment_Portfolio'!B25 | C6: ='S12_AR_Summary'!F27 | E6: ='S12_AR_Summary'!B33 | G6: ='S12_AR_Summary'!B34 | I6: ='S02_Equipment_Portfolio'!Q20
A7: Equipment + Installation (USD) | C7: Incl. contingency + FX reserve (USD) | E7: Scenario B vs A — 8% WACC (USD) | G7: 10-yr, vs 8.0% hurdle rate | I7: Full portfolio (USD/yr)
A9: ANNUAL PRODUCTION CAPACITY | C9: BASELINE UTILIZATION | E9: SUPPLY CHAIN RISK INDEX | G9: PROGRAM % COMPLETE | I9: OPEN PROGRAM BLOCKERS
A10: ='S10_Capacity_Planning'!B31 | C10: =750000/'S10_Capacity_Planning'!B31 | E10: ='S03_Supplier_Dataset'!B26 | G10: ='S25_Milestone_Gate_Tracker'!B44 | I10: ='S25_Milestone_Gate_Tracker'!B46
A11: Process tools (units/yr) | C11: Baseline Demand / Capacity | E11: Avg Composite Risk Score | G11: Avg milestone completion | I11: Across all gates
A14: CAPEX & FINANCIAL METRICS | F14: SUPPLY CHAIN & SUPPLIER RISK
A15: Metric | B15: Value | C15: Source Sheet | F15: Metric | G15: Value | H15: Source Sheet
A16: Total Equipment Purchase Cost | B16: ='S02_Equipment_Portfolio'!I20 | D16: S02_Equipment_Portfolio | F16: Avg Supplier Lead Time (wks) | G16: ='S03_Supplier_Dataset'!B23 | I16: S03 — Current market avg
A17: Total Installation Cost | B17: ='S02_Equipment_Portfolio'!K20 | D17: S02_Equipment_Portfolio | F17: Avg Lead Time Delta vs Standard (wks) | G17: ='S03_Supplier_Dataset'!B24 | I17: S03 — Market vs standard LT
A18: Total CapEx (Equip + Install) | B18: ='S02_Equipment_Portfolio'!B25 | D18: S02 — Formula | F18: Avg Supplier Reliability Score | G18: ='S03_Supplier_Dataset'!B25 | I18: S03 — 100-point scale
A19: Contingency Reserve (10%) | B19: ='S12_AR_Summary'!F24 | D19: S12_AR_Summary | F19: Avg Composite Risk Score | G19: ='S03_Supplier_Dataset'!B26 | I19: S03 — Risk Score formula
A20: FX Hedge Reserve | B20: ='S12_AR_Summary'!F25 | D20: S12_AR_Summary | F20: Max Risk Score (Worst Supplier) | G20: ='S03_Supplier_Dataset'!B27 | I20: S03 — Highest risk item
A21: NRE + Program Management | B21: ='S12_AR_Summary'!F26 | D21: S12_AR_Summary | F21: Single-Source Components | G21: ='S03_Supplier_Dataset'!B28 | I21: S03 — RED flag items
A22: TOTAL APPROVED BUDGET | B22: ='S12_AR_Summary'!F27 | D22: S12_AR_Summary | F22: HIGH Risk Tier Suppliers | G22: ='S03_Supplier_Dataset'!B30 | I22: S03 — Weekly exec review
A23: 10-Yr NPV vs Min-CapEx (Sc B-A) | B23: ='S12_AR_Summary'!B33 | D23: S13_Scenario_Analysis | F23: CRITICAL Risk Items (S16 model) | G23: =COUNTIF('S16_Supply_Chain_Risk'!J5:'S16_Supply_Chain_Risk'!J23,"CRITICAL") | I23: S16 — Escalated items
A24: Estimated IRR (10-yr) | B24: ='S12_AR_Summary'!B34 | D24: S13_Scenario_Analysis | F24: HIGH Risk Items (S16 model) | G24: =COUNTIF('S16_Supply_Chain_Risk'!J5:'S16_Supply_Chain_Risk'!J23,"HIGH") | I24: S16 — Senior mgr review
A25: Payback Period (yrs) | B25: 4.2 | D25: S13_Scenario_Analysis | F25: Components with Buffer Stock | G25: =COUNTIF('S16_Supply_Chain_Risk'!L5:'S16_Supply_Chain_Risk'!L23,"Yes") | I25: S16 — In-stock safety items
A27: CAPACITY & EQUIPMENT PERFORMANCE | F27: PROGRAM SCHEDULE & CONTROL
A28: Metric | B28: Value | C28: Source Sheet | F28: Metric | G28: Value | H28: Source Sheet
A29: Total Equipment Platforms | B29: ='S02_Equipment_Portfolio'!B27 | D29: S02 — Full portfolio | F29: Critical Path Duration (weeks) | G29: =MAX('S07_CPM_Master_Schedule'!H5:'S07_CPM_Master_Schedule'!H43) | I29: S07 — Max EF
A30: Annual Production Capacity | B30: ='S10_Capacity_Planning'!B31 | D30: S10 — Process tools only | F30: Critical Path Items | G30: =COUNTIF('S07_CPM_Master_Schedule'!L5:'S07_CPM_Master_Schedule'!L43,0) | I30: S07 — Zero float items
A31: Baseline Demand | B31: 750000 | D31: S11 — Current program target | F31: HIGH/CRITICAL Risk Deploy. Items | G31: =COUNTIF('S09_Deployment_Timeline'!P5:'S09_Deployment_Timeline'!P19,"HIGH")+COUNTIF('S09_Deployment_Timeline'!P5:'S09_Deployment_Timeline'!P19,"CRITICAL") | I31: S09 — Risk-flagged equip.
A32: Baseline Utilization | B32: =750000/'S10_Capacity_Planning'!B31 | D32: S10 — Demand / Capacity | F32: Total Milestones | G32: =COUNTA('S25_Milestone_Gate_Tracker'!A16:'S25_Milestone_Gate_Tracker'!A36) | I32: S25 — Full program scope
A33: Capacity Cushion (units/yr) | B33: ='S10_Capacity_Planning'!B33 | D33: S10 — Headroom above demand | F33: Milestones Complete | G33: =COUNTIF('S25_Milestone_Gate_Tracker'!I16:'S25_Milestone_Gate_Tracker'!I36,"COMPLETE") | I33: S25 — Formally closed
A34: Surge Demand Scenario (+20%) | B34: 900000 | D34: S11 — Stress test | F34: Milestones At Risk or Blocked | G34: ='S25_Milestone_Gate_Tracker'!B43 | I34: S25 — Require PM action
A35: Annual Energy Cost (all equip.) | B35: ='S02_Equipment_Portfolio'!Q20 | D35: S02 — Formula linked | F35: Gates Formally Approved | G35: ='S25_Milestone_Gate_Tracker'!B45 | I35: S25 — G0-G5 gates
A36: Total Spare Parts Inventory Value | B36: $124,200 | D36: S23 — Stock x unit cost | F36: Open Blockers Across All Gates | G36: ='S25_Milestone_Gate_Tracker'!B46 | I36: S25 — Must = 0 before gate
A38: PROGRAM HEALTH SCORECARD
A39: Health Dimension | B39: Current Value | C39: Target / Threshold | D39: RAG Status | E39: Action Required
A40: Budget Control | B40: 0.058 | C40: <50% contingency used | D40: AMBER | E40: Monitor change requests; contingency intact at ~5.8% used
A41: CapEx Financial Return (NPV) | B41: ='S12_AR_Summary'!B33 | C41: >$5M NPV vs Min-CapEx | D41: GREEN | E41: No action — Scenario B NPV confirmed by Finance model
A42: Supply Chain Risk | B42: ='S03_Supplier_Dataset'!B26 | C42: Avg Risk Score < 10 | D42: AMBER | E42: EQ-002 Pfeiffer single-source CRITICAL — alt vendor qual underway; escalate weekly
A43: Schedule / Critical Path | B43: =COUNTIF('S07_CPM_Master_Schedule'!L5:'S07_CPM_Master_Schedule'!L43,0) | C43: <2 zero-float items | D43: RED | E43: Multiple items with zero float; daily PM tracking required
A44: Capacity Headroom | B44: =750000/'S10_Capacity_Planning'!B31 | C44: Utilization < 90% | D44: GREEN | E44: Baseline utilization well below threshold; adequate headroom
A45: Program Milestone Progress | B45: ='S25_Milestone_Gate_Tracker'!B44 | C45: >30% complete by Wk 10 | D45: AMBER | E45: Milestones at risk require PM attention; others tracking to plan
A46: Yield / OEE Performance | B46: ='S28_Yield_Production_Metrics'!B21 | C46: OEE >= ~86% target | D46: GREEN | E46: Process tools performing at or above OEE target
A48: CapEx Program Management Model · All KPIs linked live from S01-S32 · Model prepared by: Sourabh Tarodekar, Program Manager · Workbook contains 33 sheets across 6 zones, 15 equipment platforms · For Finance / Engineering Leadership use only · CONFIDENTIAL

Sheet S31_Vendor_Scorecard
A1: S31 — Vendor Scorecard & Qualification Status — CapEx Equipment Suppliers
A2: Scores suppliers on delivery, quality, commercial, technical, and support dimensions | Qualification stage tracks RFI -> RFQ -> AVL (Approved Vendor List) | Inputs in BLUE
A4: SCORING DIMENSION WEIGHTS
A5: Dimension | B5: Weight | C5: Description
A6: Delivery Performance (On-Time %) | B6: 0.25 | C6: Historical on-time delivery rate vs committed dates
A7: Quality (Defect Rate / FAT Pass Rate) | B7: 0.2 | C7: First-pass FAT acceptance rate; incoming inspection defect rate
A8: Commercial (Pricing Competitiveness) | B8: 0.2 | C8: Benchmark vs market; responsiveness; payment terms
A9: Technical Capability (Spec Compliance) | B9: 0.25 | C9: Meets or exceeds technical specification; engineering support quality
A10: Program Support (Communication / PM) | B10: 0.1 | C10: Responsiveness; dedicated PM; escalation handling
A12: SUPPLIER SCORECARD & QUALIFICATION MATRIX
A13: Supplier | B13: Equip Ref | C13: Region | D13: Qual Stage | E13: Delivery (1-5) | F13: Quality (1-5) | G13: Commercial (1-5) | H13: Technical (1-5) | I13: Program Support (1-5) | J13: Composite Weighted Score | K13: Supplier Status | L13: Last Audit Date | M13: Next Review Date | N13: Qualification Notes
A14: Edwards Vacuum | B14: EQ-001 | C14: UK | D14: AVL — Approved | E14: 4 | F14: 4 | G14: 3 | H14: 4 | I14: 4 | J14: =0.25*E14+0.2*F14+0.2*G14+0.25*H14+0.1*I14 | K14: APPROVED | L14: 2025-Q1 | M14: 2025-Q3 | N14: Reliable supplier; post-Brexit logistics occasionally impacts lead time; alt-vendor qual complete
A15: Pfeiffer Vacuum | B15: EQ-002 | C15: DE | D15: AVL — Conditional | E15: 3 | F15: 5 | G15: 3 | H15: 5 | I15: 3 | J15: =0.25*E15+0.2*F15+0.2*G15+0.25*H15+0.1*I15 | K15: CONDITIONAL | L15: 2024-Q3 | M15: 2025-Q2 | N15: Single-source; HIGH supply risk. Conditional approval pending Shimadzu alt qualification.
A16: Thermco Systems | B16: EQ-003 | C16: USA | D16: AVL — Preferred | E16: 5 | F16: 5 | G16: 4 | H16: 5 | I16: 5 | J16: =0.25*E16+0.2*F16+0.2*G16+0.25*H16+0.1*I16 | K16: PREFERRED | L16: 2024-Q4 | M16: 2025-Q4 | N16: Best-in-class performance; strong PM support; BTU validated as alt; no concerns
A17: Tokyo Electron Ltd (TEL) | B17: EQ-004 | C17: JP | D17: AVL — Preferred | E17: 4 | F17: 5 | G17: 3 | H17: 5 | I17: 4 | J17: =0.25*E17+0.2*F17+0.2*G17+0.25*H17+0.1*I17 | K17: PREFERRED | L17: 2024-Q3 | M17: 2025-Q3 | N17: Premium supplier; higher commercial cost justified by TCO model; JPY FX hedged
A18: Brooks Automation | B18: EQ-005 | C18: USA | D18: AVL — Approved | E18: 4 | F18: 4 | G18: 4 | H18: 4 | I18: 4 | J18: =0.25*E18+0.2*F18+0.2*G18+0.25*H18+0.1*I18 | K18: APPROVED | L18: 2025-Q1 | M18: 2025-Q3 | N18: Strong delivery and quality; MES integration complexity is program risk not supplier risk
A19: Daifuku | B19: EQ-006 | C19: JP | D19: AVL — Conditional | E19: 3 | F19: 4 | G19: 3 | H19: 4 | I19: 3 | J19: =0.25*E19+0.2*F19+0.2*G19+0.25*H19+0.1*I19 | K19: CONDITIONAL | L19: 2024-Q4 | M19: 2025-Q2 | N19: Single-source for overhead track; commercial score impacted by $85K change order risk
A20: Air Liquide Engineering | B20: EQ-007 | C20: FR | D20: Qualification In Progress | E20: 3 | F20: 3 | G20: 3 | H20: 4 | I20: 3 | J20: =0.25*E20+0.2*F20+0.2*G20+0.25*H20+0.1*I20 | K20: IN QUALIFICATION | L20: N/A | M20: 2025-Q2 | N20: Quote still under negotiation; hazmat permit risk reduces score; full audit scheduled Q2
A21: Linde Engineering | B21: EQ-008 | C21: DE | D21: AVL — Approved | E21: 4 | F21: 4 | G21: 4 | H21: 4 | I21: 4 | J21: =0.25*E21+0.2*F21+0.2*G21+0.25*H21+0.1*I21 | K21: APPROVED | L21: 2024-Q3 | M21: 2025-Q4 | N21: Strong supplier; existing site gas supply contract provides leverage
A22: Siemens AG | B22: EQ-009 | C22: DE | D22: AVL — Preferred | E22: 5 | F22: 5 | G22: 4 | H22: 5 | I22: 5 | J22: =0.25*E22+0.2*F22+0.2*G22+0.25*H22+0.1*I22 | K22: PREFERRED | L22: 2024-Q2 | M22: 2025-Q4 | N22: Strategic preferred supplier; highest reliability score in portfolio
A23: Inductive Automation | B23: EQ-010 | C23: USA | D23: AVL — Approved | E23: 5 | F23: 5 | G23: 5 | H23: 4 | I23: 4 | J23: =0.25*E23+0.2*F23+0.2*G23+0.25*H23+0.1*I23 | K23: APPROVED | L23: 2024-Q4 | M23: 2025-Q4 | N23: Software vendor; excellent support; low supply risk
A24: ABB Ltd | B24: EQ-011 | C24: CH | D24: AVL — Approved | E24: 4 | F24: 4 | G24: 4 | H24: 4 | I24: 4 | J24: =0.25*E24+0.2*F24+0.2*G24+0.25*H24+0.1*I24 | K24: APPROVED | L24: 2024-Q3 | M24: 2025-Q4 | N24: Established supplier; transformer lead time extended but within program tolerance
A25: Daikin Applied | B25: EQ-012 | C25: JP | D25: AVL — Approved | E25: 4 | F25: 4 | G25: 3 | H25: 4 | I25: 4 | J25: =0.25*E25+0.2*F25+0.2*G25+0.25*H25+0.1*I25 | K25: APPROVED | L25: 2024-Q4 | M25: 2025-Q3 | N25: Solid supplier; glycol loop interface must be finalized before FAT — see CR-012
... A28: Mobile Industrial Robots (MiR) | B28: EQ-015 | C28: DK | D28: AVL — Approved | E28: 4 | F28: 4 | G28: 4 | H28: 4 | I28: 3 | J28: =0.25*E28+0.2*F28+0.2*G28+0.25*H28+0.1*I28 | K28: APPROVED | L28: 2025-Q1 | M28: 2025-Q3 | N28: Strong fleet management platform; PM support slightly below average
A29: Shimadzu Corp (Alt EQ-002) | B29: EQ-002 | C29: JP | D29: Qualification In Progress | E29: N/A | F29: N/A | G29: N/A | H29: 3 | I29: N/A | J29: — | K29: IN QUALIFICATION | L29: N/A | M29: 2025-Q3 | N29: Initiated as alt to Pfeiffer per CR-007; TMP-3203L under technical evaluation; 90-day qual program
A30: BTU International (Alt EQ-003) | B30: EQ-003 | C30: USA | D30: AVL — Approved | E30: 4 | F30: 4 | G30: 4 | H30: 4 | I30: 4 | J30: =0.25*E30+0.2*F30+0.2*G30+0.25*H30+0.1*I30 | K30: APPROVED | L30: 2024-Q2 | M30: 2025-Q4 | N30: Pre-qualified as secondary to Thermco; compatible process performance; available as backup
A31: Matheson Gas (Alt EQ-007) | B31: EQ-007 | C31: USA | D31: RFQ Issued | E31: N/A | F31: N/A | G31: 3 | H31: 3 | I31: N/A | J31: — | K31: MONITORING | L31: N/A | M31: 2025-Q2 | N31: RFQ issued as alternative to Air Liquide; pricing and delivery terms under review
A34: VENDOR QUALIFICATION SUMMARY
A35: Total Suppliers Tracked | B35: =COUNTA(A14:A31)
A36: Preferred Suppliers (AVL) | B36: =COUNTIF(K14:K31,"PREFERRED")
A37: Approved Suppliers (AVL) | B37: =COUNTIF(K14:K31,"APPROVED")
A38: Conditional / Monitoring | B38: =COUNTIF(K14:K31,"CONDITIONAL")+COUNTIF(K14:K31,"MONITORING")
A39: In Qualification | B39: =COUNTIF(K14:K31,"IN QUALIFICATION")
A40: Avg Composite Score (Active AVL) | B40: =AVERAGEIF(J14:J31,">0")

Sheet S32_Change_Tracker
A1: S32 — Engineering Change Management Tracker — CapEx Phase II Program
A2: All scope, technical, or budget changes must be logged here | Approved changes flow to AR update and decision log | Owner accountable for implementation
A4: Change ID | B4: Raised Date | C4: Equipment Ref | D4: Change Category | E4: Change Description | F4: Reason / Trigger | G4: Cost Impact (USD) | H4: Schedule Impact (wks) | I4: Quality/Tech Risk | J4: Raised By | K4: Approved By | L4: Change Status | M4: Implementation Notes
A5: CR-001 | B5: 2025-03-17 | C5: EQ-004 | D5: Installation Scope | E5: Add external 50-tonne crane hire and structural floor reinforcement for EQ-004 batch furnace installation | F5: Site walk revealed existing 3.5T facility crane is insufficient for 4,800 kg TEL furnace. Structural analysis confirmed floor reinforcement required. | G5: 62000 | H5: 1 | I5: LOW | J5: T. Okonkwo (Facilities) | K5: PM — Sourabh Tarodekar | L5: APPROVED — IMPLEMENTED | M5: Crane booked. Structural work complete Week 14. Cost added to EQ-004 install line item.
